Workbook

Sheet 揽收业务网点
A1: 有揽收业务的网点
A2: CGCM -CE | B2: CE
A3: DC MVF-RN | B3: CE
A4: F GYN 02-GO | B4: GP
A5: F APG - GO | B5: GP
A6: F RFI-DF | B6: GP
A7: F TRD-GO | B7: GP
A8: F PLN-DF | B8: GP
A9: PA MELI-SMR-SP | B9: SPS
A10: PA MELI-BRE-SP | B10: SPS
A11: PA VIA-SP | B11: SPS
A12: PA MANDAE-SP | B12: SPS
A13: PA SATELITAL-SP | B13: SPS
... A163: DC CDG-RJ | B163: RJ

Sheet 同场线路Rotas do mesmo SC
A1: 线路Rota
A2: H30-H235-0800-1
A3: H235-H30-0900-1
A4: H104-H204-0800-1
A5: H204-H104-1400-1
A6: S341-S402-0700-1
A7: S417-S401-0700-1
A8: S234-BRE-1800-1
A9: S414-S408-0700-1
A10: S175-S417-1800-1
A11: S175-S417-2000-2
A12: S061-BRE-2200-2
... A121: FEC-E362-0350-1

Sheet 支线运输综合报表
A1: Número do ID | B1: Status | C1: Nome da viagem | D1: Tipo de viagem | E1: Tipo de linha | F1: Saída do dia | G1: Quilometragem | H1: Placa do carro | I1: Modelo do veículo | J1: Nome completo do transportador | K1: Tipo de transportador | L1: Abreviatura de transportador | M1: Condutor | N1: Telefone do carro | O1: Código de estação de partida | P1: Nome de estação de partida | Q1: Regional de saída do carro | R1: Quantidade de encomendas escaneadas | S1: Número de " Pedido mãe" | T1: Tempo de início do carregamento | U1: Tempo de término do carregamento | V1: Tempo de carregamento (min) | W1: Horario de carregamento passou das 20:00 hs? | X1: hora de lacre | Y1: Tempo de partida planejada | Z1: Horário real de saída | AA1: Horário de check-out do codutor | AB1: Código de estação de chegada | AC1: Nome de estação de chegada | AD1: Regional de chegada do carro | AE1: Tempo de chegada planejado | AF1: Tempo real de chegada | AG1: Duração de atraso (min) | AH1: Horário de check-in do motorista | AI1: hora de deslacre | AJ1: Tempo de espera entre o check-in até o início do descarregamento (min) | AK1: Tempo de início de descarga | AL1: Tempo de término de descarga | AM1: Tempo de descarregamento (min) | AN1: Lacramento | AO1: Deslacramento | AP1: Chegada planejada | AQ1: Transferencia do mesmo SC, não necessita de caminhão | AR1: Determine o Ponto de Retira
A2: 任务单号 | B2: 任务状态Concluído | C2: 任务名称 | D2: 业务属性 | E2: 线路类型 | F2: 班次 | G2: 里程 | H2: 车牌号 | I2: 车型名称 | J2: 承运商全称 | K2: 承运商类型 | L2: 承运商简称 | M2: 司机 | N2: 随车电话 | O2: 发车网点编码 | P2: 发车网点名称 | Q2: 发车所属代理区 | R2: 装车扫描数量 | S2: 主单数量 | T2: 装车开始时间 | U2: 装车结束时间 | V2: 装车时长（min） | W2: 装车是否超过20H | X2: 封车时间 | Y2: 计划发车时间 | Z2: 实际发车时间 | AA2: 司机签出时间 | AB2: 到车网点编码 | AC2: 到车网点名称 | AD2: 到车所属代理区 | AE2: 计划到达时间 | AF2: 实际到达时间 | AG2: 迟到时长（min） | AH2: 司机打卡时间 | AI2: 解车时间 | AJ2: 卸车排队时长（min） | AK2: 卸车开始时间 | AL2: 卸车结束时间 | AM2: 卸车时长（min） | AN2: 封车Lacre | AO2: 解封Deslacre | AP2: 计划到达 | AQ2: 同场线路 | AR2: 判断揽收网点
A3: SRTR22605666051 | B3: Concluído：已完成 | C3: MAO1-C610-0700-1 | D3: Horário padrão | E3: Entrega | F3: 1 | G3: 500 | H3: JWP3563 | I3: 3/4 | J3: DARLISSON DANIEL MARQUES SOUSA | K3: Transportadora-三方 | L3: DARLISSON | M3: DARLISSON DANIEL MARQUES SOUSA | N3: 92985204417 | O3: 89202 | P3: DC MAO-AM | Q3: GP | R3: 409 | S3: 273 | T3: 2026-09-28 07:05:11 | U3: 2026-09-28 07:05:14 | V3: 1 | W3: Não | X3: 2026-09-28 07:05:36 | Y3: 2026-09-28 07:00:00 | Z3: 2026-09-28 07:05:36 | AA3: 2026-09-28 07:05:36 | AB3: 961564 | AC3: COA FLUVIAL-AM | AD3: GP | AE3: 2026-10-01 07:00:00 | AF3: 2026-10-01 07:31:35 | AG3: 32 | AH3: 2026-10-01 07:31:35 | AI3: 2026-10-02 07:11:10 | AJ3: 1422 | AK3: 2026-10-02 07:12:49 | AL3: 2026-10-02 10:34:23 | AM3: 202 | AN3: =IF(X3="",0,1) -> 1 | AO3: =IF(AI3="",0,1) -> 1 | AP3: =DATE(YEAR(AE3),MONTH(AE3),DAY(AE3)) -> 46296 | AQ3: =IF(COUNTIF('同场线路Rotas do mesmo SC'!A:A,C3)>0,"Sim","Não") -> Não | AR3: =IF(COUNTIF(揽收业务网点!A:A,P3)>0,"Sim","Não") -> Não
A4: SRTR22605673960 | B4: Concluído：已完成 | C4: JGS-F163-F136-F162-2200-1 | D4: Horário padrão | E4: Entrega | F4: 1 | G4: 180 | H4: JHX4C23 | I4: Truck | J4: RANYELLE SANTANA SILVA MARTINS | K4: Frota-自营 | L4: RVSSM | M4: ADRIANO ALEXANDRE DA SILVA | N4: 989851421 | O4: 781160 | P4: CPV 02-PB | Q4: CE | R4: 44 | S4: 41 | T4: 2026-09-30 05:27:16 | U4: 2026-09-30 05:40:51 | V4: 14 | W4: Não | X4: 2026-09-30 05:44:20 | Y4: 2026-10-01 03:30:00 | Z4: 2026-09-30 05:48:47 | AA4: 2026-09-30 05:48:47 | AB4: 883105 | AC4: PTS -PB | AD4: CE | AE4: 2026-10-01 07:30:00 | AF4: 2026-09-30 09:24:04 | AG4: -1325 | AH4: 2026-09-30 09:24:04 | AI4: 2026-09-30 09:32:04 | AJ4: 9 | AK4: 2026-09-30 09:32:18 | AL4: 2026-09-30 11:11:49 | AM4: 100 | AN4: =IF(X4="",0,1) -> 1 | AO4: =IF(AI4="",0,1) -> 1 | AP4: =DATE(YEAR(AE4),MONTH(AE4),DAY(AE4)) -> 46296 | AQ4: =IF(COUNTIF('同场线路Rotas do mesmo SC'!A:A,C4)>0,"Sim","Não") -> Não | AR4: =IF(COUNTIF(揽收业务网点!A:A,P4)>0,"Sim","Não") -> Não
A5: SRTR22605683400 | B5: Concluído：已完成 | C5: STM-C427-0500-1 | D5: Horário padrão | E5: Entrega | F5: 1 | G5: 264 | H5: OGT4E97 | I5: 3/4 | J5: SERGIO MANUEL LIMA DA SILVA | K5: Transportadora-三方 | L5: ATIVA T | M5: CARLOS ALBERTO DOS SANTOS NUNES JUNIOR | N5: 994640724 | O5: 89000 | P5: PA STM | Q5: GP | R5: 1398 | S5: 1014 | T5: 2026-09-28 20:36:18 | U5: 2026-09-28 20:45:26 | V5: 10 | W5: Não | X5: 2026-09-28 21:36:17 | Y5: 2026-09-29 05:00:00 | Z5: 2026-09-28 22:22:22 | AA5: 2026-09-28 22:22:22 | AB5: 961381 | AC5: F PRT -AM | AD5: GP | AE5: 2026-10-01 07:00:00 | AF5: 2026-10-01 06:29:51 | AG5: -30 | AH5: 2026-10-01 06:29:51 | AI5: 2026-10-01 06:31:40 | AJ5: 9 | AK5: 2026-10-01 06:38:11 | AL5: 2026-10-01 07:42:56 | AM5: 65 | AN5: =IF(X5="",0,1) -> 1 | AO5: =IF(AI5="",0,1) -> 1 | AP5: =DATE(YEAR(AE5),MONTH(AE5),DAY(AE5)) -> 46296 | AQ5: =IF(COUNTIF('同场线路Rotas do mesmo SC'!A:A,C5)>0,"Sim","Não") -> Não | AR5: =IF(COUNTIF(揽收业务网点!A:A,P5)>0,"Sim","Não") -> Não
A6: SRTR22605687811 | B6: Concluído：已完成 | C6: ANA-C537-0600-1 | D6: Horário padrão | E6: Entrega | F6: 1 | G6: 800 | H6: TWF0F29 | I6: Barco | J6: SAO DOMINGOS NAVEGACAO LTDA | K6: Transportadora-三方 | L6: SD | M6: VALDIR VIEIRA CORREA JUNIOR | N6: 91985099819 | O6: 89101 | P6: PA ANA | Q6: GP | R6: 2689 | S6: 1375 | T6: 2026-09-28 08:53:13 | U6: 2026-09-28 21:56:30 | V6: 784 | W6: Não | X6: 2026-09-29 02:41:13 | Y6: 2026-09-29 06:00:00 | Z6: 2026-09-29 03:48:41 | AA6: 2026-09-29 03:48:41 | AB6: 961491 | AC6: F BRV 02 -PA | AD6: GP | AE6: 2026-10-01 07:00:00 | AF6: 2026-09-30 09:51:46 | AG6: -1268 | AH6: 2026-09-30 09:51:46 | AI6: 2026-09-30 09:58:27 | AJ6: 9 | AK6: 2026-09-30 10:00:30 | AL6: 2026-09-30 11:13:04 | AM6: 73 | AN6: =IF(X6="",0,1) -> 1 | AO6: =IF(AI6="",0,1) -> 1 | AP6: =DATE(YEAR(AE6),MONTH(AE6),DAY(AE6)) -> 46296 | AQ6: =IF(COUNTIF('同场线路Rotas do mesmo SC'!A:A,C6)>0,"Sim","Não") -> Não | AR6: =IF(COUNTIF(揽收业务网点!A:A,P6)>0,"Sim","Não") -> Não
A7: SRTR22605691320 | B7: Concluído：已完成 | C7: ANA-C492-0600-1 | D7: Horário padrão | E7: Entrega | F7: 1 | G7: 800 | H7: 0937799 | I7: Barco | J7: NAVEGACAO OLIVEIRA LTDA | K7: Transportadora-三方 | L7: ANAMARQUES | M7: ALANA OLIVEIRA DO NASCIMENTO | N7: 96991413173 | O7: 89101 | P7: PA ANA | Q7: GP | R7: 332 | S7: 324 | T7: 2026-09-28 08:59:37 | U7: 2026-09-29 02:01:17 | V7: 1022 | W7: Não | X7: 2026-09-29 02:10:48 | Y7: 2026-09-29 06:00:00 | Z7: 2026-09-29 03:48:28 | AA7: 2026-09-29 03:48:28 | AB7: 961446 | AC7: LRJ-AP | AD7: GP | AE7: 2026-10-01 10:00:00 | AF7: 2026-09-30 22:07:16 | AG7: -712 | AH7: 2026-09-30 22:07:16 | AI7: 2026-10-02 14:35:44 | AJ7: 2433 | AK7: 2026-10-02 14:39:20 | AL7: 2026-10-03 08:08:26 | AM7: 1050 | AN7: =IF(X7="",0,1) -> 1 | AO7: =IF(AI7="",0,1) -> 1 | AP7: =DATE(YEAR(AE7),MONTH(AE7),DAY(AE7)) -> 46296 | AQ7: =IF(COUNTIF('同场线路Rotas do mesmo SC'!A:A,C7)>0,"Sim","Não") -> Não | AR7: =IF(COUNTIF(揽收业务网点!A:A,P7)>0,"Sim","Não") -> Não
A8: SRTR22605698631 | B8: Concluído：已完成 | C8: MAO1-C610-0700-1 | D8: Horário padrão | E8: Entrega | F8: 1 | G8: 500 | H8: JWP3563 | I8: 3/4 | J8: DARLISSON DANIEL MARQUES SOUSA | K8: Transportadora-三方 | L8: DARLISSON | M8: DARLISSON DANIEL MARQUES SOUSA | N8: 92985204417 | O8: 89202 | P8: DC MAO-AM | Q8: GP | R8: 399 | S8: 345 | T8: 2026-09-29 06:49:45 | U8: 2026-09-29 06:49:49 | V8: 1 | W8: Não | X8: 2026-09-29 06:54:11 | Y8: 2026-09-29 07:00:00 | Z8: 2026-09-29 06:54:39 | AA8: 2026-09-29 06:54:39 | AB8: 961564 | AC8: COA FLUVIAL-AM | AD8: GP | AE8: 2026-10-02 07:00:00 | AF8: 2026-10-01 07:30:26 | AG8: -1409 | AH8: 2026-10-01 07:30:26 | AI8: 2026-10-01 07:31:00 | AJ8: 4 | AK8: 2026-10-01 07:34:06 | AL8: 2026-10-01 09:52:24 | AM8: 139 | AN8: =IF(X8="",0,1) -> 1 | AO8: =IF(AI8="",0,1) -> 1 | AP8: =DATE(YEAR(AE8),MONTH(AE8),DAY(AE8)) -> 46297 | AQ8: =IF(COUNTIF('同场线路Rotas do mesmo SC'!A:A,C8)>0,"Sim","Não") -> Não | AR8: =IF(COUNTIF(揽收业务网点!A:A,P8)>0,"Sim","Não") -> Não
A9: SRTR22605702080 | B9: Concluído：已完成 | C9: THE-H206-H217-2200-1 | D9: Horário padrão | E9: Entrega | F9: 1 | G9: 375 | H9: QRZ0E84 | I9: Furgao | J9: AFA DE S OLIVEIRA TRANSPORTADO | K9: Transportadora-三方 | L9: ANDREIA | M9: WENDEL RIBEIRO | N9: 86998631695 | O9: 88601 | P9: PI THE | Q9: CE | R9: 2265 | S9: 1407 | T9: 2026-09-30 18:20:12 | U9: 2026-09-30 18:44:45 | V9: 25 | W9: Não | X9: 2026-09-30 20:30:38 | Y9: 2026-09-30 22:00:00 | Z9: 2026-09-30 20:54:53 | AA9: 2026-09-30 20:54:53 | AB9: 898114 | AC9: ITM -MA | AD9: CE | AE9: 2026-10-01 05:00:00 | AF9: 2026-10-01 03:29:21 | AG9: -90 | AH9: 2026-10-01 03:29:21 | AI9: 2026-10-01 03:32:54 | AJ9: 87 | AK9: 2026-10-01 04:56:06 | AL9: 2026-10-01 06:25:12 | AM9: 90 | AN9: =IF(X9="",0,1) -> 1 | AO9: =IF(AI9="",0,1) -> 1 | AP9: =DATE(YEAR(AE9),MONTH(AE9),DAY(AE9)) -> 46296 | AQ9: =IF(COUNTIF('同场线路Rotas do mesmo SC'!A:A,C9)>0,"Sim","Não") -> Não | AR9: =IF(COUNTIF(揽收业务网点!A:A,P9)>0,"Sim","Não") -> Não
A10: SRTR22605702091 | B10: Concluído：已完成 | C10: H104-H202-2000-1 | D10: Horário padrão | E10: Entrega | F10: 1 | G10: 391 | H10: RCJ5H28 | I10: Truck | J10: JOSIVAL FERREIRA DA SILVA | K10: Transportadora-三方 | L10: JOSIVAL FE | M10: EDINALDO OLIVEIRA DE LUCENA | N10: 99992241748 | O10: 899002 | P10: DC IMP-MA | Q10: CE | R10: 1564 | S10: 1333 | T10: 2026-09-30 15:19:39 | U10: 2026-09-30 15:27:20 | V10: 8 | W10: Não | X10: 2026-09-30 15:33:16 | Y10: 2026-09-30 20:00:00 | Z10: 2026-09-30 15:40:55 | AA10: 2026-09-30 15:40:55 | AB10: 899107 | AC10: BSS -MA | AD10: CE | AE10: 2026-10-01 04:00:00 | AF10: 2026-10-01 03:02:42 | AG10: -57 | AH10: 2026-10-01 03:02:42 | AI10: 2026-10-01 05:15:32 | AJ10: 143 | AK10: 2026-10-01 05:25:01 | AL10: 2026-10-01 08:39:46 | AM10: 195 | AN10: =IF(X10="",0,1) -> 1 | AO10: =IF(AI10="",0,1) -> 1 | AP10: =DATE(YEAR(AE10),MONTH(AE10),DAY(AE10)) -> 46296 | AQ10: =IF(COUNTIF('同场线路Rotas do mesmo SC'!A:A,C10)>0,"Sim","Não") -> Não | AR10: =IF(COUNTIF(揽收业务网点!A:A,P10)>0,"Sim","Não") -> Não
A11: SRTR22605702560 | B11: Concluído：已完成 | C11: RBR1-O03-O02-O04-1100-1 | D11: Horário padrão | E11: Entrega | F11: 1 | G11: 400 | H11: AWQ6F13 | I11: 3/4 | J11: FABIO FERREIRA DA SILVA | K11: Transportadora-三方 | L11: FABIO FER. | M11: TAC CARRO - FABIO FERREIRA DA SILVA | N11: 68999818172 | O11: 86802 | P11: DC RBR-AC | Q11: GP | R11: 6710 | S11: 3518 | T11: 2026-09-30 06:10:23 | U11: 2026-09-30 06:12:58 | V11: 3 | W11: Não | X11: 2026-09-30 06:15:34 | Y11: 2026-09-30 11:00:00 | Z11: 2026-09-30 06:15:19 | AA11: 2026-09-30 06:15:19 | AB11: 868101 | AC11: SMD -AC | AD11: GP | AE11: 2026-10-01 15:00:00 | AF11: 2026-10-01 01:00:00 | AG11: -840 | AH11: 2026-10-01 01:00:00 | AN11: =IF(X11="",0,1) -> 1 | AO11: =IF(AI11="",0,1) -> 0 | AP11: =DATE(YEAR(AE11),MONTH(AE11),DAY(AE11)) -> 46296 | AQ11: =IF(COUNTIF('同场线路Rotas do mesmo SC'!A:A,C11)>0,"Sim","Não") -> Não | AR11: =IF(COUNTIF(揽收业务网点!A:A,P11)>0,"Sim","Não") -> Não
A12: SRTR22605702680 | B12: Concluído：已完成 | C12: ANA-I269-0600-1 | D12: Horário padrão | E12: Entrega | F12: 1 | G12: 600 | H12: 0920411 | I12: Barco | J12: NV IRMAOS SANTANA /ANA BEATRIZ | K12: Transportadora-三方 | L12: AnaBEATRIZ | M12: ALANA OLIVEIRA DO NASCIMENTO | N12: 96991413173 | O12: 89101 | P12: PA ANA | Q12: GP | R12: 2906 | S12: 1267 | T12: 2026-09-29 09:24:08 | U12: 2026-09-30 02:34:55 | V12: 1031 | W12: Não | X12: 2026-09-30 04:16:31 | Y12: 2026-09-30 06:00:00 | Z12: 2026-09-30 04:28:11 | AA12: 2026-09-30 04:28:11 | AB12: 896104 | AC12: MCP FLUVIAL -AP | AD12: GP | AE12: 2026-10-01 23:59:00 | AF12: 2026-10-01 07:00:00 | AG12: -1019 | AH12: 2026-10-01 07:00:00 | AI12: 2026-10-01 20:36:04 | AJ12: 840 | AK12: 2026-10-01 20:59:26 | AL12: 2026-10-02 01:01:11 | AM12: 242 | AN12: =IF(X12="",0,1) -> 1 | AO12: =IF(AI12="",0,1) -> 1 | AP12: =DATE(YEAR(AE12),MONTH(AE12),DAY(AE12)) -> 46296 | AQ12: =IF(COUNTIF('同场线路Rotas do mesmo SC'!A:A,C12)>0,"Sim","Não") -> Não | AR12: =IF(COUNTIF(揽收业务网点!A:A,P12)>0,"Sim","Não") -> Não
A13: SRTR22605702851 | B13: Concluído：已完成 | C13: CGE-M119-1900-1 | D13: Horário padrão | E13: Entrega | F13: 1 | G13: 413 | H13: TZT7A69 | I13: Truck | J13: MGL TRASNPORTES E SERVIÇOS | K13: Transportadora-三方 | L13: MGL | M13: JOSE CARLOS SOUSA SILVA DE LIMA | N13: 38998845392 | O13: 53102 | P13: MG CGE | Q13: MG | R13: 11620 | S13: 11544 | T13: 2026-09-30 15:06:38 | U13: 2026-09-30 17:49:14 | V13: 163 | W13: Não | X13: 2026-09-30 18:00:03 | Y13: 2026-09-30 19:00:00 | Z13: 2026-09-30 18:01:28 | AA13: 2026-09-30 18:01:28 | AB13: 538001 | AC13: DC MTC-MG | AD13: MG | AE13: 2026-10-01 02:00:00 | AF13: 2026-10-01 00:42:48 | AG13: -77 | AH13: 2026-10-01 00:42:48 | AI13: 2026-10-01 00:49:49 | AJ13: 76 | AK13: 2026-10-01 01:58:37 | AL13: 2026-10-01 17:31:22 | AM13: 933 | AN13: =IF(X13="",0,1) -> 1 | AO13: =IF(AI13="",0,1) -> 1 | AP13: =DATE(YEAR(AE13),MONTH(AE13),DAY(AE13)) -> 46296 | AQ13: =IF(COUNTIF('同场线路Rotas do mesmo SC'!A:A,C13)>0,"Sim","Não") -> Não | AR13: =IF(COUNTIF(揽收业务网点!A:A,P13)>0,"Sim","Não") -> Não
A14: SRTR22605703260 | B14: Concluído：已完成 | C14: STM-I224-2300-1 | D14: Horário padrão | E14: Entrega | F14: 1 | G14: 225 | H14: TWS5B46 | I14: 3/4 | J14: ERICA RAIANA PINTO DA ROCHA | K14: Transportadora-三方 | L14: E. ROCHA | M14: LUIZ GUSTAVO PINTO PEREIRA | N14: 992147307 | O14: 89000 | P14: PA STM | Q14: GP | R14: 1070 | S14: 756 | T14: 2026-09-30 20:57:03 | U14: 2026-09-30 21:17:03 | V14: 21 | W14: Não | X14: 2026-09-30 22:29:33 | Y14: 2026-09-30 23:00:00 | Z14: 2026-09-30 22:35:10 | AA14: 2026-09-30 22:35:10 | AB14: 893107 | AC14: URA -PA | AD14: GP | AE14: 2026-10-01 06:00:00 | AF14: 2026-10-01 06:03:26 | AG14: 4 | AH14: 2026-10-01 06:03:26 | AI14: 2026-10-01 07:11:40 | AJ14: 65 | AK14: 2026-10-01 07:08:06 | AL14: 2026-10-01 08:57:43 | AM14: 110 | AN14: =IF(X14="",0,1) -> 1 | AO14: =IF(AI14="",0,1) -> 1 | AP14: =DATE(YEAR(AE14),MONTH(AE14),DAY(AE14)) -> 46296 | AQ14: =IF(COUNTIF('同场线路Rotas do mesmo SC'!A:A,C14)>0,"Sim","Não") -> Não | AR14: =IF(COUNTIF(揽收业务网点!A:A,P14)>0,"Sim","Não") -> Não
A15: SRTR22605703300 | B15: Concluído：已完成 | C15: S294-BRE-2330-1 | D15: Horário padrão | E15: Coleta | F15: 1 | G15: 104 | H15: ELQ5700 | I15: 3/4 | J15: CEOS EXPRESS | K15: Transportadora-三方 | L15: CEOS EXPRE | M15: JUAN JOSE GONZAGA SILVA | N15: 11954519066 | O15: 311200 | P15: PA PEGAKI-VCP-SP | Q15: SPS | R15: 1134 | S15: 1134 | T15: 2026-09-30 18:25:20 | U15: 2026-09-30 22:09:33 | V15: 225 | W15: Não | X15: 2026-09-30 22:16:21 | Y15: 2026-09-30 23:30:00 | Z15: 2026-09-30 19:23:16 | AA15: 2026-09-30 19:23:16 | AB15: 31101 | AC15: SP BRE | AD15: SPS | AE15: 2026-10-01 02:30:00 | AF15: 2026-10-01 00:27:33 | AG15: -122 | AH15: 2026-10-01 00:27:33 | AI15: 2026-10-01 00:36:17 | AJ15: 33 | AK15: 2026-10-01 00:59:36 | AL15: 2026-10-05 11:20:03 | AM15: 6381 | AN15: =IF(X15="",0,1) -> 1 | AO15: =IF(AI15="",0,1) -> 1 | AP15: =DATE(YEAR(AE15),MONTH(AE15),DAY(AE15)) -> 46296 | AQ15: =IF(COUNTIF('同场线路Rotas do mesmo SC'!A:A,C15)>0,"Sim","Não") -> Não | AR15: =IF(COUNTIF(揽收业务网点!A:A,P15)>0,"Sim","Não") -> Sim
A16: SRTR22605703640 | B16: Concluído：已完成 | C16: S343-RAO-2300-1 | D16: Horário padrão | E16: Coleta | F16: 1 | G16: 145 | H16: EFV8C09 | I16: Cavalo | J16: MULLER ENXOVAIS LTDA | K16: Transportadora-三方 | L16: MULLER ENX | M16: maycon lucas ferreira | N16: 16981876694 | O16: 316375 | P16: F IBG-SP | Q16: SPN | R16: 7808 | S16: 7808 | T16: 2026-09-30 14:14:21 | U16: 2026-09-30 17:14:00 | V16: 180 | W16: Não | X16: 2026-09-30 17:23:52 | Y16: 2026-09-30 23:00:00 | Z16: 2026-09-30 17:26:24 | AA16: 2026-09-30 17:26:24 | AB16: 31601 | AC16: SN RAO | AD16: SPN | AE16: 2026-10-01 01:40:00 | AF16: 2026-09-30 21:06:40 | AG16: -273 | AH16: 2026-09-30 21:06:40 | AI16: 2026-10-01 00:55:41 | AJ16: 231 | AK16: 2026-10-01 00:56:42 | AL16: 2026-10-01 05:59:36 | AM16: 303 | AN16: =IF(X16="",0,1) -> 1 | AO16: =IF(AI16="",0,1) -> 1 | AP16: =DATE(YEAR(AE16),MONTH(AE16),DAY(AE16)) -> 46296 | AQ16: =IF(COUNTIF('同场线路Rotas do mesmo SC'!A:A,C16)>0,"Sim","Não") -> Não | AR16: =IF(COUNTIF(揽收业务网点!A:A,P16)>0,"Sim","Não") -> Sim
A17: SRTR22605703760 | B17: Concluído：已完成 | C17: STM-I217-1900-1 | D17: Horário padrão | E17: Entrega | F17: 1 | G17: 370 | H17: QVL2J83 | I17: Truck | J17: S V DA ROCHA TRANSPORTES | K17: Transportadora-三方 | L17: EXPRES STM | M17: ERLISON RICARDO PINTO DA ROCHA | N17: 93991406800 | O17: 89000 | P17: PA STM | Q17: GP | R17: 1705 | S17: 1385 | T17: 2026-09-30 16:49:27 | U17: 2026-09-30 17:35:19 | V17: 46 | W17: Não | X17: 2026-09-30 17:53:31 | Y17: 2026-09-30 19:00:00 | Z17: 2026-09-30 17:56:19 | AA17: 2026-09-30 17:56:19 | AB17: 893104 | AC17: ITT -PA | AD17: GP | AE17: 2026-10-01 07:00:00 | AF17: 2026-10-01 05:53:13 | AG17: -66 | AH17: 2026-10-01 05:53:13 | AI17: 2026-10-01 08:50:23 | AJ17: 175 | AK17: 2026-10-01 08:47:44 | AL17: 2026-10-02 10:55:07 | AM17: 1568 | AN17: =IF(X17="",0,1) -> 1 | AO17: =IF(AI17="",0,1) -> 1 | AP17: =DATE(YEAR(AE17),MONTH(AE17),DAY(AE17)) -> 46296 | AQ17: =IF(COUNTIF('同场线路Rotas do mesmo SC'!A:A,C17)>0,"Sim","Não") -> Não | AR17: =IF(COUNTIF(揽收业务网点!A:A,P17)>0,"Sim","Não") -> Não
A18: SRTR22605703820 | B18: Concluído：已完成 | C18: JGS-F163-F136-F162-2200-1 | D18: Horário padrão | E18: Entrega | F18: 1 | G18: 214 | H18: NQA0D23 | I18: Toco | J18: RENNAM CABRAL DE OLIVEIRA | K18: Transportadora-三方 | L18: RENNAM TR | M18: RENNAM CABRAL DE OLIVEIRA | N18: 81985460015 | O18: 78101 | P18: PE JGS | Q18: CE | R18: 5872 | S18: 4858 | T18: 2026-09-30 14:04:00 | U18: 2026-09-30 21:45:38 | V18: 462 | W18: Não | X18: 2026-09-30 22:34:11 | Y18: 2026-09-30 22:00:00 | Z18: 2026-09-30 22:58:40 | AA18: 2026-09-30 22:58:40 | AB18: 883107 | AC18: CPV -PB | AD18: CE | AE18: 2026-10-01 03:30:00 | AF18: 2026-10-01 03:23:33 | AG18: -6 | AH18: 2026-10-01 03:23:33 | AI18: 2026-10-01 03:43:13 | AJ18: 171 | AK18: 2026-10-01 06:14:16 | AL18: 2026-10-02 06:27:21 | AM18: 1454 | AN18: =IF(X18="",0,1) -> 1 | AO18: =IF(AI18="",0,1) -> 1 | AP18: =DATE(YEAR(AE18),MONTH(AE18),DAY(AE18)) -> 46296 | AQ18: =IF(COUNTIF('同场线路Rotas do mesmo SC'!A:A,C18)>0,"Sim","Não") -> Não | AR18: =IF(COUNTIF(揽收业务网点!A:A,P18)>0,"Sim","Não") -> Não
A19: SRTR22605703820 | B19: Concluído：已完成 | C19: JGS-F163-F136-F162-2200-1 | D19: Horário padrão | E19: Entrega | F19: 1 | G19: 180 | H19: NQA0D23 | I19: Toco | J19: RENNAM CABRAL DE OLIVEIRA | K19: Transportadora-三方 | L19: RENNAM TR | M19: RENNAM CABRAL DE OLIVEIRA | N19: 81985460015 | O19: 781160 | P19: CPV 02-PB | Q19: CE | R19: 18 | S19: 18 | T19: 2026-10-01 05:38:54 | U19: 2026-10-01 05:38:54 | V19: 0 | W19: Não | X19: 2026-10-01 05:41:05 | Y19: 2026-10-02 04:00:00 | Z19: 2026-10-01 05:45:38 | AA19: 2026-10-01 05:45:38 | AB19: 883105 | AC19: PTS -PB | AD19: CE | AE19: 2026-10-02 08:00:00 | AF19: 2026-10-01 08:43:17 | AG19: -1396 | AH19: 2026-10-01 08:43:17 | AI19: 2026-10-01 08:51:13 | AJ19: 9 | AK19: 2026-10-01 08:52:06 | AL19: 2026-10-01 11:30:26 | AM19: 159 | AN19: =IF(X19="",0,1) -> 1 | AO19: =IF(AI19="",0,1) -> 1 | AP19: =DATE(YEAR(AE19),MONTH(AE19),DAY(AE19)) -> 46297 | AQ19: =IF(COUNTIF('同场线路Rotas do mesmo SC'!A:A,C19)>0,"Sim","Não") -> Não | AR19: =IF(COUNTIF(揽收业务网点!A:A,P19)>0,"Sim","Não") -> Não
A20: SRTR22605704071 | B20: Concluído：已完成 | C20: S236-BRE-2200-2 | D20: Horário padrão | E20: Coleta | F20: 2 | G20: 24 | H20: FSR4520 | I20: Truck | J20: DEBORA TRANSPORTES | K20: Transportadora-三方 | L20: DEB | M20: SILVIO DE ANDRADE | N20: 11971583378 | O20: 311111 | P20: PA MANDAE-SP | Q20: SPS | R20: 1848 | S20: 1848 | T20: 2026-09-30 20:01:13 | U20: 2026-09-30 21:35:18 | V20: 95 | W20: Não | X20: 2026-09-30 21:37:36 | Y20: 2026-09-30 22:00:00 | Z20: 2026-09-30 21:42:53 | AA20: 2026-09-30 21:42:53 | AB20: 31101 | AC20: SP BRE | AD20: SPS | AE20: 2026-10-01 00:00:00 | AF20: 2026-09-30 23:04:31 | AG20: -55 | AH20: 2026-09-30 23:04:31 | AI20: 2026-09-30 22:53:10 | AJ20: 3 | AK20: 2026-09-30 23:06:38 | AL20: 2026-10-03 05:43:50 | AM20: 3278 | AN20: =IF(X20="",0,1) -> 1 | AO20: =IF(AI20="",0,1) -> 1 | AP20: =DATE(YEAR(AE20),MONTH(AE20),DAY(AE20)) -> 46296 | AQ20: =IF(COUNTIF('同场线路Rotas do mesmo SC'!A:A,C20)>0,"Sim","Não") -> Não | AR20: =IF(COUNTIF(揽收业务网点!A:A,P20)>0,"Sim","Não") -> Sim
A21: SRTR22605704451 | B21: Concluído：已完成 | C21: FEC-E305-0200-1 | D21: Horário padrão | E21: Entrega | F21: 1 | G21: 103 | H21: NZQ6E08 | I21: Furgao | J21: RODO BELLA TRANSPORTE LTDA | K21: Transportadora-三方 | L21: RODOBELLA | M21: LEANDRO SANTANA DOS SANTOS | N21: 988678172 | O21: 77501 | P21: BA FEC | Q21: BA | R21: 1247 | S21: 1090 | T21: 2026-09-29 16:38:59 | U21: 2026-09-30 00:07:29 | V21: 449 | W21: Não | X21: 2026-09-30 00:13:04 | Y21: 2026-09-30 02:00:00 | Z21: 2026-09-30 00:20:04 | AA21: 2026-09-30 00:20:04 | AB21: 773124 | AC21: POLI-BA | AD21: BA | AE21: 2026-10-01 08:10:00 | AF21: 2026-09-30 05:17:29 | AG21: -1612 | AH21: 2026-09-30 05:17:29 | AI21: 2026-09-30 05:50:33 | AJ21: 41 | AK21: 2026-09-30 05:58:03 | AL21: 2026-09-30 07:20:34 | AM21: 83 | AN21: =IF(X21="",0,1) -> 1 | AO21: =IF(AI21="",0,1) -> 1 | AP21: =DATE(YEAR(AE21),MONTH(AE21),DAY(AE21)) -> 46296 | AQ21: =IF(COUNTIF('同场线路Rotas do mesmo SC'!A:A,C21)>0,"Sim","Não") -> Não | AR21: =IF(COUNTIF(揽收业务网点!A:A,P21)>0,"Sim","Não") -> Não
A22: SRTR22605704951 | B22: Concluído：已完成 | C22: STM-I272-2300-1 | D22: Horário padrão | E22: Entrega | F22: 1 | G22: 10 | H22: RXE7I39 | I22: 3/4 | J22: JET EXPRESS PA | K22: Frota-自营 | L22: JET PA | M22: EDIVALDO PIRES DE SOUZA | N22: 93992429221 | O22: 89000 | P22: PA STM | Q22: GP | R22: 495 | S22: 283 | T22: 2026-09-30 17:15:20 | U22: 2026-09-30 17:15:27 | V22: 1 | W22: Não | X22: 2026-09-30 17:20:02 | Y22: 2026-09-30 23:00:00 | Z22: 2026-09-30 17:22:25 | AA22: 2026-09-30 17:22:25 | AB22: 896105 | AC22: STM FLUVIAL -PA | AD22: GP | AE22: 2026-10-01 04:00:00 | AF22: 2026-09-30 17:22:34 | AG22: -637 | AH22: 2026-09-30 17:22:34 | AI22: 2026-09-30 17:23:40 | AJ22: 8 | AK22: 2026-09-30 17:29:45 | AL22: 2026-10-01 07:44:45 | AM22: 855 | AN22: =IF(X22="",0,1) -> 1 | AO22: =IF(AI22="",0,1) -> 1 | AP22: =DATE(YEAR(AE22),MONTH(AE22),DAY(AE22)) -> 46296 | AQ22: =IF(COUNTIF('同场线路Rotas do mesmo SC'!A:A,C22)>0,"Sim","Não") -> Não | AR22: =IF(COUNTIF(揽收业务网点!A:A,P22)>0,"Sim","Não") -> Não
A23: SRTR22605705220 | B23: Concluído：已完成 | C23: M209-BRE-2300-2 | D23: Horário padrão | E23: Coleta | F23: 2 | G23: 1 | H23: FCX7J05 | I23: Truck | J23: RHS TRANSPORTES E SERVIÇOS | K23: Transportadora-三方 | L23: RHS TRANS | M23: VALDECI ALVES DE OLIVEIRA JUNIOR | N23: 11932427923 | O23: 535104 | P23: EXT -MG | Q23: MG | R23: 7155 | S23: 6482 | T23: 2026-09-30 17:05:54 | U23: 2026-09-30 17:59:38 | V23: 54 | W23: Não | X23: 2026-09-30 18:04:04 | Y23: 2026-09-30 23:00:00 | Z23: 2026-09-30 17:01:24 | AA23: 2026-09-30 17:01:24 | AB23: 31101 | AC23: SP BRE | AD23: SPS | AE23: 2026-10-01 04:00:00 | AF23: 2026-09-30 21:06:02 | AG23: -413 | AH23: 2026-09-30 21:06:02 | AI23: 2026-09-30 23:07:45 | AJ23: 123 | AK23: 2026-09-30 23:08:33 | AL23: 2026-10-05 08:57:36 | AM23: 6350 | AN23: =IF(X23="",0,1) -> 1 | AO23: =IF(AI23="",0,1) -> 1 | AP23: =DATE(YEAR(AE23),MONTH(AE23),DAY(AE23)) -> 46296 | AQ23: =IF(COUNTIF('同场线路Rotas do mesmo SC'!A:A,C23)>0,"Sim","Não") -> Não | AR23: =IF(COUNTIF(揽收业务网点!A:A,P23)>0,"Sim","Não") -> Sim
... A26: SRTR22605706200 | B26: Concluído：已完成 | C26: M209-BRE-2203-4 | D26: Horário padrão | E26: Coleta | F26: 4 | G26: 132 | H26: DVT3F87 | I26: Truck | J26: WILIAN CARLOS DE OLIVEIRA | K26: Transportadora-三方 | L26: WILIAN | M26: diovani iran francisco da silva | N26: 3597327569 | O26: 535104 | P26: EXT -MG | Q26: MG | R26: 7022 | S26: 7021 | T26: 2026-09-30 19:10:40 | U26: 2026-09-30 22:00:02 | V26: 170 | W26: Não | X26: 2026-09-30 21:41:08 | Y26: 2026-09-30 22:03:00 | Z26: 2026-09-30 20:57:51 | AA26: 2026-09-30 20:57:51 | AB26: 31101 | AC26: SP BRE | AD26: SPS | AE26: 2026-10-01 00:33:00 | AF26: 2026-10-01 00:31:42 | AG26: -1 | AH26: 2026-10-01 00:31:42 | AI26: 2026-10-01 01:28:14 | AJ26: -86 | AK26: 2026-09-30 23:04:55 | AL26: 2026-10-03 04:32:15 | AM26: 3208 | AN26: =IF(X26="",0,1) -> 1 | AO26: =IF(AI26="",0,1) -> 1 | AP26: =DATE(YEAR(AE26),MONTH(AE26),DAY(AE26)) -> 46296 | AQ26: =IF(COUNTIF('同场线路Rotas do mesmo SC'!A:A,C26)>0,"Sim","Não") -> Não | AR26: =IF(COUNTIF(揽收业务网点!A:A,P26)>0,"Sim","Não") -> Sim
A27: SRTR22605706280 | B27: Concluído：已完成 | C27: P110-P235-1400-2 | D27: Horário padrão | E27: Entrega | F27: 2 | G27: 640 | H27: AWP1D85 | I27: VUC | J27: ESTEFANI RODRIGUES DE JESUS M | K27: Transportadora-三方 | L27: ESTEFANI R | M27: KLEBER LOPES DE LIMA | N27: 4499213179 | O27: 244002 | P27: DC MGF-PR | Q27: PR | R27: 693 | S27: 670 | T27: 2026-09-30 02:49:18 | U27: 2026-09-30 06:18:45 | V27: 210 | W27: Não | Y27: 2026-09-30 14:00:00 | Z27: 2026-09-30 06:18:45 | AA27: 2026-09-30 06:18:45 | AB27: 244003 | AC27: MGF-PR | AD27: PR | AE27: 2026-10-01 00:40:00 | AF27: 2026-09-30 05:16:34 | AG27: -1163 | AH27: 2026-09-30 05:16:34 | AJ27: 10 | AK27: 2026-09-30 05:26:34 | AL27: 2026-09-30 07:00:21 | AM27: 94 | AN27: =IF(X27="",0,1) -> 0 | AO27: =IF(AI27="",0,1) -> 0 | AP27: =DATE(YEAR(AE27),MONTH(AE27),DAY(AE27)) -> 46296 | AQ27: =IF(COUNTIF('同场线路Rotas do mesmo SC'!A:A,C27)>0,"Sim","Não") -> Não | AR27: =IF(COUNTIF(揽收业务网点!A:A,P27)>0,"Sim","Não") -> Não
A28: SRTR22605707011 | B28: Concluído：已完成 | C28: P244-SJS-2330-2 | D28: Horário padrão | E28: Coleta | F28: 2 | G28: 30 | H28: QIG5E10 | I28: 3/4 | J28: 29.370.448 ADMILSON JOSE DE | K28: Transportadora-三方 | L28: ADMILSON | M28: ADMILSON JOSE DE MORAIS | N28: 41984557890 | O28: 241117 | P28: SJS -PR | Q28: PR | R28: 14262 | S28: 14262 | T28: 2026-09-29 09:58:04 | U28: 2026-09-30 22:00:10 | V28: 2163 | W28: Sim | X28: 2026-09-30 04:54:10 | Y28: 2026-09-30 23:30:00 | Z28: 2026-09-30 04:21:59 | AA28: 2026-09-30 04:21:59 | AB28: 24101 | AC28: PR SJS | AD28: PR | AE28: 2026-10-01 01:00:00 | AF28: 2026-09-30 11:22:18 | AG28: -817 | AH28: 2026-09-30 11:22:18 | AJ28: -740 | AK28: 2026-09-29 23:01:49 | AL28: 2026-10-02 12:57:35 | AM28: 3716 | AN28: =IF(X28="",0,1) -> 1 | AO28: =IF(AI28="",0,1) -> 0 | AP28: =DATE(YEAR(AE28),MONTH(AE28),DAY(AE28)) -> 46296 | AQ28: =IF(COUNTIF('同场线路Rotas do mesmo SC'!A:A,C28)>0,"Sim","Não") -> Não | AR28: =IF(COUNTIF(揽收业务网点!A:A,P28)>0,"Sim","Não") -> Sim
A29: SRTR22605707220 | B29: Concluído：已完成 | C29: FEC-E213-0200-1 | D29: Horário padrão | E29: Entrega | F29: 1 | G29: 115 | H29: JRJ2B79 | I29: Furgao | J29: RODO BELLA TRANSPORTE LTDA | K29: Transportadora-三方 | L29: RODOBELLA | M29: MAURICIO DE FIGUEIREDO SILVA | N29: 991735004 | O29: 77501 | P29: BA FEC | Q29: BA | R29: 896 | S29: 773 | T29: 2026-09-29 16:41:11 | U29: 2026-09-29 21:56:17 | V29: 316 | W29: Não | X29: 2026-09-29 23:56:36 | Y29: 2026-09-30 02:00:00 | Z29: 2026-09-30 00:12:23 | AA29: 2026-09-30 00:12:23 | AB29: 771106 | AC29: SSA -BA | AD29: BA | AE29: 2026-10-01 06:50:00 | AF29: 2026-09-30 03:10:38 | AG29: -1659 | AH29: 2026-09-30 03:10:38 | AI29: 2026-09-30 06:02:17 | AJ29: 213 | AK29: 2026-09-30 06:43:30 | AL29: 2026-10-01 08:33:24 | AM29: 1550 | AN29: =IF(X29="",0,1) -> 1 | AO29: =IF(AI29="",0,1) -> 1 | AP29: =DATE(YEAR(AE29),MONTH(AE29),DAY(AE29)) -> 46296 | AQ29: =IF(COUNTIF('同场线路Rotas do mesmo SC'!A:A,C29)>0,"Sim","Não") -> Não | AR29: =IF(COUNTIF(揽收业务网点!A:A,P29)>0,"Sim","Não") -> Não
A30: SRTR22605707300 | B30: Concluído：已完成 | C30: A002-A212-A272-A221-A372-2310-1 | D30: Horário padrão | E30: Entrega | F30: 1 | G30: 240 | H30: IWG3B32 | I30: 3/4 | J30: GUILHERME HENRIQUE DE LIMA | K30: Transportadora-三方 | L30: GUILHERME | M30: GUILHERME HENRIQUE DE LIMA ROSA | N30: 51992695994 | O30: 154001 | P30: DC PFB-RS | Q30: PR | R30: 2321 | S30: 2307 | T30: 2026-09-30 00:01:31 | U30: 2026-09-30 00:05:47 | V30: 5 | W30: Não | X30: 2026-09-30 00:07:35 | Y30: 2026-09-30 23:10:00 | Z30: 2026-09-30 00:24:19 | AA30: 2026-09-30 00:24:19 | AB30: 155102 | AC30: IJU -RS | AD30: PR | AE30: 2026-10-01 03:10:00 | AF30: 2026-09-30 03:02:03 | AG30: -1447 | AH30: 2026-09-30 03:02:03 | AN30: =IF(X30="",0,1) -> 1 | AO30: =IF(AI30="",0,1) -> 0 | AP30: =DATE(YEAR(AE30),MONTH(AE30),DAY(AE30)) -> 46296 | AQ30: =IF(COUNTIF('同场线路Rotas do mesmo SC'!A:A,C30)>0,"Sim","Não") -> Não | AR30: =IF(COUNTIF(揽收业务网点!A:A,P30)>0,"Sim","Não") -> Não
A31: SRTR22605707300 | B31: Concluído：已完成 | C31: A002-A212-A272-A221-A372-2310-1 | D31: Horário padrão | E31: Entrega | F31: 1 | G31: 90 | H31: IWG3B32 | I31: 3/4 | J31: GUILHERME HENRIQUE DE LIMA | K31: Transportadora-三方 | L31: GUILHERME | M31: GUILHERME HENRIQUE DE LIMA ROSA | N31: 51992695994 | O31: 155119 | P31: F IJI-RS | Q31: PR | R31: 7 | S31: 7 | T31: 2026-09-29 17:47:08 | U31: 2026-09-29 17:47:31 | V31: 1 | W31: Não | X31: 2026-09-30 03:38:26 | Y31: 2026-10-01 04:30:00 | Z31: 2026-09-30 03:39:53 | AA31: 2026-09-30 03:39:53 | AB31: 155105 | AC31: STR -RS | AD31: PR | AE31: 2026-10-01 06:00:00 | AF31: 2026-09-30 05:04:22 | AG31: -1495 | AH31: 2026-09-30 05:04:22 | AI31: 2026-09-30 05:43:27 | AJ31: 133 | AK31: 2026-09-30 07:16:24 | AL31: 2026-09-30 08:09:44 | AM31: 54 | AN31: =IF(X31="",0,1) -> 1 | AO31: =IF(AI31="",0,1) -> 1 | AP31: =DATE(YEAR(AE31),MONTH(AE31),DAY(AE31)) -> 46296 | AQ31: =IF(COUNTIF('同场线路Rotas do mesmo SC'!A:A,C31)>0,"Sim","Não") -> Não | AR31: =IF(COUNTIF(揽收业务网点!A:A,P31)>0,"Sim","Não") -> Não
A32: SRTR22605707511 | B32: Concluído：已完成 | C32: THE-H203-1800-1 | D32: Horário padrão | E32: Entrega | F32: 1 | G32: 370 | H32: FUX5A91 | I32: Truck | J32: JET EXPRESS CE | K32: Frota-自营 | L32: JET CE | M32: SAVIO SILVA DE SOUSA | N32: 86981545029 | O32: 88601 | P32: PI THE | Q32: CE | R32: 7307 | S32: 4947 | T32: 2026-09-30 16:55:42 | U32: 2026-09-30 17:43:20 | V32: 48 | W32: Não | X32: 2026-09-30 17:48:10 | Y32: 2026-09-30 18:00:00 | Z32: 2026-09-30 17:54:12 | AA32: 2026-09-30 17:54:12 | AB32: 898111 | AC32: STN -MA | AD32: CE | AE32: 2026-10-01 01:15:00 | AF32: 2026-10-01 00:40:28 | AG32: -34 | AH32: 2026-10-01 00:40:28 | AI32: 2026-10-01 01:08:16 | AJ32: 43 | AK32: 2026-10-01 01:23:20 | AL32: 2026-10-02 10:29:01 | AM32: 1986 | AN32: =IF(X32="",0,1) -> 1 | AO32: =IF(AI32="",0,1) -> 1 | AP32: =DATE(YEAR(AE32),MONTH(AE32),DAY(AE32)) -> 46296 | AQ32: =IF(COUNTIF('同场线路Rotas do mesmo SC'!A:A,C32)>0,"Sim","Não") -> Não | AR32: =IF(COUNTIF(揽收业务网点!A:A,P32)>0,"Sim","Não") -> Não
A33: SRTR22605707660 | B33: Concluído：已完成 | C33: STM-C410-0500-1 | D33: Horário padrão | E33: Entrega | F33: 1 | G33: 205 | H33: OGT4E97 | I33: 3/4 | J33: SERGIO MANUEL LIMA DA SILVA | K33: Transportadora-三方 | L33: ATIVA T | M33: JAIMISON LIMA PEREIRA | N33: 999769763 | O33: 89000 | P33: PA STM | Q33: GP | R33: 448 | S33: 283 | T33: 2026-09-29 21:52:43 | U33: 2026-09-29 21:53:46 | V33: 2 | W33: Não | X33: 2026-09-29 22:02:13 | Y33: 2026-09-30 05:00:00 | Z33: 2026-09-29 22:31:14 | AA33: 2026-09-29 22:31:14 | AB33: 961364 | AC33: F JRT-PA | AD33: GP | AE33: 2026-10-01 08:00:00 | AF33: 2026-10-01 08:52:24 | AG33: 53 | AH33: 2026-10-01 08:52:24 | AI33: 2026-10-01 08:54:04 | AJ33: 8 | AK33: 2026-10-01 08:59:33 | AL33: 2026-10-01 11:25:06 | AM33: 146 | AN33: =IF(X33="",0,1) -> 1 | AO33: =IF(AI33="",0,1) -> 1 | AP33: =DATE(YEAR(AE33),MONTH(AE33),DAY(AE33)) -> 46296 | AQ33: =IF(COUNTIF('同场线路Rotas do mesmo SC'!A:A,C33)>0,"Sim","Não") -> Não | AR33: =IF(COUNTIF(揽收业务网点!A:A,P33)>0,"Sim","Não") -> Não
A34: SRTR22605707871 | B34: Concluído：已完成 | C34: JGS-F56-2300-1 | D34: Horário padrão | E34: Entrega | F34: 1 | G34: 129 | H34: FNS7D41 | I34: Truck | J34: MARCOS AURELIO PEREIRA DE SA | K34: Transportadora-三方 | L34: MARCOSAURE | M34: EDMAR MARTINS DA SILVA | N34: 989728618 | O34: 78101 | P34: PE JGS | Q34: CE | R34: 7860 | S34: 6182 | T34: 2026-09-30 14:43:05 | U34: 2026-09-30 22:42:39 | V34: 480 | W34: Não | X34: 2026-09-30 23:42:04 | Y34: 2026-09-30 23:00:00 | Z34: 2026-09-30 22:50:52 | AA34: 2026-09-30 22:50:52 | AB34: 883002 | AC34: DC BYE-PB | AD34: CE | AE34: 2026-10-01 02:00:00 | AF34: 2026-10-01 01:56:06 | AG34: -3 | AH34: 2026-10-01 01:56:06 | AI34: 2026-10-01 03:10:16 | AJ34: 52 | AK34: 2026-10-01 02:47:51 | AL34: 2026-10-01 03:15:02 | AM34: 28 | AN34: =IF(X34="",0,1) -> 1 | AO34: =IF(AI34="",0,1) -> 1 | AP34: =DATE(YEAR(AE34),MONTH(AE34),DAY(AE34)) -> 46296 | AQ34: =IF(COUNTIF('同场线路Rotas do mesmo SC'!A:A,C34)>0,"Sim","Não") -> Não | AR34: =IF(COUNTIF(揽收业务网点!A:A,P34)>0,"Sim","Não") -> Não
A35: SRTR22605707911 | B35: Concluído：已完成 | C35: RAO-D138-2300-1 | D35: Horário padrão | E35: Entrega | F35: 1 | G35: 205 | H35: LSE4I06 | I35: 3/4 | J35: LALALOG EXPRESS LTDA | K35: Transportadora-三方 | L35: LALALOG | M35: ANTONY JOABE DE OLIVEIRA VIANA | N35: 16982292807 | O35: 31601 | P35: SN RAO | Q35: SPN | R35: 1916 | S35: 1916 | T35: 2026-09-30 19:14:23 | U35: 2026-09-30 22:52:41 | V35: 219 | W35: Não | X35: 2026-09-30 22:53:35 | Y35: 2026-09-30 23:00:00 | Z35: 2026-09-30 22:28:35 | AA35: 2026-09-30 22:28:35 | AB35: 319153 | AC35: DC SJP-SP | AD35: SPN | AE35: 2026-10-01 01:50:00 | AF35: 2026-10-01 01:42:28 | AG35: -7 | AH35: 2026-10-01 01:42:28 | AI35: 2026-10-01 01:45:36 | AJ35: 12 | AK35: 2026-10-01 01:53:41 | AL35: 2026-10-01 03:22:47 | AM35: 90 | AN35: =IF(X35="",0,1) -> 1 | AO35: =IF(AI35="",0,1) -> 1 | AP35: =DATE(YEAR(AE35),MONTH(AE35),DAY(AE35)) -> 46296 | AQ35: =IF(COUNTIF('同场线路Rotas do mesmo SC'!A:A,C35)>0,"Sim","Não") -> Não | AR35: =IF(COUNTIF(揽收业务网点!A:A,P35)>0,"Sim","Não") -> Não
A36: SRTR22605707980 | B36: Concluído：已完成 | C36: M209-BRE-2202-6 | D36: Horário padrão | E36: Coleta | F36: 6 | G36: 132 | H36: RMZ8J06 | I36: Truck | J36: RHS TRANSPORTES E SERVIÇOS | K36: Transportadora-三方 | L36: RHS | M36: RODRIGO APARECIDO PASSOLONGO | N36: 11985286393 | O36: 535104 | P36: EXT -MG | Q36: MG | R36: 5145 | S36: 5145 | T36: 2026-09-30 07:21:39 | U36: 2026-09-30 20:36:24 | V36: 795 | W36: Não | X36: 2026-09-30 20:42:38 | Y36: 2026-09-30 22:02:00 | Z36: 2026-09-30 17:47:45 | AA36: 2026-09-30 17:47:45 | AB36: 31101 | AC36: SP BRE | AD36: SPS | AE36: 2026-10-01 00:32:00 | AF36: 2026-09-30 23:16:51 | AG36: -75 | AH36: 2026-09-30 23:16:51 | AI36: 2026-10-01 06:54:06 | AJ36: 264 | AK36: 2026-10-01 03:40:17 | AL36: 2026-10-03 06:51:57 | AM36: 3072 | AN36: =IF(X36="",0,1) -> 1 | AO36: =IF(AI36="",0,1) -> 1 | AP36: =DATE(YEAR(AE36),MONTH(AE36),DAY(AE36)) -> 46296 | AQ36: =IF(COUNTIF('同场线路Rotas do mesmo SC'!A:A,C36)>0,"Sim","Não") -> Não | AR36: =IF(COUNTIF(揽收业务网点!A:A,P36)>0,"Sim","Não") -> Sim
A37: SRTR22605708320 | B37: Concluído：已完成 | C37: STM-C380-1900-1 | D37: Horário padrão | E37: Entrega | F37: 1 | G37: 370 | H37: QVL2J83 | I37: Truck | J37: S V DA ROCHA TRANSPORTES | K37: Transportadora-三方 | L37: EXPRES STM | M37: ERLISON RICARDO PINTO DA ROCHA | N37: 93991406800 | O37: 89000 | P37: PA STM | Q37: GP | R37: 932 | S37: 774 | T37: 2026-09-30 16:42:40 | U37: 2026-09-30 17:08:46 | V37: 27 | W37: Não | X37: 2026-09-30 17:52:40 | Y37: 2026-09-30 19:00:00 | Z37: 2026-09-30 17:56:44 | AA37: 2026-09-30 17:56:44 | AB37: 961334 | AC37: F ITT-PA | AD37: GP | AE37: 2026-10-01 07:00:00 | AF37: 2026-10-01 07:10:07 | AG37: 11 | AH37: 2026-10-01 07:10:07 | AI37: 2026-10-01 07:37:10 | AJ37: 42 | AK37: 2026-10-01 07:51:58 | AL37: 2026-10-01 13:24:23 | AM37: 333 | AN37: =IF(X37="",0,1) -> 1 | AO37: =IF(AI37="",0,1) -> 1 | AP37: =DATE(YEAR(AE37),MONTH(AE37),DAY(AE37)) -> 46296 | AQ37: =IF(COUNTIF('同场线路Rotas do mesmo SC'!A:A,C37)>0,"Sim","Não") -> Não | AR37: =IF(COUNTIF(揽收业务网点!A:A,P37)>0,"Sim","Não") -> Não
A38: SRTR22605708511 | B38: Concluído：已完成 | C38: A285-BLU-2200-1 | D38: Horário padrão | E38: Coleta | F38: 1 | G38: 150 | H38: MME5F49 | I38: 3/4 | J38: TRANSPORTES CARVALHO LTDA | K38: Transportadora-三方 | L38: CARVALHO | M38: EDMAR OLIVEIRA FERREIRA | N38: 48996411466 | O38: 155133 | P38: SJE-SC | Q38: PR | R38: 2348 | S38: 2348 | T38: 2026-09-30 14:33:55 | U38: 2026-09-30 18:29:42 | V38: 236 | W38: Não | X38: 2026-09-30 18:42:57 | Y38: 2026-09-30 22:00:00 | Z38: 2026-09-30 18:46:14 | AA38: 2026-09-30 18:46:14 | AB38: 14804 | AC38: SC BLU | AD38: PR | AE38: 2026-10-01 00:30:00 | AF38: 2026-09-30 21:12:11 | AG38: -197 | AH38: 2026-09-30 21:12:11 | AI38: 2026-09-30 22:37:13 | AN38: =IF(X38="",0,1) -> 1 | AO38: =IF(AI38="",0,1) -> 1 | AP38: =DATE(YEAR(AE38),MONTH(AE38),DAY(AE38)) -> 46296 | AQ38: =IF(COUNTIF('同场线路Rotas do mesmo SC'!A:A,C38)>0,"Sim","Não") -> Não | AR38: =IF(COUNTIF(揽收业务网点!A:A,P38)>0,"Sim","Não") -> Sim
A39: SRTR22605708560 | B39: Concluído：已完成 | C39: M209-BRE-2200-5 | D39: Horário padrão | E39: Coleta | F39: 5 | G39: 150 | H39: IPA7I02 | I39: Truck | J39: WILIAN CARLOS DE OLIVEIRA | K39: Transportadora-三方 | L39: WILIAN | M39: EDERSON CARLOS DE OLIVEIRA | N39: 11958040524 | O39: 535104 | P39: EXT -MG | Q39: MG | R39: 9136 | S39: 9111 | T39: 2026-09-30 17:35:36 | U39: 2026-09-30 19:23:35 | V39: 108 | W39: Não | X39: 2026-09-30 19:30:49 | Y39: 2026-09-30 22:00:00 | Z39: 2026-09-30 18:09:55 | AA39: 2026-09-30 18:09:55 | AB39: 31101 | AC39: SP BRE | AD39: SPS | AE39: 2026-10-01 03:20:00 | AF39: 2026-09-30 22:15:52 | AG39: -304 | AH39: 2026-09-30 22:15:52 | AI39: 2026-09-30 22:27:41 | AJ39: 32 | AK39: 2026-09-30 22:47:20 | AL39: 2026-10-05 09:12:04 | AM39: 6385 | AN39: =IF(X39="",0,1) -> 1 | AO39: =IF(AI39="",0,1) -> 1 | AP39: =DATE(YEAR(AE39),MONTH(AE39),DAY(AE39)) -> 46296 | AQ39: =IF(COUNTIF('同场线路Rotas do mesmo SC'!A:A,C39)>0,"Sim","Não") -> Não | AR39: =IF(COUNTIF(揽收业务网点!A:A,P39)>0,"Sim","Não") -> Sim
A40: SRTR22605708880 | B40: Concluído：已完成 | C40: R350-SJM-1830-1 | D40: Horário padrão | E40: Coleta | F40: 1 | G40: 156 | H40: AUE8A13 | I40: Toco | J40: JMJ TRANSPORTE | K40: Transportadora-三方 | L40: JMJ TRANSP | M40: ALEX LIMA PEREIRA | N40: 21989931855 | O40: 691155 | P40: PA NVF-RJ | Q40: RJ | R40: 12646 | S40: 12646 | T40: 2026-09-30 17:07:11 | U40: 2026-09-30 17:58:08 | V40: 51 | W40: Não | X40: 2026-09-30 18:01:40 | Y40: 2026-09-30 18:30:00 | Z40: 2026-09-30 18:02:45 | AA40: 2026-09-30 18:02:45 | AB40: 62101 | AC40: RJ SJM | AD40: RJ | AE40: 2026-10-01 00:20:00 | AF40: 2026-09-30 21:05:38 | AG40: -194 | AH40: 2026-09-30 21:05:38 | AI40: 2026-09-30 22:24:51 | AJ40: 87 | AK40: 2026-09-30 22:31:56 | AL40: 2026-10-02 20:43:26 | AM40: 2772 | AN40: =IF(X40="",0,1) -> 1 | AO40: =IF(AI40="",0,1) -> 1 | AP40: =DATE(YEAR(AE40),MONTH(AE40),DAY(AE40)) -> 46296 | AQ40: =IF(COUNTIF('同场线路Rotas do mesmo SC'!A:A,C40)>0,"Sim","Não") -> Não | AR40: =IF(COUNTIF(揽收业务网点!A:A,P40)>0,"Sim","Não") -> Sim
A41: SRTR22605709840 | B41: Concluído：已完成 | C41: R350-SJM-2000-2 | D41: Horário padrão | E41: Coleta | F41: 2 | G41: 150 | H41: TME6G23 | I41: Truck | J41: JBSL TRANSPORTES LTDA | K41: Transportadora-三方 | L41: JBSL | M41: CARLOS EDUARDO DOS SANTOS FERREIRA | N41: 21965008441 | O41: 691155 | P41: PA NVF-RJ | Q41: RJ | R41: 21419 | S41: 21419 | T41: 2026-09-30 19:20:41 | U41: 2026-09-30 20:31:11 | V41: 71 | W41: Não | X41: 2026-09-30 20:31:47 | Y41: 2026-09-30 20:00:00 | Z41: 2026-09-29 21:27:04 | AA41: 2026-09-29 21:27:04 | AB41: 62101 | AC41: RJ SJM | AD41: RJ | AE41: 2026-10-01 02:40:00 | AF41: 2026-09-30 22:57:10 | AG41: -222 | AH41: 2026-09-30 22:57:10 | AI41: 2026-10-01 00:54:16 | AJ41: 97 | AK41: 2026-10-01 00:33:15 | AL41: 2026-10-05 10:08:40 | AM41: 6336 | AN41: =IF(X41="",0,1) -> 1 | AO41: =IF(AI41="",0,1) -> 1 | AP41: =DATE(YEAR(AE41),MONTH(AE41),DAY(AE41)) -> 46296 | AQ41: =IF(COUNTIF('同场线路Rotas do mesmo SC'!A:A,C41)>0,"Sim","Não") -> Não | AR41: =IF(COUNTIF(揽收业务网点!A:A,P41)>0,"Sim","Não") -> Sim
A42: SRTR22605709851 | B42: Concluído：已完成 | C42: M209-RBP-2000-1 | D42: Horário padrão | E42: Coleta | F42: 1 | G42: 328 | H42: BAG0F98 | I42: 3/4 | J42: WILIAN CARLOS DE OLIVEIRA | K42: Transportadora-三方 | L42: WILIAN | M42: JOSE NARCISO DIAS JUNIOR | N42: 11996257659 | O42: 535104 | P42: EXT -MG | Q42: MG | R42: 1692 | S42: 1691 | T42: 2026-09-30 18:32:53 | U42: 2026-09-30 18:58:12 | V42: 26 | W42: Não | X42: 2026-09-30 19:08:57 | Y42: 2026-09-30 20:00:00 | Z42: 2026-09-30 18:31:57 | AA42: 2026-09-30 18:31:57 | AB42: 31901 | AC42: SP RBP | AD42: SPN | AE42: 2026-10-01 00:48:00 | AF42: 2026-09-30 23:26:20 | AG42: -81 | AH42: 2026-09-30 23:26:20 | AI42: 2026-10-01 01:09:49 | AJ42: 105 | AK42: 2026-10-01 01:10:22 | AL42: 2026-10-01 06:07:35 | AM42: 298 | AN42: =IF(X42="",0,1) -> 1 | AO42: =IF(AI42="",0,1) -> 1 | AP42: =DATE(YEAR(AE42),MONTH(AE42),DAY(AE42)) -> 46296 | AQ42: =IF(COUNTIF('同场线路Rotas do mesmo SC'!A:A,C42)>0,"Sim","Não") -> Não | AR42: =IF(COUNTIF(揽收业务网点!A:A,P42)>0,"Sim","Não") -> Sim
A43: SRTR22605709880 | B43: Concluído：已完成 | C43: S120-GRU-2230-2 | D43: Horário padrão | E43: Coleta | F43: 2 | G43: 24 | H43: DVT2A97 | I43: Toco | J43: CEOS EXPRESS | K43: Transportadora-三方 | L43: CEOS EXPRE | M43: GUSTAVO HENRIQUE BAUTE PORFIRIO | N43: 11946111548 | O43: 311044 | P43: S-SAPOP-SP | Q43: SPE | R43: 15369 | S43: 15369 | T43: 2026-09-30 20:41:11 | U43: 2026-09-30 22:05:35 | V43: 85 | W43: Não | X43: 2026-09-30 22:07:55 | Y43: 2026-09-30 22:30:00 | Z43: 2026-09-30 21:58:13 | AA43: 2026-09-30 21:58:13 | AB43: 30001 | AC43: SP GRU | AD43: SPE | AE43: 2026-10-01 01:30:00 | AF43: 2026-09-30 22:57:09 | AG43: -152 | AH43: 2026-09-30 22:57:09 | AI43: 2026-10-04 04:32:06 | AJ43: 109 | AK43: 2026-10-01 00:45:33 | AL43: 2026-10-05 15:27:10 | AM43: 6642 | AN43: =IF(X43="",0,1) -> 1 | AO43: =IF(AI43="",0,1) -> 1 | AP43: =DATE(YEAR(AE43),MONTH(AE43),DAY(AE43)) -> 46296 | AQ43: =IF(COUNTIF('同场线路Rotas do mesmo SC'!A:A,C43)>0,"Sim","Não") -> Não | AR43: =IF(COUNTIF(揽收业务网点!A:A,P43)>0,"Sim","Não") -> Sim
A44: SRTR22605710351 | B44: Concluído：已完成 | C44: S343-BRE-2330-4 | D44: Horário padrão | E44: Coleta | F44: 4 | G44: 343 | H44: AZA4D30 | I44: Cavalo | J44: MULLER ENXOVAIS LTDA | K44: Transportadora-三方 | L44: MULLER ENX | M44: ARIEL MORAIS FERREIRA DA SILVA | N44: 16997989517 | O44: 316375 | P44: F IBG-SP | Q44: SPN | R44: 5153 | S44: 5153 | T44: 2026-09-30 09:17:39 | U44: 2026-09-30 19:14:59 | V44: 598 | W44: Não | X44: 2026-09-30 19:51:29 | Y44: 2026-09-30 23:30:00 | Z44: 2026-09-30 09:22:30 | AA44: 2026-09-30 09:22:30 | AB44: 31101 | AC44: SP BRE | AD44: SPS | AE44: 2026-10-01 06:00:00 | AF44: 2026-10-01 00:56:10 | AG44: -303 | AH44: 2026-10-01 00:56:10 | AI44: 2026-10-01 06:08:31 | AJ44: 65 | AK44: 2026-10-01 02:01:08 | AL44: 2026-10-05 11:20:09 | AM44: 6320 | AN44: =IF(X44="",0,1) -> 1 | AO44: =IF(AI44="",0,1) -> 1 | AP44: =DATE(YEAR(AE44),MONTH(AE44),DAY(AE44)) -> 46296 | AQ44: =IF(COUNTIF('同场线路Rotas do mesmo SC'!A:A,C44)>0,"Sim","Não") -> Não | AR44: =IF(COUNTIF(揽收业务网点!A:A,P44)>0,"Sim","Não") -> Sim
A45: SRTR22605710511 | B45: Concluído：已完成 | C45: THE-H210-F170-2200-1 | D45: Horário padrão | E45: Entrega | F45: 1 | G45: 311 | H45: UKG3D54 | I45: Furgao | J45: RAIMUNDO ATEVALDO SILVA DE SOU | K45: Transportadora-三方 | L45: ATEVALDO | M45: JOSE LEONISIO LOPES | N45: 86999993706 | O45: 88601 | P45: PI THE | Q45: CE | R45: 1482 | S45: 1028 | T45: 2026-09-30 18:57:25 | U45: 2026-09-30 19:15:40 | V45: 19 | W45: Não | X45: 2026-09-30 20:11:53 | Y45: 2026-09-30 22:00:00 | Z45: 2026-09-30 20:52:42 | AA45: 2026-09-30 20:52:42 | AB45: 899109 | AC45: BDC -MA | AD45: CE | AE45: 2026-10-01 04:00:00 | AF45: 2026-10-01 03:34:12 | AG45: -25 | AH45: 2026-10-01 03:34:12 | AI45: 2026-10-01 03:56:42 | AJ45: 49 | AK45: 2026-10-01 04:22:25 | AL45: 2026-10-01 04:53:14 | AM45: 31 | AN45: =IF(X45="",0,1) -> 1 | AO45: =IF(AI45="",0,1) -> 1 | AP45: =DATE(YEAR(AE45),MONTH(AE45),DAY(AE45)) -> 46296 | AQ45: =IF(COUNTIF('同场线路Rotas do mesmo SC'!A:A,C45)>0,"Sim","Não") -> Não | AR45: =IF(COUNTIF(揽收业务网点!A:A,P45)>0,"Sim","Não") -> Não
A46: SRTR22605710531 | B46: Concluído：已完成 | C46: THE-H239-1800-1 | D46: Horário padrão | E46: Entrega | F46: 1 | G46: 347 | H46: RSI5H68 | I46: 3/4 | J46: AFA DE S OLIVEIRA TRANSPORTADO | K46: Transportadora-三方 | L46: ANDREIA | M46: ORLANDO JOSE DA SILVA SOUSA | N46: 86994992641 | O46: 88601 | P46: PI THE | Q46: CE | R46: 4043 | S46: 3038 | T46: 2026-09-30 17:08:28 | U46: 2026-09-30 17:29:52 | V46: 22 | W46: Não | X46: 2026-09-30 17:42:15 | Y46: 2026-09-30 18:00:00 | Z46: 2026-09-30 17:57:03 | AA46: 2026-09-30 17:57:03 | AB46: 886106 | AC46: PHB -PI | AD46: CE | AE46: 2026-10-01 01:30:00 | AF46: 2026-09-30 23:57:42 | AG46: -92 | AH46: 2026-09-30 23:57:42 | AI46: 2026-10-01 00:20:30 | AJ46: 36 | AK46: 2026-10-01 00:33:28 | AL46: 2026-10-01 19:21:14 | AM46: 1128 | AN46: =IF(X46="",0,1) -> 1 | AO46: =IF(AI46="",0,1) -> 1 | AP46: =DATE(YEAR(AE46),MONTH(AE46),DAY(AE46)) -> 46296 | AQ46: =IF(COUNTIF('同场线路Rotas do mesmo SC'!A:A,C46)>0,"Sim","Não") -> Não | AR46: =IF(COUNTIF(揽收业务网点!A:A,P46)>0,"Sim","Não") -> Não
A47: SRTR22605710811 | B47: Concluído：已完成 | C47: S341-BRE-2300-1 | D47: Horário padrão | E47: Coleta | F47: 1 | G47: 62 | H47: LMU7B28 | I47: Cavalo | J47: JND TRANSPORTES LTDA | K47: Transportadora-三方 | L47: JND TRANSP | M47: aldivan jose lemos da silva | N47: 989260070 | O47: 316373 | P47: DC SOD 02-SP | Q47: SPS | R47: 7085 | S47: 7085 | T47: 2026-09-30 19:16:08 | U47: 2026-09-30 22:08:16 | V47: 173 | W47: Não | Y47: 2026-09-30 23:00:00 | Z47: 2026-09-30 23:47:22 | AA47: 2026-09-30 23:47:22 | AB47: 31101 | AC47: SP BRE | AD47: SPS | AE47: 2026-10-01 00:30:00 | AF47: 2026-10-01 01:58:57 | AG47: 89 | AH47: 2026-10-01 01:58:57 | AI47: 2026-10-01 14:08:27 | AJ47: -37 | AK47: 2026-10-01 01:21:27 | AL47: 2026-10-05 14:36:58 | AM47: 6556 | AN47: =IF(X47="",0,1) -> 0 | AO47: =IF(AI47="",0,1) -> 1 | AP47: =DATE(YEAR(AE47),MONTH(AE47),DAY(AE47)) -> 46296 | AQ47: =IF(COUNTIF('同场线路Rotas do mesmo SC'!A:A,C47)>0,"Sim","Não") -> Não | AR47: =IF(COUNTIF(揽收业务网点!A:A,P47)>0,"Sim","Não") -> Sim
A48: SRTR22605711660 | B48: Concluído：已完成 | C48: STM-C464-1900-1 | D48: Horário padrão | E48: Entrega | F48: 1 | G48: 370 | H48: QVL2J83 | I48: Truck | J48: S V DA ROCHA TRANSPORTES | K48: Transportadora-三方 | L48: EXPRES STM | M48: ERLISON RICARDO PINTO DA ROCHA | N48: 93991406800 | O48: 89000 | P48: PA STM | Q48: GP | R48: 1213 | S48: 848 | T48: 2026-09-30 17:25:56 | U48: 2026-09-30 17:39:24 | V48: 14 | W48: Não | X48: 2026-09-30 17:54:17 | Y48: 2026-09-30 19:00:00 | Z48: 2026-09-30 17:57:12 | AA48: 2026-09-30 17:57:12 | AB48: 961418 | AC48: ITT 02-PA | AD48: GP | AE48: 2026-10-01 07:00:00 | AF48: 2026-10-01 06:03:47 | AG48: -56 | AH48: 2026-10-01 06:03:47 | AI48: 2026-10-01 07:50:35 | AJ48: 112 | AK48: 2026-10-01 07:54:52 | AL48: 2026-10-01 10:13:32 | AM48: 139 | AN48: =IF(X48="",0,1) -> 1 | AO48: =IF(AI48="",0,1) -> 1 | AP48: =DATE(YEAR(AE48),MONTH(AE48),DAY(AE48)) -> 46296 | AQ48: =IF(COUNTIF('同场线路Rotas do mesmo SC'!A:A,C48)>0,"Sim","Não") -> Não | AR48: =IF(COUNTIF(揽收业务网点!A:A,P48)>0,"Sim","Não") -> Não
A49: SRTR22605711860 | B49: Concluído：已完成 | C49: M209-D105-1900-1 | D49: Horário padrão | E49: Coleta | F49: 1 | G49: 368 | H49: FGY5I25 | I49: 3/4 | J49: WILIAN CARLOS DE OLIVEIRA | K49: Transportadora-三方 | L49: WILIAN | M49: FRANCISCO GILCLECIO FERNANDES | N49: 11982889362 | O49: 535104 | P49: EXT -MG | Q49: MG | R49: 960 | S49: 960 | T49: 2026-09-30 17:52:08 | U49: 2026-09-30 17:57:09 | V49: 6 | W49: Não | X49: 2026-09-30 18:03:28 | Y49: 2026-09-30 19:00:00 | Z49: 2026-09-30 17:47:19 | AA49: 2026-09-30 17:47:19 | AB49: 314001 | AC49: DC BAU-SP | AD49: SPN | AE49: 2026-10-01 00:32:00 | AF49: 2026-09-30 23:14:54 | AG49: -77 | AH49: 2026-09-30 23:14:54 | AI49: 2026-10-01 00:55:10 | AJ49: 103 | AK49: 2026-10-01 00:57:14 | AL49: 2026-10-01 01:08:31 | AM49: 12 | AN49: =IF(X49="",0,1) -> 1 | AO49: =IF(AI49="",0,1) -> 1 | AP49: =DATE(YEAR(AE49),MONTH(AE49),DAY(AE49)) -> 46296 | AQ49: =IF(COUNTIF('同场线路Rotas do mesmo SC'!A:A,C49)>0,"Sim","Não") -> Não | AR49: =IF(COUNTIF(揽收业务网点!A:A,P49)>0,"Sim","Não") -> Sim
A50: SRTR22605712200 | B50: Concluído：已完成 | C50: BRE-D105-2100-4 | D50: Horário padrão | E50: Entrega | F50: 4 | G50: 303 | H50: EGK0B15 | I50: Cavalo | J50: MARCELO FERREIRA DA SILVA | K50: Transportadora-三方 | L50: MARCELO BR | M50: ROBSON PAULO DE ANDRADE | N50: 14997054985 | O50: 31101 | P50: SP BRE | Q50: SPS | R50: 4822 | S50: 4804 | T50: 2026-09-30 17:43:23 | U50: 2026-09-30 20:41:17 | V50: 178 | W50: Não | X50: 2026-09-30 20:45:59 | Y50: 2026-09-30 21:00:00 | Z50: 2026-09-30 20:35:47 | AA50: 2026-09-30 20:35:47 | AB50: 314001 | AC50: DC BAU-SP | AD50: SPN | AE50: 2026-10-01 02:00:00 | AF50: 2026-10-01 01:01:57 | AG50: -58 | AH50: 2026-10-01 01:01:57 | AJ50: 64 | AK50: 2026-10-01 02:05:45 | AL50: 2026-10-01 05:22:28 | AM50: 197 | AN50: =IF(X50="",0,1) -> 1 | AO50: =IF(AI50="",0,1) -> 0 | AP50: =DATE(YEAR(AE50),MONTH(AE50),DAY(AE50)) -> 46296 | AQ50: =IF(COUNTIF('同场线路Rotas do mesmo SC'!A:A,C50)>0,"Sim","Não") -> Não | AR50: =IF(COUNTIF(揽收业务网点!A:A,P50)>0,"Sim","Não") -> Não
A51: SRTR22605712611 | B51: Concluído：已完成 | C51: S05-BRE-2300-9 | D51: Horário padrão | E51: Coleta | F51: 9 | G51: 34 | H51: BYE6A85 | I51: Utilitário | J51: Lumina Mix | K51: Transportadora-三方 | L51: Lumina | M51: EDILSON ANDRADE DE OLIVEIRA | N51: 11985810115 | O51: 311022 | P51: DC S-BRFD-SP | Q51: SPS | R51: 20984 | S51: 20984 | T51: 2026-09-30 20:52:17 | U51: 2026-09-30 21:58:09 | V51: 66 | W51: Não | X51: 2026-09-30 22:10:17 | Y51: 2026-09-30 23:00:00 | Z51: 2026-09-30 22:02:39 | AA51: 2026-09-30 22:02:39 | AB51: 31101 | AC51: SP BRE | AD51: SPS | AE51: 2026-10-01 01:00:00 | AI51: 2026-10-01 03:55:58 | AK51: 2026-10-01 02:26:09 | AL51: 2026-10-05 08:52:05 | AM51: 6146 | AN51: =IF(X51="",0,1) -> 1 | AO51: =IF(AI51="",0,1) -> 1 | AP51: =DATE(YEAR(AE51),MONTH(AE51),DAY(AE51)) -> 46296 | AQ51: =IF(COUNTIF('同场线路Rotas do mesmo SC'!A:A,C51)>0,"Sim","Não") -> Não | AR51: =IF(COUNTIF(揽收业务网点!A:A,P51)>0,"Sim","Não") -> Sim
A52: SRTR22605712780 | B52: Concluído：已完成 | C52: SJS-A402-A284-1430-1 | D52: Horário padrão | E52: Entrega | F52: 1 | G52: 810 | H52: AZT0F27 | I52: Truck | J52: MAG TRANSPORTES E LOGISTISCA | K52: Transportadora-三方 | L52: MAG TRANSP | M52: DOUGLAS GAVRON CORDEIRO | N52: 4198116999 | O52: 24101 | P52: PR SJS | Q52: PR | R52: 4510 | S52: 4301 | T52: 2026-09-29 11:45:57 | U52: 2026-09-30 12:51:52 | V52: 1506 | W52: Sim | X52: 2026-09-30 13:36:09 | Y52: 2026-09-30 14:30:00 | Z52: 2026-09-30 13:40:23 | AA52: 2026-09-30 13:40:23 | AB52: 155253 | AC52: F MDA-PR | AD52: PR | AE52: 2026-10-01 04:00:00 | AF52: 2026-10-01 01:34:03 | AG52: -145 | AH52: 2026-10-01 01:34:03 | AJ52: 1549 | AK52: 2026-10-02 03:22:51 | AL52: 2026-10-02 07:25:00 | AM52: 243 | AN52: =IF(X52="",0,1) -> 1 | AO52: =IF(AI52="",0,1) -> 0 | AP52: =DATE(YEAR(AE52),MONTH(AE52),DAY(AE52)) -> 46296 | AQ52: =IF(COUNTIF('同场线路Rotas do mesmo SC'!A:A,C52)>0,"Sim","Não") -> Não | AR52: =IF(COUNTIF(揽收业务网点!A:A,P52)>0,"Sim","Não") -> Não
A53: SRTR22605712780 | B53: Concluído：已完成 | C53: SJS-A402-A284-1430-1 | D53: Horário padrão | E53: Entrega | F53: 1 | G53: 30 | H53: AZT0F27 | I53: Truck | J53: MAG TRANSPORTES E LOGISTISCA | K53: Transportadora-三方 | L53: MAG TRANSP | M53: DOUGLAS GAVRON CORDEIRO | N53: 4198116999 | O53: 155253 | P53: F MDA-PR | Q53: PR | R53: 29 | S53: 29 | T53: 2026-10-01 02:19:54 | U53: 2026-10-01 02:21:37 | V53: 2 | W53: Não | Y53: 2026-10-01 05:00:00 | Z53: 2026-10-01 02:36:47 | AA53: 2026-10-01 02:36:47 | AB53: 155132 | AC53: F FDI-PR | AD53: PR | AE53: 2026-10-01 05:30:00 | AF53: 2026-10-01 03:27:07 | AG53: -122 | AH53: 2026-10-01 03:27:07 | AJ53: 94 | AK53: 2026-10-01 05:00:14 | AL53: 2026-10-01 07:38:19 | AM53: 159 | AN53: =IF(X53="",0,1) -> 0 | AO53: =IF(AI53="",0,1) -> 0 | AP53: =DATE(YEAR(AE53),MONTH(AE53),DAY(AE53)) -> 46296 | AQ53: =IF(COUNTIF('同场线路Rotas do mesmo SC'!A:A,C53)>0,"Sim","Não") -> Não | AR53: =IF(COUNTIF(揽收业务网点!A:A,P53)>0,"Sim","Não") -> Não
A54: SRTR22605713391 | B54: Concluído：已完成 | C54: STM-C427-0500-1 | D54: Horário padrão | E54: Entrega | F54: 1 | G54: 264 | H54: OGT4E97 | I54: 3/4 | J54: SERGIO MANUEL LIMA DA SILVA | K54: Transportadora-三方 | L54: ATIVA T | M54: CARLOS ALBERTO DOS SANTOS NUNES JUNIOR | N54: 994640724 | O54: 89000 | P54: PA STM | Q54: GP | R54: 1421 | S54: 846 | T54: 2026-09-29 21:08:23 | U54: 2026-09-29 21:17:45 | V54: 10 | W54: Não | X54: 2026-09-29 22:04:31 | Y54: 2026-09-30 05:00:00 | Z54: 2026-09-29 22:23:46 | AA54: 2026-09-29 22:23:46 | AB54: 961381 | AC54: F PRT -AM | AD54: GP | AE54: 2026-10-02 07:00:00 | AF54: 2026-10-02 06:59:01 | AG54: 0 | AH54: 2026-10-02 06:59:01 | AI54: 2026-10-02 06:59:57 | AJ54: 4 | AK54: 2026-10-02 07:02:44 | AL54: 2026-10-02 08:23:04 | AM54: 81 | AN54: =IF(X54="",0,1) -> 1 | AO54: =IF(AI54="",0,1) -> 1 | AP54: =DATE(YEAR(AE54),MONTH(AE54),DAY(AE54)) -> 46297 | AQ54: =IF(COUNTIF('同场线路Rotas do mesmo SC'!A:A,C54)>0,"Sim","Não") -> Não | AR54: =IF(COUNTIF(揽收业务网点!A:A,P54)>0,"Sim","Não") -> Não
A55: SRTR22605714540 | B55: Concluído：已完成 | C55: BNU-B208-B236-2330-1 | D55: Horário padrão | E55: Entrega | F55: 1 | G55: 240 | H55: MIL1284 | I55: 3/4 | J55: C. R. DOS SANTOS TRANSPORTES | K55: Transportadora-三方 | L55: C. R. | M55: MARCIEL MARCELINO | N55: 47999201530 | O55: 14802 | P55: SC BNU | Q55: PR | R55: 4407 | S55: 4391 | T55: 2026-09-30 19:25:12 | U55: 2026-09-30 23:20:26 | V55: 236 | W55: Não | X55: 2026-09-30 23:21:36 | Y55: 2026-09-30 23:30:00 | Z55: 2026-09-30 20:37:05 | AA55: 2026-09-30 20:37:05 | AB55: 149107 | AC55: LGS -SC | AD55: PR | AE55: 2026-10-01 03:30:00 | AF55: 2026-10-01 03:36:17 | AG55: 7 | AH55: 2026-10-01 03:36:17 | AI55: 2026-10-01 03:24:22 | AJ55: -28 | AK55: 2026-10-01 03:07:18 | AL55: 2026-10-01 05:57:45 | AM55: 171 | AN55: =IF(X55="",0,1) -> 1 | AO55: =IF(AI55="",0,1) -> 1 | AP55: =DATE(YEAR(AE55),MONTH(AE55),DAY(AE55)) -> 46296 | AQ55: =IF(COUNTIF('同场线路Rotas do mesmo SC'!A:A,C55)>0,"Sim","Não") -> Não | AR55: =IF(COUNTIF(揽收业务网点!A:A,P55)>0,"Sim","Não") -> Não
A56: SRTR22605715331 | B56: Concluído：已完成 | C56: BRE-S417-2200-1 | D56: Horário padrão | E56: Entrega | F56: 1 | G56: 61 | H56: GCO3J08 | I56: Cavalo | J56: JND TRANSPORTES LTDA | K56: Transportadora-三方 | L56: JND TRANSP | M56: PAULO MARQUES DA SILVA SOBRINHO | N56: 11967684658 | O56: 31101 | P56: SP BRE | Q56: SPS | R56: 13735 | S56: 13674 | T56: 2026-09-29 23:58:30 | U56: 2026-09-30 09:51:01 | V56: 593 | W56: Não | X56: 2026-09-30 12:11:55 | Y56: 2026-09-30 22:00:00 | Z56: 2026-09-30 12:43:58 | AA56: 2026-09-30 12:43:58 | AB56: 311455 | AC56: DC JND 02-SP | AD56: SPS | AE56: 2026-10-01 00:00:00 | AF56: 2026-09-30 14:10:29 | AG56: -589 | AH56: 2026-09-30 14:10:29 | AI56: 2026-09-30 22:43:32 | AJ56: 515 | AK56: 2026-09-30 22:45:03 | AL56: 2026-10-01 04:58:10 | AM56: 374 | AN56: =IF(X56="",0,1) -> 1 | AO56: =IF(AI56="",0,1) -> 1 | AP56: =DATE(YEAR(AE56),MONTH(AE56),DAY(AE56)) -> 46296 | AQ56: =IF(COUNTIF('同场线路Rotas do mesmo SC'!A:A,C56)>0,"Sim","Não") -> Não | AR56: =IF(COUNTIF(揽收业务网点!A:A,P56)>0,"Sim","Não") -> Não
A57: SRTR22605715600 | B57: Concluído：已完成 | C57: M209-BRE-2100-9 | D57: Horário padrão | E57: Coleta | F57: 9 | G57: 150 | H57: EJZ8B20 | I57: Cavalo | J57: RHS TRANSPORTES E SERVIÇOS | K57: Transportadora-三方 | L57: RHS | M57: ederson rodrigues maciel | N57: 11942137825 | O57: 535104 | P57: EXT -MG | Q57: MG | R57: 16548 | S57: 13439 | T57: 2026-09-30 11:01:05 | U57: 2026-09-30 16:39:20 | V57: 339 | W57: Não | X57: 2026-09-30 15:53:44 | Y57: 2026-09-30 21:00:00 | Z57: 2026-09-30 10:58:12 | AA57: 2026-09-30 10:58:12 | AB57: 31101 | AC57: SP BRE | AD57: SPS | AE57: 2026-10-01 00:00:00 | AF57: 2026-09-30 19:32:24 | AG57: -267 | AH57: 2026-09-30 19:32:24 | AI57: 2026-09-30 20:55:24 | AJ57: -208 | AK57: 2026-09-30 16:04:07 | AL57: 2026-10-05 09:09:17 | AM57: 6786 | AN57: =IF(X57="",0,1) -> 1 | AO57: =IF(AI57="",0,1) -> 1 | AP57: =DATE(YEAR(AE57),MONTH(AE57),DAY(AE57)) -> 46296 | AQ57: =IF(COUNTIF('同场线路Rotas do mesmo SC'!A:A,C57)>0,"Sim","Não") -> Não | AR57: =IF(COUNTIF(揽收业务网点!A:A,P57)>0,"Sim","Não") -> Sim
A58: SRTR22605715771 | B58: Concluído：已完成 | C58: BRE-S02-2300-5 | D58: Horário padrão | E58: Entrega | F58: 5 | G58: 22 | H58: PBV9A56 | I58: Cavalo | J58: JND TRANSPORTES LTDA | K58: Transportadora-三方 | L58: JND TRANSP | M58: MATHEUS ANTUNES SOARES | N58: 11979534035 | O58: 31101 | P58: SP BRE | Q58: SPS | R58: 11453 | S58: 11362 | T58: 2026-09-30 14:30:43 | U58: 2026-09-30 23:00:45 | V58: 511 | W58: Não | X58: 2026-09-30 23:00:24 | Y58: 2026-09-30 23:00:00 | Z58: 2026-09-30 23:12:38 | AA58: 2026-09-30 23:12:38 | AB58: 311030 | AC58: DC S-VLANA-SP | AD58: SPS | AE58: 2026-10-01 00:00:00 | AF58: 2026-10-01 00:34:50 | AG58: 35 | AH58: 2026-10-01 00:34:50 | AI58: 2026-10-01 00:41:06 | AJ58: 8 | AK58: 2026-10-01 00:41:57 | AL58: 2026-10-01 04:34:49 | AM58: 233 | AN58: =IF(X58="",0,1) -> 1 | AO58: =IF(AI58="",0,1) -> 1 | AP58: =DATE(YEAR(AE58),MONTH(AE58),DAY(AE58)) -> 46296 | AQ58: =IF(COUNTIF('同场线路Rotas do mesmo SC'!A:A,C58)>0,"Sim","Não") -> Não | AR58: =IF(COUNTIF(揽收业务网点!A:A,P58)>0,"Sim","Não") -> Não
A59: SRTR22605716600 | B59: Concluído：已完成 | C59: S291-BRE-2300-2 | D59: Horário padrão | E59: Coleta | F59: 2 | G59: 23 | H59: BSG6E29 | I59: Toco | J59: CEOS EXPRESS | K59: Transportadora-三方 | L59: CEOS EXPRE | M59: MARCONI PINTO MORORO | N59: 11950734278 | O59: 311951 | P59: PA OLIST-SP | Q59: SPS | R59: 2107 | S59: 2107 | T59: 2026-09-30 17:46:15 | U59: 2026-09-30 21:46:51 | V59: 241 | W59: Não | X59: 2026-09-30 22:05:17 | Y59: 2026-09-30 23:00:00 | Z59: 2026-09-30 22:15:43 | AA59: 2026-09-30 22:15:43 | AB59: 31101 | AC59: SP BRE | AD59: SPS | AE59: 2026-10-01 00:00:00 | AF59: 2026-09-30 23:12:26 | AG59: -47 | AH59: 2026-09-30 23:12:26 | AI59: 2026-09-30 23:27:27 | AJ59: 27 | AK59: 2026-09-30 23:38:39 | AL59: 2026-10-02 02:36:40 | AM59: 1619 | AN59: =IF(X59="",0,1) -> 1 | AO59: =IF(AI59="",0,1) -> 1 | AP59: =DATE(YEAR(AE59),MONTH(AE59),DAY(AE59)) -> 46296 | AQ59: =IF(COUNTIF('同场线路Rotas do mesmo SC'!A:A,C59)>0,"Sim","Não") -> Não | AR59: =IF(COUNTIF(揽收业务网点!A:A,P59)>0,"Sim","Não") -> Sim
A60: SRTR22605717511 | B60: Concluído：已完成 | C60: C276-GYN-2000-1 | D60: Horário padrão | E60: Coleta | F60: 1 | G60: 280 | H60: NGW8G19 | I60: 3/4 | J60: JOSE JENUARIO SILVA | K60: Transportadora-三方 | L60: JOSE J.S | M60: WESLEY CLAYTON PEREIRA MARTINS | N60: 62995368825 | O60: 961230 | P60: F GYN 02-GO | Q60: GP | R60: 5349 | S60: 5349 | T60: 2026-09-30 16:03:12 | U60: 2026-09-30 21:09:44 | V60: 307 | W60: Não | X60: 2026-09-30 22:11:47 | Y60: 2026-09-30 20:00:00 | Z60: 2026-09-30 19:00:00 | AA60: 2026-09-30 19:00:00 | AB60: 96100 | AC60: GO GYN | AD60: GP | AE60: 2026-10-01 03:00:00 | AF60: 2026-09-30 22:52:28 | AG60: -247 | AH60: 2026-09-30 22:52:28 | AI60: 2026-09-30 23:11:59 | AJ60: 321 | AK60: 2026-10-01 04:12:40 | AL60: 2026-10-02 10:53:36 | AM60: 1841 | AN60: =IF(X60="",0,1) -> 1 | AO60: =IF(AI60="",0,1) -> 1 | AP60: =DATE(YEAR(AE60),MONTH(AE60),DAY(AE60)) -> 46296 | AQ60: =IF(COUNTIF('同场线路Rotas do mesmo SC'!A:A,C60)>0,"Sim","Não") -> Não | AR60: =IF(COUNTIF(揽收业务网点!A:A,P60)>0,"Sim","Não") -> Sim
A61: SRTR22605717871 | B61: Concluído：已完成 | C61: ANA-C537-0600-1 | D61: Horário padrão | E61: Entrega | F61: 1 | G61: 800 | H61: TWF0F29 | I61: Barco | J61: SAO DOMINGOS NAVEGACAO LTDA | K61: Transportadora-三方 | L61: SD | M61: VALDIR VIEIRA CORREA JUNIOR | N61: 91985099819 | O61: 89101 | P61: PA ANA | Q61: GP | R61: 3918 | S61: 2041 | T61: 2026-09-29 09:07:16 | U61: 2026-09-30 02:50:45 | V61: 1064 | W61: Não | X61: 2026-09-30 04:18:38 | Y61: 2026-09-30 06:00:00 | Z61: 2026-09-30 04:27:00 | AA61: 2026-09-30 04:27:00 | AB61: 961491 | AC61: F BRV 02 -PA | AD61: GP | AE61: 2026-10-02 07:00:00 | AF61: 2026-10-01 13:30:10 | AG61: -1049 | AH61: 2026-10-01 13:30:10 | AI61: 2026-10-01 13:46:42 | AJ61: 18 | AK61: 2026-10-01 13:47:34 | AL61: 2026-10-02 09:09:57 | AM61: 1163 | AN61: =IF(X61="",0,1) -> 1 | AO61: =IF(AI61="",0,1) -> 1 | AP61: =DATE(YEAR(AE61),MONTH(AE61),DAY(AE61)) -> 46297 | AQ61: =IF(COUNTIF('同场线路Rotas do mesmo SC'!A:A,C61)>0,"Sim","Não") -> Não | AR61: =IF(COUNTIF(揽收业务网点!A:A,P61)>0,"Sim","Não") -> Não
A62: SRTR22605718291 | B62: Concluído：已完成 | C62: S343-RAO-2330-7 | D62: Horário padrão | E62: Coleta | F62: 7 | G62: 145 | H62: EGJ3H63 | I62: CAVALO | J62: MULLER ENXOVAIS LTDA | K62: Transportadora-三方 | L62: MULLER ENX | M62: ANDERSON LUIZ DE AQUINO BARREIRA | N62: 16997798805 | O62: 316375 | P62: F IBG-SP | Q62: SPN | R62: 6466 | S62: 6466 | T62: 2026-09-30 09:16:58 | U62: 2026-09-30 12:54:33 | V62: 218 | W62: Não | X62: 2026-09-30 13:25:42 | Y62: 2026-09-30 23:30:00 | Z62: 2026-09-30 08:50:12 | AA62: 2026-09-30 08:50:12 | AB62: 31601 | AC62: SN RAO | AD62: SPN | AE62: 2026-10-01 04:00:00 | AF62: 2026-09-30 16:15:30 | AG62: -704 | AH62: 2026-09-30 16:15:30 | AI62: 2026-09-30 22:35:26 | AJ62: 395 | AK62: 2026-09-30 22:50:28 | AL62: 2026-10-01 00:57:04 | AM62: 127 | AN62: =IF(X62="",0,1) -> 1 | AO62: =IF(AI62="",0,1) -> 1 | AP62: =DATE(YEAR(AE62),MONTH(AE62),DAY(AE62)) -> 46296 | AQ62: =IF(COUNTIF('同场线路Rotas do mesmo SC'!A:A,C62)>0,"Sim","Não") -> Não | AR62: =IF(COUNTIF(揽收业务网点!A:A,P62)>0,"Sim","Não") -> Sim
A63: SRTR22605718731 | B63: Concluído：已完成 | C63: A002-A297-A371-2310-1 | D63: Horário padrão | E63: Entrega | F63: 1 | G63: 120 | H63: JAV0C45 | I63: Furgao | J63: TRANSPORTES JC &amp; FILHO LTDA | K63: Transportadora-三方 | L63: JC &amp; FILHO | M63: CARLOS LEANDRO FRANCISCO | N63: 54991697473 | O63: 154001 | P63: DC PFB-RS | Q63: PR | R63: 565 | S63: 560 | T63: 2026-09-30 14:47:16 | U63: 2026-09-30 14:49:26 | V63: 3 | W63: Não | X63: 2026-09-30 15:30:23 | Y63: 2026-09-30 23:10:00 | Z63: 2026-09-30 15:21:34 | AA63: 2026-09-30 15:21:34 | AB63: 155145 | AC63: F CRZ-RS | AD63: PR | AE63: 2026-10-01 01:10:00 | AF63: 2026-09-30 16:24:30 | AG63: -525 | AH63: 2026-09-30 16:24:30 | AI63: 2026-09-30 17:14:52 | AJ63: 52 | AK63: 2026-09-30 17:16:18 | AL63: 2026-09-30 17:45:29 | AM63: 30 | AN63: =IF(X63="",0,1) -> 1 | AO63: =IF(AI63="",0,1) -> 1 | AP63: =DATE(YEAR(AE63),MONTH(AE63),DAY(AE63)) -> 46296 | AQ63: =IF(COUNTIF('同场线路Rotas do mesmo SC'!A:A,C63)>0,"Sim","Não") -> Não | AR63: =IF(COUNTIF(揽收业务网点!A:A,P63)>0,"Sim","Não") -> Não
A64: SRTR22605718731 | B64: Concluído：已完成 | C64: A002-A297-A371-2310-1 | D64: Horário padrão | E64: Entrega | F64: 1 | G64: 100 | H64: JAV0C45 | I64: Furgao | J64: TRANSPORTES JC &amp; FILHO LTDA | K64: Transportadora-三方 | L64: JC &amp; FILHO | M64: CARLOS LEANDRO FRANCISCO | N64: 54991697473 | O64: 155145 | P64: F CRZ-RS | Q64: PR | R64: 144 | S64: 131 | T64: 2026-09-30 14:59:08 | U64: 2026-09-30 15:46:26 | V64: 48 | W64: Não | Y64: 2026-10-01 01:30:00 | Z64: 2026-09-30 16:25:00 | AA64: 2026-09-30 16:25:00 | AB64: 155222 | AC64: F CAT-RS | AD64: PR | AE64: 2026-10-01 03:10:00 | AF64: 2026-09-30 18:02:39 | AG64: -547 | AH64: 2026-09-30 18:02:39 | AI64: 2026-09-30 18:06:38 | AJ64: 7 | AK64: 2026-09-30 18:08:46 | AL64: 2026-09-30 18:21:06 | AM64: 13 | AN64: =IF(X64="",0,1) -> 0 | AO64: =IF(AI64="",0,1) -> 1 | AP64: =DATE(YEAR(AE64),MONTH(AE64),DAY(AE64)) -> 46296 | AQ64: =IF(COUNTIF('同场线路Rotas do mesmo SC'!A:A,C64)>0,"Sim","Não") -> Não | AR64: =IF(COUNTIF(揽收业务网点!A:A,P64)>0,"Sim","Não") -> Não
A65: SRTR22605720971 | B65: Concluído：已完成 | C65: M209-BRE-2315-16 | D65: Horário padrão | E65: Coleta | F65: 16 rit | G65: 150 | H65: DAU3B67 | I65: Truck | J65: WILIAN CARLOS DE OLIVEIRA | K65: Transportadora-三方 | L65: WILIAN | M65: WILLIAN CARLOS DE OLIVEIRA | N65: 11974034385 | O65: 535104 | P65: EXT -MG | Q65: MG | R65: 3833 | S65: 3830 | T65: 2026-09-30 21:30:53 | U65: 2026-09-30 22:44:05 | V65: 74 | W65: Não | X65: 2026-09-30 22:53:25 | Y65: 2026-09-30 23:15:00 | Z65: 2026-09-30 22:09:49 | AA65: 2026-09-30 22:09:49 | AB65: 31101 | AC65: SP BRE | AD65: SPS | AE65: 2026-10-01 02:15:00 | AF65: 2026-10-01 02:39:49 | AG65: 25 | AH65: 2026-10-01 02:39:49 | AI65: 2026-10-01 06:11:57 | AJ65: 10 | AK65: 2026-10-01 02:49:42 | AL65: 2026-10-02 14:52:20 | AM65: 2163 | AN65: =IF(X65="",0,1) -> 1 | AO65: =IF(AI65="",0,1) -> 1 | AP65: =DATE(YEAR(AE65),MONTH(AE65),DAY(AE65)) -> 46296 | AQ65: =IF(COUNTIF('同场线路Rotas do mesmo SC'!A:A,C65)>0,"Sim","Não") -> Não | AR65: =IF(COUNTIF(揽收业务网点!A:A,P65)>0,"Sim","Não") -> Sim
A66: SRTR22605721060 | B66: Concluído：已完成 | C66: STM-C547-1900-1 | D66: Horário padrão | E66: Entrega | F66: 1 | G66: 124 | H66: HPH3D99 | I66: Furgao | J66: I M BRITO SOARES TRANSPORTES | K66: Transportadora-三方 | L66: ISLOG | M66: MARCIO JUNIOR RIBEIRO DIAS | N66: 991932619 | O66: 89000 | P66: PA STM | Q66: GP | R66: 761 | S66: 417 | T66: 2026-09-30 16:25:38 | U66: 2026-09-30 17:17:15 | V66: 52 | W66: Não | X66: 2026-09-30 17:46:53 | Y66: 2026-09-30 19:00:00 | Z66: 2026-09-30 17:48:47 | AA66: 2026-09-30 17:48:47 | AB66: 961501 | AC66: MTA FLUVIAL-PA | AD66: GP | AE66: 2026-10-01 07:00:00 | AF66: 2026-10-01 07:21:22 | AG66: 22 | AH66: 2026-10-01 07:21:22 | AI66: 2026-10-01 08:20:10 | AJ66: 56 | AK66: 2026-10-01 08:16:47 | AL66: 2026-10-01 09:45:43 | AM66: 89 | AN66: =IF(X66="",0,1) -> 1 | AO66: =IF(AI66="",0,1) -> 1 | AP66: =DATE(YEAR(AE66),MONTH(AE66),DAY(AE66)) -> 46296 | AQ66: =IF(COUNTIF('同场线路Rotas do mesmo SC'!A:A,C66)>0,"Sim","Não") -> Não | AR66: =IF(COUNTIF(揽收业务网点!A:A,P66)>0,"Sim","Não") -> Não
A67: SRTR22605721371 | B67: Concluído：已完成 | C67: ANA-C492-0600-1 | D67: Horário padrão | E67: Entrega | F67: 1 | G67: 800 | H67: 0920411 | I67: Barco | J67: NV IRMAOS SANTANA /ANA BEATRIZ | K67: Transportadora-三方 | L67: AnaBEATRIZ | M67: ALANA OLIVEIRA DO NASCIMENTO | N67: 96991413173 | O67: 89101 | P67: PA ANA | Q67: GP | R67: 205 | S67: 205 | T67: 2026-09-29 09:20:12 | U67: 2026-09-30 02:36:21 | V67: 1037 | W67: Não | X67: 2026-09-30 04:15:52 | Y67: 2026-09-30 06:00:00 | Z67: 2026-09-30 04:28:38 | AA67: 2026-09-30 04:28:38 | AB67: 961446 | AC67: LRJ-AP | AD67: GP | AE67: 2026-10-02 10:00:00 | AF67: 2026-10-01 08:00:00 | AG67: -1559 | AH67: 2026-10-01 08:00:00 | AI67: 2026-10-03 08:35:20 | AJ67: 2923 | AK67: 2026-10-03 08:42:38 | AL67: 2026-10-03 10:10:48 | AM67: 89 | AN67: =IF(X67="",0,1) -> 1 | AO67: =IF(AI67="",0,1) -> 1 | AP67: =DATE(YEAR(AE67),MONTH(AE67),DAY(AE67)) -> 46297 | AQ67: =IF(COUNTIF('同场线路Rotas do mesmo SC'!A:A,C67)>0,"Sim","Não") -> Não | AR67: =IF(COUNTIF(揽收业务网点!A:A,P67)>0,"Sim","Não") -> Não
A68: SRTR22605721891 | B68: Concluído：已完成 | C68: M209-BRE-2130-10 | D68: Horário padrão | E68: Coleta | F68: 10 | G68: 150 | H68: HET7H17 | I68: Cavalo | J68: RHS TRANSPORTES E SERVIÇOS | K68: Transportadora-三方 | L68: RHS | M68: ALD DE OLIVEIRA BARRA | N68: 35992121297 | O68: 535104 | P68: EXT -MG | Q68: MG | R68: 12704 | S68: 7265 | T68: 2026-09-30 14:36:49 | U68: 2026-09-30 17:03:39 | V68: 147 | W68: Não | X68: 2026-09-30 17:11:57 | Y68: 2026-09-30 21:30:00 | Z68: 2026-09-30 14:41:12 | AA68: 2026-09-30 14:41:12 | AB68: 31101 | AC68: SP BRE | AD68: SPS | AE68: 2026-10-01 00:30:00 | AF68: 2026-09-30 21:42:36 | AG68: -167 | AH68: 2026-09-30 21:42:36 | AI68: 2026-10-01 01:20:13 | AJ68: 35 | AK68: 2026-09-30 22:16:50 | AL68: 2026-10-05 06:45:42 | AM68: 6269 | AN68: =IF(X68="",0,1) -> 1 | AO68: =IF(AI68="",0,1) -> 1 | AP68: =DATE(YEAR(AE68),MONTH(AE68),DAY(AE68)) -> 46296 | AQ68: =IF(COUNTIF('同场线路Rotas do mesmo SC'!A:A,C68)>0,"Sim","Não") -> Não | AR68: =IF(COUNTIF(揽收业务网点!A:A,P68)>0,"Sim","Não") -> Sim
A69: SRTR22605722140 | B69: Concluído：已完成 | C69: STM-C514-0500-1 | D69: Horário padrão | E69: Entrega | F69: 1 | G69: 150 | H69: OGT4E97 | I69: 3/4 | J69: SERGIO MANUEL LIMA DA SILVA | K69: Transportadora-三方 | L69: ATIVA T | M69: CARLOS ALBERTO DOS SANTOS NUNES JUNIOR | N69: 994640724 | O69: 89000 | P69: PA STM | Q69: GP | R69: 777 | S69: 423 | T69: 2026-09-29 21:54:17 | U69: 2026-09-29 21:57:41 | V69: 4 | W69: Não | X69: 2026-09-29 22:01:32 | Y69: 2026-09-30 05:00:00 | Z69: 2026-09-29 22:28:03 | AA69: 2026-09-29 22:28:03 | AB69: 961468 | AC69: F ALQ FLUVIAL-PA | AD69: GP | AE69: 2026-10-01 06:00:00 | AF69: 2026-10-01 08:07:31 | AG69: 128 | AH69: 2026-10-01 08:07:31 | AI69: 2026-10-01 08:11:02 | AJ69: 6 | AK69: 2026-10-01 08:12:40 | AL69: 2026-10-01 08:36:11 | AM69: 24 | AN69: =IF(X69="",0,1) -> 1 | AO69: =IF(AI69="",0,1) -> 1 | AP69: =DATE(YEAR(AE69),MONTH(AE69),DAY(AE69)) -> 46296 | AQ69: =IF(COUNTIF('同场线路Rotas do mesmo SC'!A:A,C69)>0,"Sim","Não") -> Não | AR69: =IF(COUNTIF(揽收业务网点!A:A,P69)>0,"Sim","Não") -> Não
A70: SRTR22605722780 | B70: Concluído：已完成 | C70: S339-GRU-2030-1 | D70: Horário padrão | E70: Coleta | F70: 1 | G70: 106 | H70: UDC5H11 | I70: Toco | J70: BBR Agrolog Ltda | K70: Transportadora-三方 | L70: BBR LTDA | M70: LUCAS SOUSA TOMAZ DA PAZ | N70: 11996033567 | O70: 316371 | P70: SVT 02-SP | Q70: SPE | R70: 1297 | S70: 1297 | T70: 2026-09-30 18:43:13 | U70: 2026-09-30 20:53:24 | V70: 131 | W70: Não | X70: 2026-09-30 20:55:26 | Y70: 2026-09-30 20:30:00 | Z70: 2026-09-30 20:28:36 | AA70: 2026-09-30 20:28:36 | AB70: 30001 | AC70: SP GRU | AD70: SPE | AE70: 2026-10-01 00:30:00 | AF70: 2026-09-30 22:48:43 | AG70: -101 | AH70: 2026-09-30 22:48:43 | AI70: 2026-10-01 00:52:18 | AJ70: 126 | AK70: 2026-10-01 00:53:48 | AL70: 2026-10-01 22:35:00 | AM70: 1302 | AN70: =IF(X70="",0,1) -> 1 | AO70: =IF(AI70="",0,1) -> 1 | AP70: =DATE(YEAR(AE70),MONTH(AE70),DAY(AE70)) -> 46296 | AQ70: =IF(COUNTIF('同场线路Rotas do mesmo SC'!A:A,C70)>0,"Sim","Não") -> Não | AR70: =IF(COUNTIF(揽收业务网点!A:A,P70)>0,"Sim","Não") -> Sim
A71: SRTR22605723440 | B71: Concluído：已完成 | C71: CGE-M116-2200-1 | D71: Horário padrão | E71: Entrega | F71: 1 | G71: 322 | H71: GXM5977 | I71: Truck | J71: PEDRO LUCAS SIQUEIRA DA SILVA | K71: Transportadora-三方 | L71: PedroLucas | M71: CARLOS HENRIQUE NOGUEIRA GOMES | N71: 3799842986 | O71: 53102 | P71: MG CGE | Q71: MG | R71: 7181 | S71: 7144 | T71: 2026-09-30 15:01:00 | U71: 2026-09-30 21:24:24 | V71: 384 | W71: Não | X71: 2026-09-30 21:33:58 | Y71: 2026-09-30 22:00:00 | Z71: 2026-09-30 21:36:18 | AA71: 2026-09-30 21:36:18 | AB71: 533003 | AC71: DC GVR 001 | AD71: MG | AE71: 2026-10-01 04:00:00 | AF71: 2026-10-01 03:40:30 | AG71: -19 | AH71: 2026-10-01 03:40:30 | AI71: 2026-10-01 04:05:52 | AJ71: 28 | AK71: 2026-10-01 04:07:59 | AL71: 2026-10-01 10:11:52 | AM71: 364 | AN71: =IF(X71="",0,1) -> 1 | AO71: =IF(AI71="",0,1) -> 1 | AP71: =DATE(YEAR(AE71),MONTH(AE71),DAY(AE71)) -> 46296 | AQ71: =IF(COUNTIF('同场线路Rotas do mesmo SC'!A:A,C71)>0,"Sim","Não") -> Não | AR71: =IF(COUNTIF(揽收业务网点!A:A,P71)>0,"Sim","Não") -> Não
A72: SRTR22605723451 | B72: Concluído：已完成 | C72: CGE-M104-2200-1 | D72: Horário padrão | E72: Entrega | F72: 1 | G72: 460 | H72: TYP7D27 | I72: Truck | J72: MGL TRASNPORTES E SERVIÇOS | K72: Transportadora-三方 | L72: MGL | M72: ROBERT CHRISTIAN DE JESUS | N72: 31995713577 | O72: 53102 | P72: MG CGE | Q72: MG | R72: 6681 | S72: 6666 | T72: 2026-09-30 15:57:29 | U72: 2026-09-30 21:34:29 | V72: 337 | W72: Não | X72: 2026-09-30 21:35:55 | Y72: 2026-09-30 22:00:00 | Z72: 2026-09-30 21:44:02 | AA72: 2026-09-30 21:44:02 | AB72: 533001 | AC72: DC TFL 001 | AD72: MG | AE72: 2026-10-01 06:00:00 | AF72: 2026-10-01 06:22:49 | AG72: 23 | AH72: 2026-10-01 06:22:49 | AI72: 2026-10-01 06:53:00 | AJ72: 31 | AK72: 2026-10-01 06:53:33 | AL72: 2026-10-01 11:57:56 | AM72: 305 | AN72: =IF(X72="",0,1) -> 1 | AO72: =IF(AI72="",0,1) -> 1 | AP72: =DATE(YEAR(AE72),MONTH(AE72),DAY(AE72)) -> 46296 | AQ72: =IF(COUNTIF('同场线路Rotas do mesmo SC'!A:A,C72)>0,"Sim","Não") -> Não | AR72: =IF(COUNTIF(揽收业务网点!A:A,P72)>0,"Sim","Não") -> Não
A73: SRTR22605724311 | B73: Concluído：已完成 | C73: A210-A425-2300-1 | D73: Horário padrão | E73: Coleta | F73: 1 | G73: 130 | H73: IUA2F47 | I73: 3/4 | J73: 63.602.375 ALEX ROBSON DA SILV | K73: Transportadora-三方 | L73: ALEX | M73: ALEX ROBSON DA SILVA | N73: 54996060388 | O73: 154103 | P73: NPT -RS | Q73: PR | R73: 257 | S73: 257 | T73: 2026-09-30 08:30:22 | U73: 2026-09-30 08:30:25 | V73: 1 | W73: Não | Y73: 2026-09-30 23:00:00 | Z73: 2026-09-30 08:31:26 | AA73: 2026-09-30 08:31:26 | AB73: 155276 | AC73: DC CXJ01 | AD73: PR | AE73: 2026-10-01 01:10:00 | AF73: 2026-09-30 13:19:49 | AG73: -710 | AH73: 2026-09-30 13:19:49 | AN73: =IF(X73="",0,1) -> 0 | AO73: =IF(AI73="",0,1) -> 0 | AP73: =DATE(YEAR(AE73),MONTH(AE73),DAY(AE73)) -> 46296 | AQ73: =IF(COUNTIF('同场线路Rotas do mesmo SC'!A:A,C73)>0,"Sim","Não") -> Não | AR73: =IF(COUNTIF(揽收业务网点!A:A,P73)>0,"Sim","Não") -> Sim
A74: SRTR22605725840 | B74: Concluído：已完成 | C74: S117-BRE-2100-1 | D74: Horário padrão | E74: Coleta | F74: 1 | G74: 124 | H74: TIT7F87 | I74: 3/4 | J74: BBR Agrolog Ltda | K74: Transportadora-三方 | L74: BBR LTDA | M74: EMERSON FERREIRA DE SOUZA | N74: 11966043671 | O74: 313105 | P74: SSZ-SP | Q74: SPE | R74: 1425 | S74: 1425 | T74: 2026-09-30 20:36:29 | U74: 2026-09-30 20:39:52 | V74: 4 | W74: Não | X74: 2026-09-30 21:20:49 | Y74: 2026-09-30 21:00:00 | Z74: 2026-09-30 21:15:17 | AA74: 2026-09-30 21:15:17 | AB74: 31101 | AC74: SP BRE | AD74: SPS | AE74: 2026-10-01 00:30:00 | AF74: 2026-09-30 23:14:04 | AG74: -75 | AH74: 2026-09-30 23:14:04 | AI74: 2026-09-30 23:33:01 | AJ74: 30 | AK74: 2026-09-30 23:43:37 | AL74: 2026-10-01 14:35:02 | AM74: 892 | AN74: =IF(X74="",0,1) -> 1 | AO74: =IF(AI74="",0,1) -> 1 | AP74: =DATE(YEAR(AE74),MONTH(AE74),DAY(AE74)) -> 46296 | AQ74: =IF(COUNTIF('同场线路Rotas do mesmo SC'!A:A,C74)>0,"Sim","Não") -> Não | AR74: =IF(COUNTIF(揽收业务网点!A:A,P74)>0,"Sim","Não") -> Sim
A75: SRTR22605726480 | B75: Concluído：已完成 | C75: BNU-A404-B15-2131-1 | D75: Horário padrão | E75: Entrega | F75: 1 | G75: 330 | H75: UMK9G35 | I75: Truck | J75: C. R. DOS SANTOS TRANSPORTES | K75: Transportadora-三方 | L75: C. R. | M75: RENAN JONES DE SOUZA | N75: 47992103709 | O75: 14802 | P75: SC BNU | Q75: PR | R75: 3979 | S75: 3973 | T75: 2026-09-30 19:24:48 | U75: 2026-09-30 20:59:26 | V75: 95 | W75: Não | X75: 2026-09-30 21:37:03 | Y75: 2026-09-30 21:31:00 | Z75: 2026-09-30 19:50:22 | AA75: 2026-09-30 19:50:22 | AB75: 155255 | AC75: CFC-SC | AD75: PR | AE75: 2026-10-01 03:01:00 | AF75: 2026-10-01 03:12:40 | AG75: 12 | AH75: 2026-10-01 03:12:40 | AI75: 2026-10-01 03:13:57 | AJ75: 48 | AK75: 2026-10-01 03:59:50 | AL75: 2026-10-01 07:15:20 | AM75: 196 | AN75: =IF(X75="",0,1) -> 1 | AO75: =IF(AI75="",0,1) -> 1 | AP75: =DATE(YEAR(AE75),MONTH(AE75),DAY(AE75)) -> 46296 | AQ75: =IF(COUNTIF('同场线路Rotas do mesmo SC'!A:A,C75)>0,"Sim","Não") -> Não | AR75: =IF(COUNTIF(揽收业务网点!A:A,P75)>0,"Sim","Não") -> Não
A76: SRTR22605726900 | B76: Concluído：已完成 | C76: BNU-B03-A336-2230-1 | D76: Horário padrão | E76: Entrega | F76: 1 | G76: 390 | H76: MHR1F45 | I76: Truck | J76: C. R. DOS SANTOS TRANSPORTES | K76: Transportadora-三方 | L76: C. R. | M76: JULINHO FRANCISCO DE OLIVEIRA JUNIOR | N76: 47996417874 | O76: 14802 | P76: SC BNU | Q76: PR | R76: 6100 | S76: 6080 | T76: 2026-09-30 19:23:41 | U76: 2026-09-30 22:02:33 | V76: 159 | W76: Não | X76: 2026-09-30 22:17:09 | Y76: 2026-09-30 22:30:00 | Z76: 2026-09-30 19:57:59 | AA76: 2026-09-30 19:57:59 | AB76: 148004 | AC76: DC CCM-SC | AD76: PR | AE76: 2026-10-01 05:00:00 | AF76: 2026-10-01 03:18:30 | AG76: -101 | AH76: 2026-10-01 03:18:30 | AI76: 2026-10-01 04:06:18 | AJ76: 59 | AK76: 2026-10-01 04:16:38 | AL76: 2026-10-01 09:37:30 | AM76: 321 | AN76: =IF(X76="",0,1) -> 1 | AO76: =IF(AI76="",0,1) -> 1 | AP76: =DATE(YEAR(AE76),MONTH(AE76),DAY(AE76)) -> 46296 | AQ76: =IF(COUNTIF('同场线路Rotas do mesmo SC'!A:A,C76)>0,"Sim","Não") -> Não | AR76: =IF(COUNTIF(揽收业务网点!A:A,P76)>0,"Sim","Não") -> Não
A77: SRTR22605727060 | B77: Concluído：已完成 | C77: S414-BRE-2200-1 | D77: Horário padrão | E77: Coleta | F77: 1 | G77: 130 | H77: CUE1J71 | I77: Cavalo | J77: PACHECO E PACHECO | K77: Transportadora-三方 | L77: PACHECO | M77: MAURICIO DONIZETI CAVALHEIRO | N77: 11947961080 | O77: 311452 | P77: DC NOD-SP | Q77: SPS | R77: 4945 | S77: 4945 | T77: 2026-09-30 15:42:41 | U77: 2026-09-30 21:30:21 | V77: 348 | W77: Não | X77: 2026-09-30 21:54:37 | Y77: 2026-09-30 22:00:00 | Z77: 2026-09-30 21:53:49 | AA77: 2026-09-30 21:53:49 | AB77: 31101 | AC77: SP BRE | AD77: SPS | AE77: 2026-10-01 01:00:00 | AF77: 2026-10-01 00:23:13 | AG77: -36 | AH77: 2026-10-01 00:23:13 | AI77: 2026-10-01 04:55:52 | AJ77: 274 | AK77: 2026-10-01 04:56:16 | AL77: 2026-10-01 11:31:45 | AM77: 396 | AN77: =IF(X77="",0,1) -> 1 | AO77: =IF(AI77="",0,1) -> 1 | AP77: =DATE(YEAR(AE77),MONTH(AE77),DAY(AE77)) -> 46296 | AQ77: =IF(COUNTIF('同场线路Rotas do mesmo SC'!A:A,C77)>0,"Sim","Não") -> Não | AR77: =IF(COUNTIF(揽收业务网点!A:A,P77)>0,"Sim","Não") -> Sim
A78: SRTR22605727791 | B78: Concluído：已完成 | C78: BNU-A348-B219-A448-A413-2330-1 | D78: Horário padrão | E78: Entrega | F78: 1 | G78: 230 | H78: MEA6H88 | I78: Toco | J78: C. R. DOS SANTOS TRANSPORTES | K78: Transportadora-三方 | L78: C. R. | M78: CHARLES RICARDO DOS SANTOS | N78: 47991577485 | O78: 14802 | P78: SC BNU | Q78: PR | R78: 3457 | S78: 3454 | T78: 2026-09-30 19:30:56 | U78: 2026-09-30 23:03:58 | V78: 214 | W78: Não | X78: 2026-09-30 23:14:05 | Y78: 2026-09-30 23:30:00 | Z78: 2026-09-30 19:46:42 | AA78: 2026-09-30 19:46:42 | AB78: 155199 | AC78: IBB -SC | AD78: PR | AE78: 2026-10-01 03:20:00 | AF78: 2026-10-01 02:37:07 | AG78: -42 | AH78: 2026-10-01 02:37:07 | AI78: 2026-10-01 03:09:39 | AJ78: 72 | AK78: 2026-10-01 03:48:40 | AL78: 2026-10-01 05:36:59 | AM78: 109 | AN78: =IF(X78="",0,1) -> 1 | AO78: =IF(AI78="",0,1) -> 1 | AP78: =DATE(YEAR(AE78),MONTH(AE78),DAY(AE78)) -> 46296 | AQ78: =IF(COUNTIF('同场线路Rotas do mesmo SC'!A:A,C78)>0,"Sim","Não") -> Não | AR78: =IF(COUNTIF(揽收业务网点!A:A,P78)>0,"Sim","Não") -> Não
A79: SRTR22605728171 | B79: Concluído：已完成 | C79: M211-CHV-2110-2 | D79: Horário padrão | E79: Coleta | F79: 2 | G79: 130 | H79: TZZ6D87 | I79: Truck | J79: VIA LACTEA DISTRIBUIDORA LTDA | K79: Transportadora-三方 | L79: VIA LACTEA | M79: EVERTON GOMES BRITO | N79: 31998361819 | O79: 537103 | P79: DIQ -MG | Q79: MG | R79: 5125 | S79: 5125 | T79: 2026-09-30 12:52:57 | U79: 2026-09-30 20:04:38 | V79: 432 | W79: Não | X79: 2026-09-30 20:36:56 | Y79: 2026-09-30 21:10:00 | Z79: 2026-09-30 20:34:23 | AA79: 2026-09-30 20:34:23 | AB79: 531259 | AC79: MG CHV | AD79: MG | AE79: 2026-10-01 00:00:00 | AF79: 2026-09-30 22:22:37 | AG79: -97 | AH79: 2026-09-30 22:22:37 | AI79: 2026-09-30 22:35:39 | AJ79: 14 | AK79: 2026-09-30 22:35:54 | AL79: 2026-10-01 00:56:56 | AM79: 142 | AN79: =IF(X79="",0,1) -> 1 | AO79: =IF(AI79="",0,1) -> 1 | AP79: =DATE(YEAR(AE79),MONTH(AE79),DAY(AE79)) -> 46296 | AQ79: =IF(COUNTIF('同场线路Rotas do mesmo SC'!A:A,C79)>0,"Sim","Não") -> Não | AR79: =IF(COUNTIF(揽收业务网点!A:A,P79)>0,"Sim","Não") -> Sim
A80: SRTR22605728740 | B80: Concluído：已完成 | C80: BRE-S414-2200-9 | D80: Horário padrão | E80: Entrega | F80: 9 | G80: 129 | H80: FMH6B45 | I80: Cavalo | J80: EASY CARGO SOLUÇOES | K80: Transportadora-三方 | L80: EASY | M80: MARCELO WILLIAN TILTACKI | N80: 11943291145 | O80: 31101 | P80: SP BRE | Q80: SPS | R80: 9523 | S80: 9517 | T80: 2026-09-30 16:50:35 | U80: 2026-09-30 21:31:43 | V80: 282 | W80: Não | X80: 2026-09-30 21:44:46 | Y80: 2026-09-30 22:00:00 | Z80: 2026-09-30 22:13:10 | AA80: 2026-09-30 22:13:10 | AB80: 311452 | AC80: DC NOD-SP | AD80: SPS | AE80: 2026-10-01 01:00:00 | AF80: 2026-10-01 00:13:00 | AG80: -47 | AH80: 2026-10-01 00:13:00 | AJ80: 565 | AK80: 2026-10-01 09:37:35 | AL80: 2026-10-05 15:20:20 | AM80: 6103 | AN80: =IF(X80="",0,1) -> 1 | AO80: =IF(AI80="",0,1) -> 0 | AP80: =DATE(YEAR(AE80),MONTH(AE80),DAY(AE80)) -> 46296 | AQ80: =IF(COUNTIF('同场线路Rotas do mesmo SC'!A:A,C80)>0,"Sim","Não") -> Não | AR80: =IF(COUNTIF(揽收业务网点!A:A,P80)>0,"Sim","Não") -> Não
A81: SRTR22605728960 | B81: Concluído：已完成 | C81: MAO1-C610-0700-1 | D81: Horário padrão | E81: Entrega | F81: 1 | G81: 500 | H81: JWP3563 | I81: 3/4 | J81: DARLISSON DANIEL MARQUES SOUSA | K81: Transportadora-三方 | L81: DARLISSON | M81: DARLISSON DANIEL MARQUES SOUSA | N81: 92985204417 | O81: 89202 | P81: DC MAO-AM | Q81: GP | R81: 378 | S81: 215 | T81: 2026-09-30 06:55:21 | U81: 2026-09-30 06:55:28 | V81: 1 | W81: Não | X81: 2026-09-30 06:58:00 | Y81: 2026-09-30 07:00:00 | Z81: 2026-09-30 06:56:24 | AA81: 2026-09-30 06:56:24 | AB81: 961564 | AC81: COA FLUVIAL-AM | AD81: GP | AE81: 2026-10-03 07:00:00 | AF81: 2026-10-01 09:00:00 | AG81: -2760 | AH81: 2026-10-01 09:00:00 | AI81: 2026-10-02 08:13:01 | AJ81: 1396 | AK81: 2026-10-02 08:15:12 | AL81: 2026-10-02 08:57:12 | AM81: 43 | AN81: =IF(X81="",0,1) -> 1 | AO81: =IF(AI81="",0,1) -> 1 | AP81: =DATE(YEAR(AE81),MONTH(AE81),DAY(AE81)) -> 46298 | AQ81: =IF(COUNTIF('同场线路Rotas do mesmo SC'!A:A,C81)>0,"Sim","Não") -> Não | AR81: =IF(COUNTIF(揽收业务网点!A:A,P81)>0,"Sim","Não") -> Não
A82: SRTR22605734820 | B82: Concluído：已完成 | C82: F77-F177-0900-1 | D82: Horário padrão | E82: Entrega | F82: 1 | G82: 1 | H82: KGN2691 | I82: VUC | J82: GASPAR FERREIRA DA SILVA FILHO | K82: Transportadora-三方 | L82: GASPARFSF | M82: GASPAR FERREIRA DA SILVA FILHO | N82: 84998355215 | O82: 884002 | P82: DC NAT-RN | Q82: CE | R82: 172 | S82: 156 | T82: 2026-10-01 04:41:03 | U82: 2026-10-01 07:29:44 | V82: 169 | W82: Não | X82: 2026-10-01 04:44:36 | Y82: 2026-10-01 09:00:00 | Z82: 2026-10-01 04:45:10 | AA82: 2026-10-01 04:45:10 | AB82: 884108 | AC82: NAT -RN | AD82: CE | AE82: 2026-10-01 09:10:00 | AF82: 2026-10-01 05:53:49 | AG82: -196 | AH82: 2026-10-01 05:53:49 | AI82: 2026-10-01 06:01:34 | AJ82: 41 | AK82: 2026-10-01 06:34:49 | AL82: 2026-10-01 07:40:29 | AM82: 66 | AN82: =IF(X82="",0,1) -> 1 | AO82: =IF(AI82="",0,1) -> 1 | AP82: =DATE(YEAR(AE82),MONTH(AE82),DAY(AE82)) -> 46296 | AQ82: =IF(COUNTIF('同场线路Rotas do mesmo SC'!A:A,C82)>0,"Sim","Não") -> Não | AR82: =IF(COUNTIF(揽收业务网点!A:A,P82)>0,"Sim","Não") -> Não
A83: SRTR22605734980 | B83: Concluído：已完成 | C83: FOR-G106-2100-1 | D83: Horário padrão | E83: Entrega | F83: 1 | G83: 230 | H83: FKT9J34 | I83: Truck | J83: ADAMO SAVIO DIAS XAVIER | K83: Transportadora-三方 | L83: ADAMOSAVIO | M83: JOAO VICTOR DE MEDEIROS FERNANDES | N83: 84921588245 | O83: 88501 | P83: CE FOR | Q83: CE | R83: 2835 | S83: 2056 | T83: 2026-10-01 20:13:06 | U83: 2026-10-01 20:50:24 | V83: 38 | W83: Não | X83: 2026-10-01 21:03:00 | Y83: 2026-10-01 21:00:00 | Z83: 2026-10-01 20:54:29 | AA83: 2026-10-01 20:54:29 | AB83: 884003 | AC83: DC MVF-RN | AD83: CE | AE83: 2026-10-02 01:00:00 | AF83: 2026-10-02 00:57:00 | AG83: -3 | AH83: 2026-10-02 00:57:00 | AI83: 2026-10-02 02:15:24 | AJ83: 73 | AK83: 2026-10-02 02:09:04 | AL83: 2026-10-02 06:02:53 | AM83: 234 | AN83: =IF(X83="",0,1) -> 1 | AO83: =IF(AI83="",0,1) -> 1 | AP83: =DATE(YEAR(AE83),MONTH(AE83),DAY(AE83)) -> 46297 | AQ83: =IF(COUNTIF('同场线路Rotas do mesmo SC'!A:A,C83)>0,"Sim","Não") -> Não | AR83: =IF(COUNTIF(揽收业务网点!A:A,P83)>0,"Sim","Não") -> Não
A84: SRTR22605734991 | B84: Concluído：已完成 | C84: RBR-O01-0850-1 | D84: Horário padrão | E84: Entrega | F84: 1 | G84: 90 | H84: RWR5A52 | I84: Utilitário | J84: JET EXPRESS GO | K84: Frota-自营 | L84: JET GO | M84: CLOVIS RODRIGUES DA SILVA JUNIOR | N84: 61995733700 | O84: 78130 | P84: AC RBR | Q84: GP | R84: 1351 | S84: 1285 | T84: 2026-10-01 01:39:39 | U84: 2026-10-01 01:39:58 | V84: 1 | W84: Não | X84: 2026-10-01 01:40:40 | Y84: 2026-10-01 08:50:00 | Z84: 2026-10-01 01:40:40 | AA84: 2026-10-01 01:40:40 | AB84: 868100 | AC84: RBR -AC | AD84: GP | AE84: 2026-10-01 13:20:00 | AF84: 2026-10-01 01:55:36 | AG84: -684 | AH84: 2026-10-01 01:55:36 | AI84: 2026-10-01 06:19:50 | AJ84: 262 | AK84: 2026-10-01 06:16:42 | AL84: 2026-10-01 07:45:17 | AM84: 89 | AN84: =IF(X84="",0,1) -> 1 | AO84: =IF(AI84="",0,1) -> 1 | AP84: =DATE(YEAR(AE84),MONTH(AE84),DAY(AE84)) -> 46296 | AQ84: =IF(COUNTIF('同场线路Rotas do mesmo SC'!A:A,C84)>0,"Sim","Não") -> Não | AR84: =IF(COUNTIF(揽收业务网点!A:A,P84)>0,"Sim","Não") -> Não
A85: SRTR22605735020 | B85: Concluído：已完成 | C85: SJS-P103-0400-1 | D85: Horário padrão | E85: Entrega | F85: 1 | G85: 30 | H85: AAH4C81 | I85: 3/4 | J85: SAN JANUARIO TRANSPORTES LTDA | K85: Transportadora-三方 | L85: SAN JANUAR | M85: FERNANDO PANCHINIAK | N85: 41996230859 | O85: 24101 | P85: PR SJS | Q85: PR | R85: 2774 | S85: 2759 | T85: 2026-09-30 12:48:14 | U85: 2026-10-01 03:43:21 | V85: 896 | W85: Não | X85: 2026-10-01 03:48:34 | Y85: 2026-10-01 04:00:00 | Z85: 2026-10-01 03:36:01 | AA85: 2026-10-01 03:36:01 | AB85: 241110 | AC85: CWB 03-PR | AD85: PR | AE85: 2026-10-01 04:30:00 | AF85: 2026-10-01 04:27:00 | AG85: -3 | AH85: 2026-10-01 04:27:00 | AI85: 2026-10-01 05:00:25 | AJ85: 49 | AK85: 2026-10-01 05:15:57 | AL85: 2026-10-01 09:38:23 | AM85: 263 | AN85: =IF(X85="",0,1) -> 1 | AO85: =IF(AI85="",0,1) -> 1 | AP85: =DATE(YEAR(AE85),MONTH(AE85),DAY(AE85)) -> 46296 | AQ85: =IF(COUNTIF('同场线路Rotas do mesmo SC'!A:A,C85)>0,"Sim","Não") -> Não | AR85: =IF(COUNTIF(揽收业务网点!A:A,P85)>0,"Sim","Não") -> Não
A86: SRTR22605735120 | B86: Concluído：已完成 | C86: H104-H202-2000-1 | D86: Horário padrão | E86: Entrega | F86: 1 | G86: 391 | H86: PSP2F60 | I86: 3/4 | J86: JOSE RONALDO ROCHA DE SOUSA | K86: Transportadora-三方 | L86: JOSE RONAL | M86: JOSE RONALDO ROCHA DE SOUSA | N86: 99991361661 | O86: 899002 | P86: DC IMP-MA | Q86: CE | R86: 1086 | S86: 708 | T86: 2026-10-01 14:12:08 | U86: 2026-10-01 14:36:46 | V86: 25 | W86: Não | X86: 2026-10-01 15:56:01 | Y86: 2026-10-01 20:00:00 | Z86: 2026-10-01 16:02:07 | AA86: 2026-10-01 16:02:07 | AB86: 899107 | AC86: BSS -MA | AD86: CE | AE86: 2026-10-02 04:00:00 | AF86: 2026-10-02 01:25:20 | AG86: -154 | AH86: 2026-10-02 01:25:20 | AI86: 2026-10-02 02:36:49 | AJ86: 113 | AK86: 2026-10-02 03:18:14 | AL86: 2026-10-02 03:58:35 | AM86: 41 | AN86: =IF(X86="",0,1) -> 1 | AO86: =IF(AI86="",0,1) -> 1 | AP86: =DATE(YEAR(AE86),MONTH(AE86),DAY(AE86)) -> 46297 | AQ86: =IF(COUNTIF('同场线路Rotas do mesmo SC'!A:A,C86)>0,"Sim","Não") -> Não | AR86: =IF(COUNTIF(揽收业务网点!A:A,P86)>0,"Sim","Não") -> Não
A87: SRTR22605735211 | B87: Concluído：已完成 | C87: ANA-I219-I235-I218-C477-I236-I254-C325-C639-0330-1 | D87: Horário padrão | E87: Entrega | F87: 1 | G87: 160 | H87: FWC0C52 | I87: Truck | J87: JET EXPRESS PA | K87: Frota-自营 | L87: JET PA | M87: DIEGO MACIEL DE SOUZA | N87: 982225551 | O87: 89101 | P87: PA ANA | Q87: GP | R87: 1958 | S87: 1488 | T87: 2026-09-30 11:52:05 | U87: 2026-10-01 00:58:35 | V87: 787 | W87: Não | X87: 2026-10-01 02:15:47 | Y87: 2026-10-01 03:30:00 | Z87: 2026-10-01 03:03:49 | AA87: 2026-10-01 03:03:49 | AB87: 891114 | AC87: CPN -PA | AD87: GP | AE87: 2026-10-01 08:50:00 | AF87: 2026-10-01 05:11:34 | AG87: -218 | AH87: 2026-10-01 05:11:34 | AI87: 2026-10-01 05:14:30 | AJ87: 23 | AK87: 2026-10-01 05:34:21 | AL87: 2026-10-01 06:00:59 | AM87: 27 | AN87: =IF(X87="",0,1) -> 1 | AO87: =IF(AI87="",0,1) -> 1 | AP87: =DATE(YEAR(AE87),MONTH(AE87),DAY(AE87)) -> 46296 | AQ87: =IF(COUNTIF('同场线路Rotas do mesmo SC'!A:A,C87)>0,"Sim","Não") -> Não | AR87: =IF(COUNTIF(揽收业务网点!A:A,P87)>0,"Sim","Não") -> Não
A88: SRTR22605735231 | B88: Concluído：已完成 | C88: NSR-A425-0301-1 | D88: Horário padrão | E88: Entrega | F88: 2 | G88: 120 | H88: IRQ4H91 | I88: Truck | J88: ALESSANDRO HAHN DA SILVA | K88: Transportadora-三方 | L88: ALHS | M88: BEM HUR DOS SANTOS DA SILVA | N88: 51984941633 | O88: 15101 | P88: RS NSR | Q88: PR | R88: 9983 | S88: 9849 | T88: 2026-09-30 19:13:59 | U88: 2026-10-01 01:59:46 | V88: 406 | W88: Não | X88: 2026-10-01 02:31:39 | Y88: 2026-10-01 03:01:00 | Z88: 2026-09-30 23:18:23 | AA88: 2026-09-30 23:18:23 | AB88: 155276 | AC88: DC CXJ01 | AD88: PR | AE88: 2026-10-01 05:01:00 | AF88: 2026-10-01 05:24:19 | AG88: 24 | AH88: 2026-10-01 05:24:19 | AI88: 2026-10-01 05:28:33 | AJ88: 130 | AK88: 2026-10-01 07:33:40 | AL88: 2026-10-01 11:29:49 | AM88: 237 | AN88: =IF(X88="",0,1) -> 1 | AO88: =IF(AI88="",0,1) -> 1 | AP88: =DATE(YEAR(AE88),MONTH(AE88),DAY(AE88)) -> 46296 | AQ88: =IF(COUNTIF('同场线路Rotas do mesmo SC'!A:A,C88)>0,"Sim","Não") -> Não | AR88: =IF(COUNTIF(揽收业务网点!A:A,P88)>0,"Sim","Não") -> Não
A89: SRTR22605735271 | B89: Concluído：已完成 | C89: F131-F237-0600-1 | D89: Horário padrão | E89: Entrega | F89: 1 | G89: 72 | H89: NXW2I51 | I89: 3/4 | J89: JOAO FELICIANO POLICARPO | K89: Transportadora-三方 | L89: JOAO F | M89: JOAO FELICIANO POLICARPO | N89: 82999875331 | O89: 782003 | P89: DC MCZ-AL | Q89: BA | R89: 686 | S89: 527 | T89: 2026-09-30 14:24:36 | U89: 2026-09-30 14:43:10 | V89: 19 | W89: Não | X89: 2026-09-30 14:57:14 | Y89: 2026-10-01 06:00:00 | Z89: 2026-10-01 03:06:20 | AA89: 2026-10-01 03:06:20 | AB89: 782111 | AC89: MDC -AL | AD89: BA | AE89: 2026-10-01 07:40:00 | AF89: 2026-10-01 04:54:12 | AG89: -165 | AH89: 2026-10-01 04:54:12 | AI89: 2026-10-01 05:09:48 | AJ89: 24 | AK89: 2026-10-01 05:18:01 | AL89: 2026-10-01 08:23:27 | AM89: 186 | AN89: =IF(X89="",0,1) -> 1 | AO89: =IF(AI89="",0,1) -> 1 | AP89: =DATE(YEAR(AE89),MONTH(AE89),DAY(AE89)) -> 46296 | AQ89: =IF(COUNTIF('同场线路Rotas do mesmo SC'!A:A,C89)>0,"Sim","Não") -> Não | AR89: =IF(COUNTIF(揽收业务网点!A:A,P89)>0,"Sim","Não") -> Não
A90: SRTR22605735280 | B90: Concluído：已完成 | C90: CGB-J228-0200-1 | D90: Horário padrão | E90: Entrega | F90: 1 | G90: 800 | H90: SDM3C13 | I90: Truck | J90: DK EVOLUTION TRANSPORTES LTDA | K90: Transportadora-三方 | L90: DKET | M90: REDSON ROSSE NOLETO DA ROCHA | N90: 61984924397 | O90: 86501 | P90: MT CGB | Q90: GP | R90: 3065 | S90: 2660 | T90: 2026-09-30 19:14:04 | U90: 2026-09-30 23:41:52 | V90: 268 | W90: Não | X90: 2026-10-01 02:00:25 | Y90: 2026-10-01 02:00:00 | Z90: 2026-10-01 02:14:42 | AA90: 2026-10-01 02:14:42 | AB90: 866009 | AC90: DC JUI-MT | AD90: GP | AE90: 2026-10-01 18:00:00 | AF90: 2026-10-01 13:22:51 | AG90: -277 | AH90: 2026-10-01 13:22:51 | AI90: 2026-10-01 15:59:11 | AJ90: 166 | AK90: 2026-10-01 16:08:42 | AL90: 2026-10-01 19:43:01 | AM90: 215 | AN90: =IF(X90="",0,1) -> 1 | AO90: =IF(AI90="",0,1) -> 1 | AP90: =DATE(YEAR(AE90),MONTH(AE90),DAY(AE90)) -> 46296 | AQ90: =IF(COUNTIF('同场线路Rotas do mesmo SC'!A:A,C90)>0,"Sim","Não") -> Não | AR90: =IF(COUNTIF(揽收业务网点!A:A,P90)>0,"Sim","Não") -> Não
A91: SRTR22605735291 | B91: Concluído：已完成 | C91: ANA-I243-I223-0330-1 | D91: Horário padrão | E91: Entrega | F91: 1 | G91: 6.2 | H91: FIY8B74 | I91: Truck | J91: JET EXPRESS PA | K91: Frota-自营 | L91: JET PA | M91: DAVID NATAN SILVA COSTA | N91: 91981149748 | O91: 89101 | P91: PA ANA | Q91: GP | R91: 1529 | S91: 1461 | T91: 2026-09-30 11:57:37 | U91: 2026-10-01 01:02:03 | V91: 785 | W91: Não | X91: 2026-10-01 02:04:38 | Y91: 2026-10-01 03:30:00 | Z91: 2026-10-01 03:13:06 | AA91: 2026-10-01 03:13:06 | AB91: 891128 | AC91: MRM -PA | AD91: GP | AE91: 2026-10-01 04:00:00 | AF91: 2026-10-01 04:14:08 | AG91: 15 | AH91: 2026-10-01 04:14:08 | AI91: 2026-10-01 04:14:45 | AJ91: 19 | AK91: 2026-10-01 04:32:31 | AL91: 2026-10-01 05:27:54 | AM91: 56 | AN91: =IF(X91="",0,1) -> 1 | AO91: =IF(AI91="",0,1) -> 1 | AP91: =DATE(YEAR(AE91),MONTH(AE91),DAY(AE91)) -> 46296 | AQ91: =IF(COUNTIF('同场线路Rotas do mesmo SC'!A:A,C91)>0,"Sim","Não") -> Não | AR91: =IF(COUNTIF(揽收业务网点!A:A,P91)>0,"Sim","Não") -> Não
A92: SRTR22605735320 | B92: Concluído：已完成 | C92: S166-BRE-2200-1 | D92: Horário padrão | E92: Coleta | F92: 1 | G92: 21 | H92: UEE4D11 | I92: VUC | J92: JET EXPRESS (YUNYI) | K92: Frota-自营 | L92: YUNYI | M92: RicardoAlexandredaSilva | N92: 11997851607 | O92: 311185 | P92: PA CEA-SP | Q92: SPS | R92: 2520 | S92: 2520 | T92: 2026-10-01 08:31:40 | U92: 2026-10-01 21:47:41 | V92: 797 | W92: Não | X92: 2026-10-01 21:55:51 | Y92: 2026-10-01 22:00:00 | Z92: 2026-10-01 17:55:30 | AA92: 2026-10-01 17:55:30 | AB92: 31101 | AC92: SP BRE | AD92: SPS | AE92: 2026-10-01 23:00:00 | AF92: 2026-10-01 22:51:07 | AG92: -8 | AH92: 2026-10-01 22:51:07 | AI92: 2026-10-01 23:25:54 | AJ92: 54 | AK92: 2026-10-01 23:44:19 | AL92: 2026-10-03 10:46:54 | AM92: 2103 | AN92: =IF(X92="",0,1) -> 1 | AO92: =IF(AI92="",0,1) -> 1 | AP92: =DATE(YEAR(AE92),MONTH(AE92),DAY(AE92)) -> 46296 | AQ92: =IF(COUNTIF('同场线路Rotas do mesmo SC'!A:A,C92)>0,"Sim","Não") -> Não | AR92: =IF(COUNTIF(揽收业务网点!A:A,P92)>0,"Sim","Não") -> Sim
... A99: SRTR22605735571 | B99: Concluído：已完成 | C99: JGS-F240-F166-F232-0401-1 | D99: Horário padrão | E99: Entrega | F99: 1 | G99: 15 | H99: ISS9D80 | I99: HR | J99: JONATAS LOURAN DA SILVA | K99: Transportadora-三方 | L99: JONAS | M99: BRUNO PEREIRA DE OLIVEIRA GUEDES | N99: 985083775 | O99: 78101 | P99: PE JGS | Q99: CE | R99: 1713 | S99: 1360 | T99: 2026-09-30 23:10:05 | U99: 2026-10-01 02:45:19 | V99: 216 | W99: Não | X99: 2026-10-01 03:09:57 | Y99: 2026-10-01 04:01:00 | Z99: 2026-10-01 01:51:39 | AA99: 2026-10-01 01:51:39 | AB99: 781123 | AC99: RIPT -PE | AD99: CE | AE99: 2026-10-01 05:31:00 | AF99: 2026-10-01 04:25:21 | AG99: -65 | AH99: 2026-10-01 04:25:21 | AI99: 2026-10-01 05:29:49 | AJ99: 82 | AK99: 2026-10-01 05:46:24 | AL99: 2026-10-01 13:26:52 | AM99: 461 | AN99: =IF(X99="",0,1) -> 1 | AO99: =IF(AI99="",0,1) -> 1 | AP99: =DATE(YEAR(AE99),MONTH(AE99),DAY(AE99)) -> 46296 | AQ99: =IF(COUNTIF('同场线路Rotas do mesmo SC'!A:A,C99)>0,"Sim","Não") -> Não | AR99: =IF(COUNTIF(揽收业务网点!A:A,P99)>0,"Sim","Não") -> Não
A100: SRTR22605735571 | B100: Concluído：已完成 | C100: JGS-F240-F166-F232-0401-1 | D100: Horário padrão | E100: Entrega | F100: 1 | G100: 15 | H100: ISS9D80 | I100: HR | J100: JONATAS LOURAN DA SILVA | K100: Transportadora-三方 | L100: JONAS | M100: BRUNO PEREIRA DE OLIVEIRA GUEDES | N100: 985083775 | O100: 781123 | P100: RIPT -PE | Q100: CE | R100: 66 | S100: 66 | T100: 2026-10-01 05:30:13 | U100: 2026-10-01 05:30:13 | V100: 0 | W100: Não | X100: 2026-10-01 05:32:13 | Y100: 2026-10-01 06:01:00 | Z100: 2026-10-01 04:26:00 | AA100: 2026-10-01 04:26:00 | AB100: 781186 | AC100: RPR-PE | AD100: CE | AE100: 2026-10-01 06:46:00 | AF100: 2026-10-01 06:00:24 | AG100: -45 | AH100: 2026-10-01 06:00:24 | AJ100: 67 | AK100: 2026-10-01 07:07:05 | AL100: 2026-10-01 07:48:57 | AM100: 42 | AN100: =IF(X100="",0,1) -> 1 | AO100: =IF(AI100="",0,1) -> 0 | AP100: =DATE(YEAR(AE100),MONTH(AE100),DAY(AE100)) -> 46296 | AQ100: =IF(COUNTIF('同场线路Rotas do mesmo SC'!A:A,C100)>0,"Sim","Não") -> Não | AR100: =IF(COUNTIF(揽收业务网点!A:A,P100)>0,"Sim","Não") -> Não
A101: SRTR22605735580 | B101: Concluído：已完成 | C101: H239-H230-0700-1 | D101: Horário padrão | E101: Entrega | F101: 1 | G101: 183 | H101: PSK5E73 | I101: HR | J101: GIANNY ALMEIDA DOS SANTOS ABRE | K101: Transportadora-三方 | L101: GIANNY ALM | M101: LUCAS DANIEL TOMAZ DO NASCIMENTO | N101: 86998586769 | O101: 886106 | P101: PHB -PI | Q101: CE | R101: 985 | S101: 648 | T101: 2026-10-01 00:55:38 | U101: 2026-10-01 00:56:24 | V101: 1 | W101: Não | X101: 2026-10-01 01:10:53 | Y101: 2026-10-01 07:00:00 | Z101: 2026-10-01 01:11:31 | AA101: 2026-10-01 01:11:31 | AB101: 898112 | AC101: BRB -MA | AD101: CE | AE101: 2026-10-01 10:00:00 | AF101: 2026-10-01 05:06:25 | AG101: -293 | AH101: 2026-10-01 05:06:25 | AI101: 2026-10-01 06:42:59 | AJ101: 98 | AK101: 2026-10-01 06:43:29 | AL101: 2026-10-01 08:06:12 | AM101: 83 | AN101: =IF(X101="",0,1) -> 1 | AO101: =IF(AI101="",0,1) -> 1 | AP101: =DATE(YEAR(AE101),MONTH(AE101),DAY(AE101)) -> 46296 | AQ101: =IF(COUNTIF('同场线路Rotas do mesmo SC'!A:A,C101)>0,"Sim","Não") -> Não | AR101: =IF(COUNTIF(揽收业务网点!A:A,P101)>0,"Sim","Não") -> Não
A102: SRTR22605735591 | B102: Concluído：已完成 | C102: JGS-F229-F165-0400-1 | D102: Horário padrão | E102: Entrega | F102: 1 | G102: 22 | H102: NQJ2C06 | I102: 3/4 | J102: JONATAS LOURAN DA SILVA | K102: Transportadora-三方 | L102: JONAS | M102: CARLOS ROBERTO SILVA DOS SANTOS | N102: 8179058684 | O102: 78101 | P102: PE JGS | Q102: CE | R102: 1402 | S102: 1296 | T102: 2026-10-01 00:36:00 | U102: 2026-10-01 01:08:03 | V102: 33 | W102: Não | X102: 2026-10-01 02:13:53 | Y102: 2026-10-01 04:00:00 | Z102: 2026-10-01 02:01:42 | AA102: 2026-10-01 02:01:42 | AB102: 781117 | AC102: RCN -PE | AD102: CE | AE102: 2026-10-01 05:28:00 | AF102: 2026-10-01 05:17:51 | AG102: -10 | AH102: 2026-10-01 05:17:51 | AI102: 2026-10-01 05:31:02 | AJ102: 67 | AK102: 2026-10-01 06:23:59 | AL102: 2026-10-01 08:04:33 | AM102: 101 | AN102: =IF(X102="",0,1) -> 1 | AO102: =IF(AI102="",0,1) -> 1 | AP102: =DATE(YEAR(AE102),MONTH(AE102),DAY(AE102)) -> 46296 | AQ102: =IF(COUNTIF('同场线路Rotas do mesmo SC'!A:A,C102)>0,"Sim","Não") -> Não | AR102: =IF(COUNTIF(揽收业务网点!A:A,P102)>0,"Sim","Não") -> Não
A103: SRTR22605735591 | B103: Concluído：已完成 | C103: JGS-F229-F165-0400-1 | D103: Horário padrão | E103: Entrega | F103: 1 | G103: 10 | H103: NQJ2C06 | I103: 3/4 | J103: JONATAS LOURAN DA SILVA | K103: Transportadora-三方 | L103: JONAS | M103: CARLOS ROBERTO SILVA DOS SANTOS | N103: 8179058684 | O103: 781117 | P103: RCN -PE | Q103: CE | R103: 57 | S103: 57 | T103: 2026-10-01 05:39:44 | U103: 2026-10-01 05:39:44 | V103: 0 | W103: Não | X103: 2026-10-01 05:42:20 | Y103: 2026-10-01 05:58:00 | Z103: 2026-10-01 05:47:02 | AA103: 2026-10-01 05:47:02 | AB103: 781185 | AC103: RCG-PE | AD103: CE | AE103: 2026-10-01 06:28:00 | AF103: 2026-10-01 05:54:20 | AG103: -33 | AH103: 2026-10-01 05:54:20 | AI103: 2026-10-01 07:03:00 | AJ103: 70 | AK103: 2026-10-01 07:03:21 | AL103: 2026-10-01 09:02:11 | AM103: 119 | AN103: =IF(X103="",0,1) -> 1 | AO103: =IF(AI103="",0,1) -> 1 | AP103: =DATE(YEAR(AE103),MONTH(AE103),DAY(AE103)) -> 46296 | AQ103: =IF(COUNTIF('同场线路Rotas do mesmo SC'!A:A,C103)>0,"Sim","Não") -> Não | AR103: =IF(COUNTIF(揽收业务网点!A:A,P103)>0,"Sim","Não") -> Não
A104: SRTR22605735611 | B104: Concluído：已完成 | C104: S172-BRE-2200-2 | D104: Horário padrão | E104: Coleta | F104: 2 | G104: 18 | H104: FHD3G08 | I104: Toco | J104: Acrion Express Logistica | K104: Transportadora-三方 | L104: ACRION | M104: RODRIGO GALVÃO DE ARAUJO | N104: 957458406 | O104: 311189 | P104: PA NESTLE-SP | Q104: SPS | R104: 571 | S104: 507 | T104: 2026-10-01 17:00:38 | U104: 2026-10-01 20:48:42 | V104: 229 | W104: Não | X104: 2026-10-01 21:18:27 | Y104: 2026-10-01 22:00:00 | Z104: 2026-10-01 21:00:34 | AA104: 2026-10-01 21:00:34 | AB104: 31101 | AC104: SP BRE | AD104: SPS | AE104: 2026-10-01 22:45:00 | AF104: 2026-10-01 21:53:25 | AG104: -51 | AH104: 2026-10-01 21:53:25 | AI104: 2026-10-02 02:31:17 | AJ104: 281 | AK104: 2026-10-02 02:34:18 | AL104: 2026-10-02 02:52:57 | AM104: 19 | AN104: =IF(X104="",0,1) -> 1 | AO104: =IF(AI104="",0,1) -> 1 | AP104: =DATE(YEAR(AE104),MONTH(AE104),DAY(AE104)) -> 46296 | AQ104: =IF(COUNTIF('同场线路Rotas do mesmo SC'!A:A,C104)>0,"Sim","Não") -> Não | AR104: =IF(COUNTIF(揽收业务网点!A:A,P104)>0,"Sim","Não") -> Sim
A105: SRTR22605735640 | B105: Concluído：已完成 | C105: ANA-I269-0600-1 | D105: Horário padrão | E105: Entrega | F105: 1 | G105: 600 | H105: 0920411 | I105: Barco | J105: NV IRMAOS SANTANA /ANA BEATRIZ | K105: Transportadora-三方 | L105: AnaBEATRIZ | M105: ALANA OLIVEIRA DO NASCIMENTO | N105: 96991413173 | O105: 89101 | P105: PA ANA | Q105: GP | R105: 2056 | S105: 1283 | T105: 2026-09-30 11:55:36 | U105: 2026-10-01 01:31:28 | V105: 816 | W105: Não | X105: 2026-10-01 02:49:16 | Y105: 2026-10-01 06:00:00 | Z105: 2026-10-01 02:49:16 | AA105: 2026-10-01 02:49:16 | AB105: 896104 | AC105: MCP FLUVIAL -AP | AD105: GP | AE105: 2026-10-02 23:59:00 | AF105: 2026-10-02 11:42:00 | AG105: -737 | AH105: 2026-10-02 11:42:00 | AI105: 2026-10-02 19:59:32 | AJ105: 518 | AK105: 2026-10-02 20:19:35 | AL105: 2026-10-02 22:13:13 | AM105: 114 | AN105: =IF(X105="",0,1) -> 1 | AO105: =IF(AI105="",0,1) -> 1 | AP105: =DATE(YEAR(AE105),MONTH(AE105),DAY(AE105)) -> 46297 | AQ105: =IF(COUNTIF('同场线路Rotas do mesmo SC'!A:A,C105)>0,"Sim","Não") -> Não | AR105: =IF(COUNTIF(揽收业务网点!A:A,P105)>0,"Sim","Não") -> Não
A106: SRTR22605735651 | B106: Concluído：已完成 | C106: S172-BRE-1700-1 | D106: Horário padrão | E106: Coleta | F106: 1 | G106: 18 | H106: EUY1E89 | I106: Toco | J106: CEOS EXPRESS | K106: Transportadora-三方 | L106: CEOS EXPRE | M106: MARIO FERNANDO EUGENIO DOS SANTOS | N106: 11994392232 | O106: 311189 | P106: PA NESTLE-SP | Q106: SPS | R106: 1353 | S106: 1289 | T106: 2026-10-01 07:14:37 | U106: 2026-10-01 16:27:06 | V106: 553 | W106: Não | X106: 2026-10-01 16:50:01 | Y106: 2026-10-01 17:00:00 | Z106: 2026-10-01 16:52:00 | AA106: 2026-10-01 16:52:00 | AB106: 31101 | AC106: SP BRE | AD106: SPS | AE106: 2026-10-01 17:45:00 | AF106: 2026-10-01 17:23:04 | AG106: -21 | AH106: 2026-10-01 17:23:04 | AI106: 2026-10-01 20:34:26 | AJ106: 27 | AK106: 2026-10-01 17:49:41 | AL106: 2026-10-02 07:58:29 | AM106: 849 | AN106: =IF(X106="",0,1) -> 1 | AO106: =IF(AI106="",0,1) -> 1 | AP106: =DATE(YEAR(AE106),MONTH(AE106),DAY(AE106)) -> 46296 | AQ106: =IF(COUNTIF('同场线路Rotas do mesmo SC'!A:A,C106)>0,"Sim","Não") -> Não | AR106: =IF(COUNTIF(揽收业务网点!A:A,P106)>0,"Sim","Não") -> Sim
A107: SRTR22605735711 | B107: Concluído：已完成 | C107: M119-M225-0800-1 | D107: Horário padrão | E107: Entrega | F107: 1 | G107: 178 | H107: HFB6E68 | I107: Furgao | J107: DANILO ONOFRE ALVES PINTO | K107: Transportadora-三方 | L107: DANILO ONO | M107: DANILO ONOFRE ALVES PINTO | N107: 38991415420 | O107: 538001 | P107: DC MTC-MG | Q107: MG | R107: 1173 | S107: 1167 | T107: 2026-10-01 02:00:41 | U107: 2026-10-01 02:13:18 | V107: 13 | W107: Não | X107: 2026-10-01 03:39:55 | Y107: 2026-10-01 08:00:00 | Z107: 2026-10-01 03:43:18 | AA107: 2026-10-01 03:43:18 | AB107: 538105 | AC107: PPR -MG | AD107: MG | AE107: 2026-10-01 11:57:00 | AF107: 2026-10-01 06:28:29 | AG107: -328 | AH107: 2026-10-01 06:28:29 | AI107: 2026-10-01 10:20:38 | AJ107: 234 | AK107: 2026-10-01 10:22:20 | AL107: 2026-10-01 15:55:01 | AM107: 333 | AN107: =IF(X107="",0,1) -> 1 | AO107: =IF(AI107="",0,1) -> 1 | AP107: =DATE(YEAR(AE107),MONTH(AE107),DAY(AE107)) -> 46296 | AQ107: =IF(COUNTIF('同场线路Rotas do mesmo SC'!A:A,C107)>0,"Sim","Não") -> Não | AR107: =IF(COUNTIF(揽收业务网点!A:A,P107)>0,"Sim","Não") -> Não
A108: SRTR22605735740 | B108: Concluído：已完成 | C108: ANA-C284-I265-I230-0300-1 | D108: Horário padrão | E108: Entrega | F108: 1 | G108: 280 | H108: JUJ6F56 | I108: 3/4 | J108: E. CARVALHO S. LOGISTICA | K108: Transportadora-三方 | L108: E.CARVALHO | M108: PEDRO DE MOURA RODRIGUES | N108: 985322518 | O108: 89101 | P108: PA ANA | Q108: GP | R108: 749 | S108: 571 | T108: 2026-09-30 12:05:02 | U108: 2026-10-01 00:45:25 | V108: 761 | W108: Não | X108: 2026-10-01 00:53:29 | Y108: 2026-10-01 03:00:00 | Z108: 2026-10-01 01:31:51 | AA108: 2026-10-01 01:31:51 | AB108: 961238 | AC108: F BAO-PA | AD108: GP | AE108: 2026-10-01 08:00:00 | AF108: 2026-10-01 05:24:38 | AG108: -155 | AH108: 2026-10-01 05:24:38 | AI108: 2026-10-01 05:29:02 | AJ108: 34 | AK108: 2026-10-01 05:58:21 | AL108: 2026-10-01 06:12:08 | AM108: 14 | AN108: =IF(X108="",0,1) -> 1 | AO108: =IF(AI108="",0,1) -> 1 | AP108: =DATE(YEAR(AE108),MONTH(AE108),DAY(AE108)) -> 46296 | AQ108: =IF(COUNTIF('同场线路Rotas do mesmo SC'!A:A,C108)>0,"Sim","Não") -> Não | AR108: =IF(COUNTIF(揽收业务网点!A:A,P108)>0,"Sim","Não") -> Não
...

Sheet 集货封车LACRE-COLETA
A1: 集货支线封车率-10.04 Taxa de lacramento secundária-Coleta | H1: 46299
A2: 序号Nº | B2: 发车区域 Região Saída | C2: 应封车 Lacre previsto | D2: 实际封车 Lacre realizado | E2: 封车率 taxa de lacre | F2: 目标 Meta | G2: 排名 Ranking
A3: 合计 | B3: 合计 | C3: =SUM(C4:C11) -> 33 | D3: =SUM(D4:D11) -> 30 | E3: =IFERROR((D3/C3),0) -> 0.90909091 | F3: 0.95 | G3: -
A4: =ROW()-3 -> 1 | B4: RJ | C4: =COUNTIFS(支线运输综合报表!Q:Q,B4,支线运输综合报表!AP:AP,$H$1,支线运输综合报表!E:E,"COLETA") -> 3 | D4: =SUMIFS(支线运输综合报表!AN:AN,支线运输综合报表!Q:Q,B4,支线运输综合报表!AP:AP,$H$1,支线运输综合报表!E:E,"COLETA") -> 3 | E4: =IFERROR((D4/C4),0) -> 1 | F4: 0.95 | G4: =RANK(E4,$E$4:$E$11) -> 1
A5: =ROW()-3 -> 2 | B5: MG | C5: =COUNTIFS(支线运输综合报表!Q:Q,B5,支线运输综合报表!AP:AP,$H$1,支线运输综合报表!E:E,"COLETA") -> 5 | D5: =SUMIFS(支线运输综合报表!AN:AN,支线运输综合报表!Q:Q,B5,支线运输综合报表!AP:AP,$H$1,支线运输综合报表!E:E,"COLETA") -> 5 | E5: =IFERROR((D5/C5),0) -> 1 | F5: 0.95 | G5: =RANK(E5,$E$4:$E$11) -> 1
A6: =ROW()-3 -> 3 | B6: SPN | C6: =COUNTIFS(支线运输综合报表!Q:Q,B6,支线运输综合报表!AP:AP,$H$1,支线运输综合报表!E:E,"COLETA") -> 9 | D6: =SUMIFS(支线运输综合报表!AN:AN,支线运输综合报表!Q:Q,B6,支线运输综合报表!AP:AP,$H$1,支线运输综合报表!E:E,"COLETA") -> 9 | E6: =IFERROR((D6/C6),0) -> 1 | F6: 0.95 | G6: =RANK(E6,$E$4:$E$11) -> 1
A7: =ROW()-3 -> 4 | B7: GP | C7: =COUNTIFS(支线运输综合报表!Q:Q,B7,支线运输综合报表!AP:AP,$H$1,支线运输综合报表!E:E,"COLETA") -> 1 | D7: =SUMIFS(支线运输综合报表!AN:AN,支线运输综合报表!Q:Q,B7,支线运输综合报表!AP:AP,$H$1,支线运输综合报表!E:E,"COLETA") -> 1 | E7: =IFERROR((D7/C7),0) -> 1 | F7: 0.95 | G7: =RANK(E7,$E$4:$E$11) -> 1
A8: =ROW()-3 -> 5 | B8: SPS | C8: =COUNTIFS(支线运输综合报表!Q:Q,B8,支线运输综合报表!AP:AP,$H$1,支线运输综合报表!E:E,"COLETA") -> 9 | D8: =SUMIFS(支线运输综合报表!AN:AN,支线运输综合报表!Q:Q,B8,支线运输综合报表!AP:AP,$H$1,支线运输综合报表!E:E,"COLETA") -> 8 | E8: =IFERROR((D8/C8),0) -> 0.88888889 | F8: 0.95 | G8: =RANK(E8,$E$4:$E$11) -> 5
A9: =ROW()-3 -> 6 | B9: SPE | C9: =COUNTIFS(支线运输综合报表!Q:Q,B9,支线运输综合报表!AP:AP,$H$1,支线运输综合报表!E:E,"COLETA") -> 4 | D9: =SUMIFS(支线运输综合报表!AN:AN,支线运输综合报表!Q:Q,B9,支线运输综合报表!AP:AP,$H$1,支线运输综合报表!E:E,"COLETA") -> 3 | E9: =IFERROR((D9/C9),0) -> 0.75 | F9: 0.95 | G9: =RANK(E9,$E$4:$E$11) -> 6
A10: =ROW()-3 -> 7 | B10: PR | C10: =COUNTIFS(支线运输综合报表!Q:Q,B10,支线运输综合报表!AP:AP,$H$1,支线运输综合报表!E:E,"COLETA") -> 2 | D10: =SUMIFS(支线运输综合报表!AN:AN,支线运输综合报表!Q:Q,B10,支线运输综合报表!AP:AP,$H$1,支线运输综合报表!E:E,"COLETA") -> 1 | E10: =IFERROR((D10/C10),0) -> 0.5 | F10: 0.95 | G10: =RANK(E10,$E$4:$E$11) -> 7
A11: =ROW()-3 -> 8 | B11: CE | C11: =COUNTIFS(支线运输综合报表!Q:Q,B11,支线运输综合报表!AP:AP,$H$1,支线运输综合报表!E:E,"COLETA") -> 0 | D11: =SUMIFS(支线运输综合报表!AN:AN,支线运输综合报表!Q:Q,B11,支线运输综合报表!AP:AP,$H$1,支线运输综合报表!E:E,"COLETA") -> 0 | E11: =IFERROR((D11/C11),0) -> 0 | F11: 0.95 | G11: =RANK(E11,$E$4:$E$11) -> 8
A12: 备注：每个任务单实际封车次数/应该封车次数 数据源：JMS-运力平台-支线运输综合报表-封签信息 时间：T-2，计划到达时间00-23:59:59 Obs:Número real delacre por ordem de tarefa / número previsto de lacre. Fonte: JMS – Plataforma de Capacidade – Relatório Geral de Transporte Secundário – Informação de Lacre. Período: T-2, considerando o horário planejado de chegada das 00:00 às 23:59:59.

Sheet 集货解车DESLACRE-COLETA
A1: 集货支线解车率-10.04 Taxa de deslacramento secundária-Coleta | H1: 46299
A2: 序号Nº | B2: 到车区域Região chegada | C2: 应解车Deslacre previsto | D2: 实际解车Deslacre realizado | E2: 解车率Taxa de deslacre | F2: 目标 Meta | G2: 排名 Ranking
A3: 合计 | B3: 合计 | C3: =SUM(C4:C12) -> 33 | D3: =SUM(D4:D12) -> 30 | E3: =D3/C3 -> 0.90909091 | F3: 0.9 | G3: -
A4: =ROW()-3 -> 1 | B4: RJ | C4: =COUNTIFS(支线运输综合报表!AD:AD,B4,支线运输综合报表!AP:AP,$H$1,支线运输综合报表!E:E,"COLETA") -> 3 | D4: =SUMIFS(支线运输综合报表!AO:AO,支线运输综合报表!AD:AD,B4,支线运输综合报表!AP:AP,$H$1,支线运输综合报表!E:E,"COLETA") -> 3 | E4: =IFERROR(D4/C4,0) -> 1 | F4: 0.9 | G4: =RANK(E4,$E$4:$E$12) -> 1
A5: =ROW()-3 -> 2 | B5: SPS | C5: =COUNTIFS(支线运输综合报表!AD:AD,B5,支线运输综合报表!AP:AP,$H$1,支线运输综合报表!E:E,"COLETA") -> 13 | D5: =SUMIFS(支线运输综合报表!AO:AO,支线运输综合报表!AD:AD,B5,支线运输综合报表!AP:AP,$H$1,支线运输综合报表!E:E,"COLETA") -> 13 | E5: =IFERROR(D5/C5,0) -> 1 | F5: 0.9 | G5: =RANK(E5,$E$4:$E$12) -> 1
A6: =ROW()-3 -> 3 | B6: MG | C6: =COUNTIFS(支线运输综合报表!AD:AD,B6,支线运输综合报表!AP:AP,$H$1,支线运输综合报表!E:E,"COLETA") -> 2 | D6: =SUMIFS(支线运输综合报表!AO:AO,支线运输综合报表!AD:AD,B6,支线运输综合报表!AP:AP,$H$1,支线运输综合报表!E:E,"COLETA") -> 2 | E6: =IFERROR(D6/C6,0) -> 1 | F6: 0.9 | G6: =RANK(E6,$E$4:$E$12) -> 1
A7: =ROW()-3 -> 4 | B7: GP | C7: =COUNTIFS(支线运输综合报表!AD:AD,B7,支线运输综合报表!AP:AP,$H$1,支线运输综合报表!E:E,"COLETA") -> 1 | D7: =SUMIFS(支线运输综合报表!AO:AO,支线运输综合报表!AD:AD,B7,支线运输综合报表!AP:AP,$H$1,支线运输综合报表!E:E,"COLETA") -> 1 | E7: =IFERROR(D7/C7,0) -> 1 | F7: 0.9 | G7: =RANK(E7,$E$4:$E$12) -> 1
A8: =ROW()-3 -> 5 | B8: SPN | C8: =COUNTIFS(支线运输综合报表!AD:AD,B8,支线运输综合报表!AP:AP,$H$1,支线运输综合报表!E:E,"COLETA") -> 9 | D8: =SUMIFS(支线运输综合报表!AO:AO,支线运输综合报表!AD:AD,B8,支线运输综合报表!AP:AP,$H$1,支线运输综合报表!E:E,"COLETA") -> 8 | E8: =IFERROR(D8/C8,0) -> 0.88888889 | F8: 0.9 | G8: =RANK(E8,$E$4:$E$12) -> 5
A9: =ROW()-3 -> 6 | B9: SPE | C9: =COUNTIFS(支线运输综合报表!AD:AD,B9,支线运输综合报表!AP:AP,$H$1,支线运输综合报表!E:E,"COLETA") -> 3 | D9: =SUMIFS(支线运输综合报表!AO:AO,支线运输综合报表!AD:AD,B9,支线运输综合报表!AP:AP,$H$1,支线运输综合报表!E:E,"COLETA") -> 2 | E9: =IFERROR(D9/C9,0) -> 0.66666667 | F9: 0.9 | G9: =RANK(E9,$E$4:$E$12) -> 6
A10: =ROW()-3 -> 7 | B10: PR | C10: =COUNTIFS(支线运输综合报表!AD:AD,B10,支线运输综合报表!AP:AP,$H$1,支线运输综合报表!E:E,"COLETA") -> 2 | D10: =SUMIFS(支线运输综合报表!AO:AO,支线运输综合报表!AD:AD,B10,支线运输综合报表!AP:AP,$H$1,支线运输综合报表!E:E,"COLETA") -> 1 | E10: =IFERROR(D10/C10,0) -> 0.5 | F10: 0.9 | G10: =RANK(E10,$E$4:$E$12) -> 7
A11: =ROW()-3 -> 8 | B11: CE | C11: =COUNTIFS(支线运输综合报表!AD:AD,B11,支线运输综合报表!AP:AP,$H$1,支线运输综合报表!E:E,"COLETA") -> 0 | D11: =SUMIFS(支线运输综合报表!AO:AO,支线运输综合报表!AD:AD,B11,支线运输综合报表!AP:AP,$H$1,支线运输综合报表!E:E,"COLETA") -> 0 | E11: =IFERROR(D11/C11,0) -> 0 | F11: 0.9 | G11: =RANK(E11,$E$4:$E$12) -> 8
A12: =ROW()-3 -> 9 | B12: BA | C12: =COUNTIFS(支线运输综合报表!AD:AD,B12,支线运输综合报表!AP:AP,$H$1,支线运输综合报表!E:E,"COLETA") -> 0 | D12: =SUMIFS(支线运输综合报表!AO:AO,支线运输综合报表!AD:AD,B12,支线运输综合报表!AP:AP,$H$1,支线运输综合报表!E:E,"COLETA") -> 0 | E12: =IFERROR(D12/C12,0) -> 0 | F12: 0.9 | G12: =RANK(E12,$E$4:$E$12) -> 8
A13: 备注：每个任务单实际解车次数/应该解车次数 数据源：JMS-运力平台-支线运输综合报表-解封信息 时间：T-2，计划到达时间00-23:59:59 Observação: Número real de deslacre por ordem de tarefa / número previsto de deslacre. Fonte:JMS – Plataforma de Capacidade – Relatório Geral de Transporte Secundário – Informação de Deslacração. Período: T-2, considerando o horário planejado de chegada das 00:00 às 23:59:59.

Sheet 散货封车LACRE-ENTEGA
A1: 散货支线封车率-10.04 Taxa de lacramento secundária-Entrega | H1: 46299
A2: 序号Nº | B2: 发车区域 Região Saída | C2: 应封车 Lacre previsto | D2: 实际封车 Lacre realizado | E2: 封车率 taxa de lacre | F2: 目标 Meta | G2: 排名 Ranking
A3: 合计 | B3: 合计 | C3: =SUM(C4:C12) -> 542 | D3: =SUM(D4:D12) -> 525 | E3: =D3/C3 -> 0.96863469 | F3: 0.95 | G3: -
A4: =ROW()-3 -> 1 | B4: SPN | C4: =COUNTIFS(支线运输综合报表!Q:Q,B4,支线运输综合报表!AP:AP,$H$1,支线运输综合报表!E:E,"ENTREGA") -> 78 | D4: =SUMIFS(支线运输综合报表!AN:AN,支线运输综合报表!Q:Q,B4,支线运输综合报表!AP:AP,$H$1,支线运输综合报表!E:E,"ENTREGA") -> 78 | E4: =D4/C4 -> 1 | F4: 0.95 | G4: =RANK(E4,$E$4:$E$12) -> 1
A5: =ROW()-3 -> 2 | B5: BA | C5: =COUNTIFS(支线运输综合报表!Q:Q,B5,支线运输综合报表!AP:AP,$H$1,支线运输综合报表!E:E,"ENTREGA") -> 17 | D5: =SUMIFS(支线运输综合报表!AN:AN,支线运输综合报表!Q:Q,B5,支线运输综合报表!AP:AP,$H$1,支线运输综合报表!E:E,"ENTREGA") -> 17 | E5: =D5/C5 -> 1 | F5: 0.95 | G5: =RANK(E5,$E$4:$E$12) -> 1
A6: =ROW()-3 -> 3 | B6: CE | C6: =COUNTIFS(支线运输综合报表!Q:Q,B6,支线运输综合报表!AP:AP,$H$1,支线运输综合报表!E:E,"ENTREGA") -> 7 | D6: =SUMIFS(支线运输综合报表!AN:AN,支线运输综合报表!Q:Q,B6,支线运输综合报表!AP:AP,$H$1,支线运输综合报表!E:E,"ENTREGA") -> 7 | E6: =D6/C6 -> 1 | F6: 0.95 | G6: =RANK(E6,$E$4:$E$12) -> 1
A7: =ROW()-3 -> 4 | B7: SPS | C7: =COUNTIFS(支线运输综合报表!Q:Q,B7,支线运输综合报表!AP:AP,$H$1,支线运输综合报表!E:E,"ENTREGA") -> 93 | D7: =SUMIFS(支线运输综合报表!AN:AN,支线运输综合报表!Q:Q,B7,支线运输综合报表!AP:AP,$H$1,支线运输综合报表!E:E,"ENTREGA") -> 92 | E7: =D7/C7 -> 0.98924731 | F7: 0.95 | G7: =RANK(E7,$E$4:$E$12) -> 4
A8: =ROW()-3 -> 5 | B8: GP | C8: =COUNTIFS(支线运输综合报表!Q:Q,B8,支线运输综合报表!AP:AP,$H$1,支线运输综合报表!E:E,"ENTREGA") -> 137 | D8: =SUMIFS(支线运输综合报表!AN:AN,支线运输综合报表!Q:Q,B8,支线运输综合报表!AP:AP,$H$1,支线运输综合报表!E:E,"ENTREGA") -> 134 | E8: =D8/C8 -> 0.97810219 | F8: 0.95 | G8: =RANK(E8,$E$4:$E$12) -> 5
A9: =ROW()-3 -> 6 | B9: RJ | C9: =COUNTIFS(支线运输综合报表!Q:Q,B9,支线运输综合报表!AP:AP,$H$1,支线运输综合报表!E:E,"ENTREGA") -> 35 | D9: =SUMIFS(支线运输综合报表!AN:AN,支线运输综合报表!Q:Q,B9,支线运输综合报表!AP:AP,$H$1,支线运输综合报表!E:E,"ENTREGA") -> 34 | E9: =D9/C9 -> 0.97142857 | F9: 0.95 | G9: =RANK(E9,$E$4:$E$12) -> 6
A10: =ROW()-3 -> 7 | B10: MG | C10: =COUNTIFS(支线运输综合报表!Q:Q,B10,支线运输综合报表!AP:AP,$H$1,支线运输综合报表!E:E,"ENTREGA") -> 75 | D10: =SUMIFS(支线运输综合报表!AN:AN,支线运输综合报表!Q:Q,B10,支线运输综合报表!AP:AP,$H$1,支线运输综合报表!E:E,"ENTREGA") -> 72 | E10: =D10/C10 -> 0.96 | F10: 0.95 | G10: =RANK(E10,$E$4:$E$12) -> 7
A11: =ROW()-3 -> 8 | B11: SPE | C11: =COUNTIFS(支线运输综合报表!Q:Q,B11,支线运输综合报表!AP:AP,$H$1,支线运输综合报表!E:E,"ENTREGA") -> 23 | D11: =SUMIFS(支线运输综合报表!AN:AN,支线运输综合报表!Q:Q,B11,支线运输综合报表!AP:AP,$H$1,支线运输综合报表!E:E,"ENTREGA") -> 21 | E11: =D11/C11 -> 0.91304348 | F11: 0.95 | G11: =RANK(E11,$E$4:$E$12) -> 8
A12: =ROW()-3 -> 9 | B12: PR | C12: =COUNTIFS(支线运输综合报表!Q:Q,B12,支线运输综合报表!AP:AP,$H$1,支线运输综合报表!E:E,"ENTREGA") -> 77 | D12: =SUMIFS(支线运输综合报表!AN:AN,支线运输综合报表!Q:Q,B12,支线运输综合报表!AP:AP,$H$1,支线运输综合报表!E:E,"ENTREGA") -> 70 | E12: =D12/C12 -> 0.90909091 | F12: 0.95 | G12: =RANK(E12,$E$4:$E$12) -> 9
A13: 备注：每个任务单实际封车次数/应该封车次数 数据源：JMS-运力平台-支线运输综合报表-封签信息 时间：T-2，计划到达时间00-23:59:59 Obs:Número real delacre por ordem de tarefa / número previsto de lacre. Fonte: JMS – Plataforma de Capacidade – Relatório Geral de Transporte Secundário – Informação de Lacre. Período: T-2, considerando o horário planejado de chegada das 00:00 às 23:59:59.

Sheet 散货解车DESLACRE-ENTREGA
A1: 散货支线解车率-10.04 Taxa de deslacramento secundária-Entrega | H1: 46299
A2: 序号Nº | B2: 到车区域Região chegada | C2: 应解车Deslacre previsto | D2: 实际解车Deslacre realizado | E2: 解车率Taxa de deslacre | F2: 目标 Meta | G2: 排名 Ranking
A3: 合计 | B3: 合计 | C3: =SUM(C4:C12) -> 542 | D3: =SUM(D4:D12) -> 490 | E3: =D3/C3 -> 0.90405904 | F3: 0.9 | G3: -
A4: =ROW()-3 -> 1 | B4: BA | C4: =COUNTIFS(支线运输综合报表!AD:AD,B4,支线运输综合报表!AP:AP,$H$1,支线运输综合报表!E:E,"ENTREGA") -> 17 | D4: =SUMIFS(支线运输综合报表!AO:AO,支线运输综合报表!AD:AD,B4,支线运输综合报表!AP:AP,$H$1,支线运输综合报表!E:E,"ENTREGA") -> 17 | E4: =D4/C4 -> 1 | F4: 0.9 | G4: =RANK(E4,$E$4:$E$12) -> 1
A5: =ROW()-3 -> 2 | B5: SPN | C5: =COUNTIFS(支线运输综合报表!AD:AD,B5,支线运输综合报表!AP:AP,$H$1,支线运输综合报表!E:E,"ENTREGA") -> 65 | D5: =SUMIFS(支线运输综合报表!AO:AO,支线运输综合报表!AD:AD,B5,支线运输综合报表!AP:AP,$H$1,支线运输综合报表!E:E,"ENTREGA") -> 63 | E5: =D5/C5 -> 0.96923077 | F5: 0.9 | G5: =RANK(E5,$E$4:$E$12) -> 2
A6: =ROW()-3 -> 3 | B6: MG | C6: =COUNTIFS(支线运输综合报表!AD:AD,B6,支线运输综合报表!AP:AP,$H$1,支线运输综合报表!E:E,"ENTREGA") -> 93 | D6: =SUMIFS(支线运输综合报表!AO:AO,支线运输综合报表!AD:AD,B6,支线运输综合报表!AP:AP,$H$1,支线运输综合报表!E:E,"ENTREGA") -> 87 | E6: =D6/C6 -> 0.93548387 | F6: 0.9 | G6: =RANK(E6,$E$4:$E$12) -> 3
A7: =ROW()-3 -> 4 | B7: SPS | C7: =COUNTIFS(支线运输综合报表!AD:AD,B7,支线运输综合报表!AP:AP,$H$1,支线运输综合报表!E:E,"ENTREGA") -> 87 | D7: =SUMIFS(支线运输综合报表!AO:AO,支线运输综合报表!AD:AD,B7,支线运输综合报表!AP:AP,$H$1,支线运输综合报表!E:E,"ENTREGA") -> 80 | E7: =D7/C7 -> 0.91954023 | F7: 0.9 | G7: =RANK(E7,$E$4:$E$12) -> 4
A8: =ROW()-3 -> 5 | B8: GP | C8: =COUNTIFS(支线运输综合报表!AD:AD,B8,支线运输综合报表!AP:AP,$H$1,支线运输综合报表!E:E,"ENTREGA") -> 135 | D8: =SUMIFS(支线运输综合报表!AO:AO,支线运输综合报表!AD:AD,B8,支线运输综合报表!AP:AP,$H$1,支线运输综合报表!E:E,"ENTREGA") -> 123 | E8: =D8/C8 -> 0.91111111 | F8: 0.9 | G8: =RANK(E8,$E$4:$E$12) -> 5
A9: =ROW()-3 -> 6 | B9: RJ | C9: =COUNTIFS(支线运输综合报表!AD:AD,B9,支线运输综合报表!AP:AP,$H$1,支线运输综合报表!E:E,"ENTREGA") -> 35 | D9: =SUMIFS(支线运输综合报表!AO:AO,支线运输综合报表!AD:AD,B9,支线运输综合报表!AP:AP,$H$1,支线运输综合报表!E:E,"ENTREGA") -> 30 | E9: =D9/C9 -> 0.85714286 | F9: 0.9 | G9: =RANK(E9,$E$4:$E$12) -> 6
A10: =ROW()-3 -> 7 | B10: PR | C10: =COUNTIFS(支线运输综合报表!AD:AD,B10,支线运输综合报表!AP:AP,$H$1,支线运输综合报表!E:E,"ENTREGA") -> 77 | D10: =SUMIFS(支线运输综合报表!AO:AO,支线运输综合报表!AD:AD,B10,支线运输综合报表!AP:AP,$H$1,支线运输综合报表!E:E,"ENTREGA") -> 64 | E10: =D10/C10 -> 0.83116883 | F10: 0.9 | G10: =RANK(E10,$E$4:$E$12) -> 7
A11: =ROW()-3 -> 8 | B11: SPE | C11: =COUNTIFS(支线运输综合报表!AD:AD,B11,支线运输综合报表!AP:AP,$H$1,支线运输综合报表!E:E,"ENTREGA") -> 26 | D11: =SUMIFS(支线运输综合报表!AO:AO,支线运输综合报表!AD:AD,B11,支线运输综合报表!AP:AP,$H$1,支线运输综合报表!E:E,"ENTREGA") -> 21 | E11: =D11/C11 -> 0.80769231 | F11: 0.9 | G11: =RANK(E11,$E$4:$E$12) -> 8
A12: =ROW()-3 -> 9 | B12: CE | C12: =COUNTIFS(支线运输综合报表!AD:AD,B12,支线运输综合报表!AP:AP,$H$1,支线运输综合报表!E:E,"ENTREGA") -> 7 | D12: =SUMIFS(支线运输综合报表!AO:AO,支线运输综合报表!AD:AD,B12,支线运输综合报表!AP:AP,$H$1,支线运输综合报表!E:E,"ENTREGA") -> 5 | E12: =D12/C12 -> 0.71428571 | F12: 0.9 | G12: =RANK(E12,$E$4:$E$12) -> 9
A13: 备注：每个任务单实际解车次数/应该解车次数 数据源：JMS-运力平台-支线运输综合报表-解封信息 时间：T-2，计划到达时间00-23:59:59 Observação: Número real de deslacre por ordem de tarefa / número previsto de deslacre. Fonte:JMS – Plataforma de Capacidade – Relatório Geral de Transporte Secundário – Informação de Deslacração. Período: T-2, considerando o horário planejado de chegada das 00:00 às 23:59:59.

Sheet 封车趋势Tendencia lacre
A1: 集货封车率趋势Tendência da LACRE-COLETA
A2: 发车区域Região de Saída | B2: 环比Variação± | C2: 10月累计Acumulado de Outubro | D2: 46296 | E2: =D2+1 -> 46297 | F2: =E2+1 -> 46298 | G2: =F2+1 -> 46299 | H2: =G2+1 -> 46300 | I2: =H2+1 -> 46301 | J2: =I2+1 -> 46302 | K2: =J2+1 -> 46303 | L2: =K2+1 -> 46304 | ... AH2: =AG2+1 -> 46326 | AI2: 近七天趋势
A3: 合计 | B3: =G3-F3 -> -0.015327696 | C3: =IFERROR(SUMIFS(支线运输综合报表!$AN:$AN,支线运输综合报表!$E:$E,"Coleta")/COUNTIFS(支线运输综合报表!$E:$E,"Coleta"),0) -> 0.94461078 | D3: =IFERROR(SUMIFS(支线运输综合报表!$AN:$AN,支线运输综合报表!$AP:$AP,D2,支线运输综合报表!$E:$E,"Coleta")/COUNTIFS(支线运输综合报表!$AP:$AP,D2,支线运输综合报表!$E:$E,"Coleta"),0) -> 0.95217391 | E3: =IFERROR(SUMIFS(支线运输综合报表!$AN:$AN,支线运输综合报表!$AP:$AP,E2,支线运输综合报表!$E:$E,"Coleta")/COUNTIFS(支线运输综合报表!$AP:$AP,E2,支线运输综合报表!$E:$E,"Coleta"),0) -> 0.95708155 | F3: =IFERROR(SUMIFS(支线运输综合报表!$AN:$AN,支线运输综合报表!$AP:$AP,F2,支线运输综合报表!$E:$E,"Coleta")/COUNTIFS(支线运输综合报表!$AP:$AP,F2,支线运输综合报表!$E:$E,"Coleta"),0) -> 0.9244186 | G3: =IFERROR(SUMIFS(支线运输综合报表!$AN:$AN,支线运输综合报表!$AP:$AP,G2,支线运输综合报表!$E:$E,"Coleta")/COUNTIFS(支线运输综合报表!$AP:$AP,G2,支线运输综合报表!$E:$E,"Coleta"),0) -> 0.90909091 | H3: =IFERROR(SUMIFS(支线运输综合报表!$AN:$AN,支线运输综合报表!$AP:$AP,H2,支线运输综合报表!$E:$E,"Coleta")/COUNTIFS(支线运输综合报表!$AP:$AP,H2,支线运输综合报表!$E:$E,"Coleta"),0) -> 0 | I3: =IFERROR(SUMIFS(支线运输综合报表!$AN:$AN,支线运输综合报表!$AP:$AP,I2,支线运输综合报表!$E:$E,"Coleta")/COUNTIFS(支线运输综合报表!$AP:$AP,I2,支线运输综合报表!$E:$E,"Coleta"),0) -> 0 | J3: =IFERROR(SUMIFS(支线运输综合报表!$AN:$AN,支线运输综合报表!$AP:$AP,J2,支线运输综合报表!$E:$E,"Coleta")/COUNTIFS(支线运输综合报表!$AP:$AP,J2,支线运输综合报表!$E:$E,"Coleta"),0) -> 0 | K3: =IFERROR(SUMIFS(支线运输综合报表!$AN:$AN,支线运输综合报表!$AP:$AP,K2,支线运输综合报表!$E:$E,"Coleta")/COUNTIFS(支线运输综合报表!$AP:$AP,K2,支线运输综合报表!$E:$E,"Coleta"),0) -> 0 | ... AH3: =IFERROR(SUMIFS(支线运输综合报表!$AN:$AN,支线运输综合报表!$AP:$AP,AH2,支线运输综合报表!$E:$E,"Coleta")/COUNTIFS(支线运输综合报表!$AP:$AP,AH2,支线运输综合报表!$E:$E,"Coleta"),0) -> 0
A4: SPN | B4: =G4-F4 -> 0.027777778 | C4: =IFERROR(SUMIFS(支线运输综合报表!$AN:$AN,支线运输综合报表!$Q:$Q,$A4,支线运输综合报表!$E:$E,"Coleta")/COUNTIFS(支线运输综合报表!$Q:$Q,$A4,支线运输综合报表!$E:$E,"Coleta"),0) -> 0.97247706 | D4: =IFERROR(SUMIFS(支线运输综合报表!$AN:$AN,支线运输综合报表!$Q:$Q,$A4,支线运输综合报表!$AP:$AP,D$2,支线运输综合报表!$E:$E,"Coleta")/COUNTIFS(支线运输综合报表!$Q:$Q,$A4,支线运输综合报表!$AP:$AP,D$2,支线运输综合报表!$E:$E,"Coleta"),0) -> 1 | E4: =IFERROR(SUMIFS(支线运输综合报表!$AN:$AN,支线运输综合报表!$Q:$Q,$A4,支线运输综合报表!$AP:$AP,E$2,支线运输综合报表!$E:$E,"Coleta")/COUNTIFS(支线运输综合报表!$Q:$Q,$A4,支线运输综合报表!$AP:$AP,E$2,支线运输综合报表!$E:$E,"Coleta"),0) -> 0.9375 | F4: =IFERROR(SUMIFS(支线运输综合报表!$AN:$AN,支线运输综合报表!$Q:$Q,$A4,支线运输综合报表!$AP:$AP,F$2,支线运输综合报表!$E:$E,"Coleta")/COUNTIFS(支线运输综合报表!$Q:$Q,$A4,支线运输综合报表!$AP:$AP,F$2,支线运输综合报表!$E:$E,"Coleta"),0) -> 0.97222222 | G4: =IFERROR(SUMIFS(支线运输综合报表!$AN:$AN,支线运输综合报表!$Q:$Q,$A4,支线运输综合报表!$AP:$AP,G$2,支线运输综合报表!$E:$E,"Coleta")/COUNTIFS(支线运输综合报表!$Q:$Q,$A4,支线运输综合报表!$AP:$AP,G$2,支线运输综合报表!$E:$E,"Coleta"),0) -> 1 | H4: =IFERROR(SUMIFS(支线运输综合报表!$AN:$AN,支线运输综合报表!$Q:$Q,$A4,支线运输综合报表!$AP:$AP,H$2,支线运输综合报表!$E:$E,"Coleta")/COUNTIFS(支线运输综合报表!$Q:$Q,$A4,支线运输综合报表!$AP:$AP,H$2,支线运输综合报表!$E:$E,"Coleta"),0) -> 0 | I4: =IFERROR(SUMIFS(支线运输综合报表!$AN:$AN,支线运输综合报表!$Q:$Q,$A4,支线运输综合报表!$AP:$AP,I$2,支线运输综合报表!$E:$E,"Coleta")/COUNTIFS(支线运输综合报表!$Q:$Q,$A4,支线运输综合报表!$AP:$AP,I$2,支线运输综合报表!$E:$E,"Coleta"),0) -> 0 | J4: =IFERROR(SUMIFS(支线运输综合报表!$AN:$AN,支线运输综合报表!$Q:$Q,$A4,支线运输综合报表!$AP:$AP,J$2,支线运输综合报表!$E:$E,"Coleta")/COUNTIFS(支线运输综合报表!$Q:$Q,$A4,支线运输综合报表!$AP:$AP,J$2,支线运输综合报表!$E:$E,"Coleta"),0) -> 0 | K4: =IFERROR(SUMIFS(支线运输综合报表!$AN:$AN,支线运输综合报表!$Q:$Q,$A4,支线运输综合报表!$AP:$AP,K$2,支线运输综合报表!$E:$E,"Coleta")/COUNTIFS(支线运输综合报表!$Q:$Q,$A4,支线运输综合报表!$AP:$AP,K$2,支线运输综合报表!$E:$E,"Coleta"),0) -> 0 | ... AH4: =IFERROR(SUMIFS(支线运输综合报表!$AN:$AN,支线运输综合报表!$Q:$Q,$A4,支线运输综合报表!$AP:$AP,AH$2,支线运输综合报表!$E:$E,"Coleta")/COUNTIFS(支线运输综合报表!$Q:$Q,$A4,支线运输综合报表!$AP:$AP,AH$2,支线运输综合报表!$E:$E,"Coleta"),0) -> 0
A5: SPS | B5: =G5-F5 -> -0.070570571 | C5: =IFERROR(SUMIFS(支线运输综合报表!$AN:$AN,支线运输综合报表!$Q:$Q,$A5,支线运输综合报表!$E:$E,"Coleta")/COUNTIFS(支线运输综合报表!$Q:$Q,$A5,支线运输综合报表!$E:$E,"Coleta"),0) -> 0.96226415 | D5: =IFERROR(SUMIFS(支线运输综合报表!$AN:$AN,支线运输综合报表!$Q:$Q,$A5,支线运输综合报表!$AP:$AP,D$2,支线运输综合报表!$E:$E,"Coleta")/COUNTIFS(支线运输综合报表!$Q:$Q,$A5,支线运输综合报表!$AP:$AP,D$2,支线运输综合报表!$E:$E,"Coleta"),0) -> 0.95726496 | E5: =IFERROR(SUMIFS(支线运输综合报表!$AN:$AN,支线运输综合报表!$Q:$Q,$A5,支线运输综合报表!$AP:$AP,E$2,支线运输综合报表!$E:$E,"Coleta")/COUNTIFS(支线运输综合报表!$Q:$Q,$A5,支线运输综合报表!$AP:$AP,E$2,支线运输综合报表!$E:$E,"Coleta"),0) -> 0.97457627 | F5: =IFERROR(SUMIFS(支线运输综合报表!$AN:$AN,支线运输综合报表!$Q:$Q,$A5,支线运输综合报表!$AP:$AP,F$2,支线运输综合报表!$E:$E,"Coleta")/COUNTIFS(支线运输综合报表!$Q:$Q,$A5,支线运输综合报表!$AP:$AP,F$2,支线运输综合报表!$E:$E,"Coleta"),0) -> 0.95945946 | G5: =IFERROR(SUMIFS(支线运输综合报表!$AN:$AN,支线运输综合报表!$Q:$Q,$A5,支线运输综合报表!$AP:$AP,G$2,支线运输综合报表!$E:$E,"Coleta")/COUNTIFS(支线运输综合报表!$Q:$Q,$A5,支线运输综合报表!$AP:$AP,G$2,支线运输综合报表!$E:$E,"Coleta"),0) -> 0.88888889 | H5: =IFERROR(SUMIFS(支线运输综合报表!$AN:$AN,支线运输综合报表!$Q:$Q,$A5,支线运输综合报表!$AP:$AP,H$2,支线运输综合报表!$E:$E,"Coleta")/COUNTIFS(支线运输综合报表!$Q:$Q,$A5,支线运输综合报表!$AP:$AP,H$2,支线运输综合报表!$E:$E,"Coleta"),0) -> 0 | I5: =IFERROR(SUMIFS(支线运输综合报表!$AN:$AN,支线运输综合报表!$Q:$Q,$A5,支线运输综合报表!$AP:$AP,I$2,支线运输综合报表!$E:$E,"Coleta")/COUNTIFS(支线运输综合报表!$Q:$Q,$A5,支线运输综合报表!$AP:$AP,I$2,支线运输综合报表!$E:$E,"Coleta"),0) -> 0 | J5: =IFERROR(SUMIFS(支线运输综合报表!$AN:$AN,支线运输综合报表!$Q:$Q,$A5,支线运输综合报表!$AP:$AP,J$2,支线运输综合报表!$E:$E,"Coleta")/COUNTIFS(支线运输综合报表!$Q:$Q,$A5,支线运输综合报表!$AP:$AP,J$2,支线运输综合报表!$E:$E,"Coleta"),0) -> 0 | K5: =IFERROR(SUMIFS(支线运输综合报表!$AN:$AN,支线运输综合报表!$Q:$Q,$A5,支线运输综合报表!$AP:$AP,K$2,支线运输综合报表!$E:$E,"Coleta")/COUNTIFS(支线运输综合报表!$Q:$Q,$A5,支线运输综合报表!$AP:$AP,K$2,支线运输综合报表!$E:$E,"Coleta"),0) -> 0 | ... AH5: =IFERROR(SUMIFS(支线运输综合报表!$AN:$AN,支线运输综合报表!$Q:$Q,$A5,支线运输综合报表!$AP:$AP,AH$2,支线运输综合报表!$E:$E,"Coleta")/COUNTIFS(支线运输综合报表!$Q:$Q,$A5,支线运输综合报表!$AP:$AP,AH$2,支线运输综合报表!$E:$E,"Coleta"),0) -> 0
A6: GP | B6: =G6-F6 -> 0.5 | C6: =IFERROR(SUMIFS(支线运输综合报表!$AN:$AN,支线运输综合报表!$Q:$Q,$A6,支线运输综合报表!$E:$E,"Coleta")/COUNTIFS(支线运输综合报表!$Q:$Q,$A6,支线运输综合报表!$E:$E,"Coleta"),0) -> 0.66666667 | D6: =IFERROR(SUMIFS(支线运输综合报表!$AN:$AN,支线运输综合报表!$Q:$Q,$A6,支线运输综合报表!$AP:$AP,D$2,支线运输综合报表!$E:$E,"Coleta")/COUNTIFS(支线运输综合报表!$Q:$Q,$A6,支线运输综合报表!$AP:$AP,D$2,支线运输综合报表!$E:$E,"Coleta"),0) -> 0.71428571 | E6: =IFERROR(SUMIFS(支线运输综合报表!$AN:$AN,支线运输综合报表!$Q:$Q,$A6,支线运输综合报表!$AP:$AP,E$2,支线运输综合报表!$E:$E,"Coleta")/COUNTIFS(支线运输综合报表!$Q:$Q,$A6,支线运输综合报表!$AP:$AP,E$2,支线运输综合报表!$E:$E,"Coleta"),0) -> 0.71428571 | F6: =IFERROR(SUMIFS(支线运输综合报表!$AN:$AN,支线运输综合报表!$Q:$Q,$A6,支线运输综合报表!$AP:$AP,F$2,支线运输综合报表!$E:$E,"Coleta")/COUNTIFS(支线运输综合报表!$Q:$Q,$A6,支线运输综合报表!$AP:$AP,F$2,支线运输综合报表!$E:$E,"Coleta"),0) -> 0.5 | G6: =IFERROR(SUMIFS(支线运输综合报表!$AN:$AN,支线运输综合报表!$Q:$Q,$A6,支线运输综合报表!$AP:$AP,G$2,支线运输综合报表!$E:$E,"Coleta")/COUNTIFS(支线运输综合报表!$Q:$Q,$A6,支线运输综合报表!$AP:$AP,G$2,支线运输综合报表!$E:$E,"Coleta"),0) -> 1 | H6: =IFERROR(SUMIFS(支线运输综合报表!$AN:$AN,支线运输综合报表!$Q:$Q,$A6,支线运输综合报表!$AP:$AP,H$2,支线运输综合报表!$E:$E,"Coleta")/COUNTIFS(支线运输综合报表!$Q:$Q,$A6,支线运输综合报表!$AP:$AP,H$2,支线运输综合报表!$E:$E,"Coleta"),0) -> 0 | I6: =IFERROR(SUMIFS(支线运输综合报表!$AN:$AN,支线运输综合报表!$Q:$Q,$A6,支线运输综合报表!$AP:$AP,I$2,支线运输综合报表!$E:$E,"Coleta")/COUNTIFS(支线运输综合报表!$Q:$Q,$A6,支线运输综合报表!$AP:$AP,I$2,支线运输综合报表!$E:$E,"Coleta"),0) -> 0 | J6: =IFERROR(SUMIFS(支线运输综合报表!$AN:$AN,支线运输综合报表!$Q:$Q,$A6,支线运输综合报表!$AP:$AP,J$2,支线运输综合报表!$E:$E,"Coleta")/COUNTIFS(支线运输综合报表!$Q:$Q,$A6,支线运输综合报表!$AP:$AP,J$2,支线运输综合报表!$E:$E,"Coleta"),0) -> 0 | K6: =IFERROR(SUMIFS(支线运输综合报表!$AN:$AN,支线运输综合报表!$Q:$Q,$A6,支线运输综合报表!$AP:$AP,K$2,支线运输综合报表!$E:$E,"Coleta")/COUNTIFS(支线运输综合报表!$Q:$Q,$A6,支线运输综合报表!$AP:$AP,K$2,支线运输综合报表!$E:$E,"Coleta"),0) -> 0 | ... AH6: =IFERROR(SUMIFS(支线运输综合报表!$AN:$AN,支线运输综合报表!$Q:$Q,$A6,支线运输综合报表!$AP:$AP,AH$2,支线运输综合报表!$E:$E,"Coleta")/COUNTIFS(支线运输综合报表!$Q:$Q,$A6,支线运输综合报表!$AP:$AP,AH$2,支线运输综合报表!$E:$E,"Coleta"),0) -> 0
A7: SPE | B7: =G7-F7 -> -0.19444444 | C7: =IFERROR(SUMIFS(支线运输综合报表!$AN:$AN,支线运输综合报表!$Q:$Q,$A7,支线运输综合报表!$E:$E,"Coleta")/COUNTIFS(支线运输综合报表!$Q:$Q,$A7,支线运输综合报表!$E:$E,"Coleta"),0) -> 0.97619048 | D7: =IFERROR(SUMIFS(支线运输综合报表!$AN:$AN,支线运输综合报表!$Q:$Q,$A7,支线运输综合报表!$AP:$AP,D$2,支线运输综合报表!$E:$E,"Coleta")/COUNTIFS(支线运输综合报表!$Q:$Q,$A7,支线运输综合报表!$AP:$AP,D$2,支线运输综合报表!$E:$E,"Coleta"),0) -> 1 | E7: =IFERROR(SUMIFS(支线运输综合报表!$AN:$AN,支线运输综合报表!$Q:$Q,$A7,支线运输综合报表!$AP:$AP,E$2,支线运输综合报表!$E:$E,"Coleta")/COUNTIFS(支线运输综合报表!$Q:$Q,$A7,支线运输综合报表!$AP:$AP,E$2,支线运输综合报表!$E:$E,"Coleta"),0) -> 1 | F7: =IFERROR(SUMIFS(支线运输综合报表!$AN:$AN,支线运输综合报表!$Q:$Q,$A7,支线运输综合报表!$AP:$AP,F$2,支线运输综合报表!$E:$E,"Coleta")/COUNTIFS(支线运输综合报表!$Q:$Q,$A7,支线运输综合报表!$AP:$AP,F$2,支线运输综合报表!$E:$E,"Coleta"),0) -> 0.94444444 | G7: =IFERROR(SUMIFS(支线运输综合报表!$AN:$AN,支线运输综合报表!$Q:$Q,$A7,支线运输综合报表!$AP:$AP,G$2,支线运输综合报表!$E:$E,"Coleta")/COUNTIFS(支线运输综合报表!$Q:$Q,$A7,支线运输综合报表!$AP:$AP,G$2,支线运输综合报表!$E:$E,"Coleta"),0) -> 0.75 | H7: =IFERROR(SUMIFS(支线运输综合报表!$AN:$AN,支线运输综合报表!$Q:$Q,$A7,支线运输综合报表!$AP:$AP,H$2,支线运输综合报表!$E:$E,"Coleta")/COUNTIFS(支线运输综合报表!$Q:$Q,$A7,支线运输综合报表!$AP:$AP,H$2,支线运输综合报表!$E:$E,"Coleta"),0) -> 0 | I7: =IFERROR(SUMIFS(支线运输综合报表!$AN:$AN,支线运输综合报表!$Q:$Q,$A7,支线运输综合报表!$AP:$AP,I$2,支线运输综合报表!$E:$E,"Coleta")/COUNTIFS(支线运输综合报表!$Q:$Q,$A7,支线运输综合报表!$AP:$AP,I$2,支线运输综合报表!$E:$E,"Coleta"),0) -> 0 | J7: =IFERROR(SUMIFS(支线运输综合报表!$AN:$AN,支线运输综合报表!$Q:$Q,$A7,支线运输综合报表!$AP:$AP,J$2,支线运输综合报表!$E:$E,"Coleta")/COUNTIFS(支线运输综合报表!$Q:$Q,$A7,支线运输综合报表!$AP:$AP,J$2,支线运输综合报表!$E:$E,"Coleta"),0) -> 0 | K7: =IFERROR(SUMIFS(支线运输综合报表!$AN:$AN,支线运输综合报表!$Q:$Q,$A7,支线运输综合报表!$AP:$AP,K$2,支线运输综合报表!$E:$E,"Coleta")/COUNTIFS(支线运输综合报表!$Q:$Q,$A7,支线运输综合报表!$AP:$AP,K$2,支线运输综合报表!$E:$E,"Coleta"),0) -> 0 | ... AH7: =IFERROR(SUMIFS(支线运输综合报表!$AN:$AN,支线运输综合报表!$Q:$Q,$A7,支线运输综合报表!$AP:$AP,AH$2,支线运输综合报表!$E:$E,"Coleta")/COUNTIFS(支线运输综合报表!$Q:$Q,$A7,支线运输综合报表!$AP:$AP,AH$2,支线运输综合报表!$E:$E,"Coleta"),0) -> 0
A8: RJ | B8: =G8-F8 -> 0 | C8: =IFERROR(SUMIFS(支线运输综合报表!$AN:$AN,支线运输综合报表!$Q:$Q,$A8,支线运输综合报表!$E:$E,"Coleta")/COUNTIFS(支线运输综合报表!$Q:$Q,$A8,支线运输综合报表!$E:$E,"Coleta"),0) -> 0.95 | D8: =IFERROR(SUMIFS(支线运输综合报表!$AN:$AN,支线运输综合报表!$Q:$Q,$A8,支线运输综合报表!$AP:$AP,D$2,支线运输综合报表!$E:$E,"Coleta")/COUNTIFS(支线运输综合报表!$Q:$Q,$A8,支线运输综合报表!$AP:$AP,D$2,支线运输综合报表!$E:$E,"Coleta"),0) -> 1 | E8: =IFERROR(SUMIFS(支线运输综合报表!$AN:$AN,支线运输综合报表!$Q:$Q,$A8,支线运输综合报表!$AP:$AP,E$2,支线运输综合报表!$E:$E,"Coleta")/COUNTIFS(支线运输综合报表!$Q:$Q,$A8,支线运输综合报表!$AP:$AP,E$2,支线运输综合报表!$E:$E,"Coleta"),0) -> 0.83333333 | F8: =IFERROR(SUMIFS(支线运输综合报表!$AN:$AN,支线运输综合报表!$Q:$Q,$A8,支线运输综合报表!$AP:$AP,F$2,支线运输综合报表!$E:$E,"Coleta")/COUNTIFS(支线运输综合报表!$Q:$Q,$A8,支线运输综合报表!$AP:$AP,F$2,支线运输综合报表!$E:$E,"Coleta"),0) -> 1 | G8: =IFERROR(SUMIFS(支线运输综合报表!$AN:$AN,支线运输综合报表!$Q:$Q,$A8,支线运输综合报表!$AP:$AP,G$2,支线运输综合报表!$E:$E,"Coleta")/COUNTIFS(支线运输综合报表!$Q:$Q,$A8,支线运输综合报表!$AP:$AP,G$2,支线运输综合报表!$E:$E,"Coleta"),0) -> 1 | H8: =IFERROR(SUMIFS(支线运输综合报表!$AN:$AN,支线运输综合报表!$Q:$Q,$A8,支线运输综合报表!$AP:$AP,H$2,支线运输综合报表!$E:$E,"Coleta")/COUNTIFS(支线运输综合报表!$Q:$Q,$A8,支线运输综合报表!$AP:$AP,H$2,支线运输综合报表!$E:$E,"Coleta"),0) -> 0 | I8: =IFERROR(SUMIFS(支线运输综合报表!$AN:$AN,支线运输综合报表!$Q:$Q,$A8,支线运输综合报表!$AP:$AP,I$2,支线运输综合报表!$E:$E,"Coleta")/COUNTIFS(支线运输综合报表!$Q:$Q,$A8,支线运输综合报表!$AP:$AP,I$2,支线运输综合报表!$E:$E,"Coleta"),0) -> 0 | J8: =IFERROR(SUMIFS(支线运输综合报表!$AN:$AN,支线运输综合报表!$Q:$Q,$A8,支线运输综合报表!$AP:$AP,J$2,支线运输综合报表!$E:$E,"Coleta")/COUNTIFS(支线运输综合报表!$Q:$Q,$A8,支线运输综合报表!$AP:$AP,J$2,支线运输综合报表!$E:$E,"Coleta"),0) -> 0 | K8: =IFERROR(SUMIFS(支线运输综合报表!$AN:$AN,支线运输综合报表!$Q:$Q,$A8,支线运输综合报表!$AP:$AP,K$2,支线运输综合报表!$E:$E,"Coleta")/COUNTIFS(支线运输综合报表!$Q:$Q,$A8,支线运输综合报表!$AP:$AP,K$2,支线运输综合报表!$E:$E,"Coleta"),0) -> 0 | ... AH8: =IFERROR(SUMIFS(支线运输综合报表!$AN:$AN,支线运输综合报表!$Q:$Q,$A8,支线运输综合报表!$AP:$AP,AH$2,支线运输综合报表!$E:$E,"Coleta")/COUNTIFS(支线运输综合报表!$Q:$Q,$A8,支线运输综合报表!$AP:$AP,AH$2,支线运输综合报表!$E:$E,"Coleta"),0) -> 0
A9: PR | B9: =G9-F9 -> -0.16666667 | C9: =IFERROR(SUMIFS(支线运输综合报表!$AN:$AN,支线运输综合报表!$Q:$Q,$A9,支线运输综合报表!$E:$E,"Coleta")/COUNTIFS(支线运输综合报表!$Q:$Q,$A9,支线运输综合报表!$E:$E,"Coleta"),0) -> 0.77142857 | D9: =IFERROR(SUMIFS(支线运输综合报表!$AN:$AN,支线运输综合报表!$Q:$Q,$A9,支线运输综合报表!$AP:$AP,D$2,支线运输综合报表!$E:$E,"Coleta")/COUNTIFS(支线运输综合报表!$Q:$Q,$A9,支线运输综合报表!$AP:$AP,D$2,支线运输综合报表!$E:$E,"Coleta"),0) -> 0.77777778 | E9: =IFERROR(SUMIFS(支线运输综合报表!$AN:$AN,支线运输综合报表!$Q:$Q,$A9,支线运输综合报表!$AP:$AP,E$2,支线运输综合报表!$E:$E,"Coleta")/COUNTIFS(支线运输综合报表!$Q:$Q,$A9,支线运输综合报表!$AP:$AP,E$2,支线运输综合报表!$E:$E,"Coleta"),0) -> 0.91666667 | F9: =IFERROR(SUMIFS(支线运输综合报表!$AN:$AN,支线运输综合报表!$Q:$Q,$A9,支线运输综合报表!$AP:$AP,F$2,支线运输综合报表!$E:$E,"Coleta")/COUNTIFS(支线运输综合报表!$Q:$Q,$A9,支线运输综合报表!$AP:$AP,F$2,支线运输综合报表!$E:$E,"Coleta"),0) -> 0.66666667 | G9: =IFERROR(SUMIFS(支线运输综合报表!$AN:$AN,支线运输综合报表!$Q:$Q,$A9,支线运输综合报表!$AP:$AP,G$2,支线运输综合报表!$E:$E,"Coleta")/COUNTIFS(支线运输综合报表!$Q:$Q,$A9,支线运输综合报表!$AP:$AP,G$2,支线运输综合报表!$E:$E,"Coleta"),0) -> 0.5 | H9: =IFERROR(SUMIFS(支线运输综合报表!$AN:$AN,支线运输综合报表!$Q:$Q,$A9,支线运输综合报表!$AP:$AP,H$2,支线运输综合报表!$E:$E,"Coleta")/COUNTIFS(支线运输综合报表!$Q:$Q,$A9,支线运输综合报表!$AP:$AP,H$2,支线运输综合报表!$E:$E,"Coleta"),0) -> 0 | I9: =IFERROR(SUMIFS(支线运输综合报表!$AN:$AN,支线运输综合报表!$Q:$Q,$A9,支线运输综合报表!$AP:$AP,I$2,支线运输综合报表!$E:$E,"Coleta")/COUNTIFS(支线运输综合报表!$Q:$Q,$A9,支线运输综合报表!$AP:$AP,I$2,支线运输综合报表!$E:$E,"Coleta"),0) -> 0 | J9: =IFERROR(SUMIFS(支线运输综合报表!$AN:$AN,支线运输综合报表!$Q:$Q,$A9,支线运输综合报表!$AP:$AP,J$2,支线运输综合报表!$E:$E,"Coleta")/COUNTIFS(支线运输综合报表!$Q:$Q,$A9,支线运输综合报表!$AP:$AP,J$2,支线运输综合报表!$E:$E,"Coleta"),0) -> 0 | K9: =IFERROR(SUMIFS(支线运输综合报表!$AN:$AN,支线运输综合报表!$Q:$Q,$A9,支线运输综合报表!$AP:$AP,K$2,支线运输综合报表!$E:$E,"Coleta")/COUNTIFS(支线运输综合报表!$Q:$Q,$A9,支线运输综合报表!$AP:$AP,K$2,支线运输综合报表!$E:$E,"Coleta"),0) -> 0 | ... AH9: =IFERROR(SUMIFS(支线运输综合报表!$AN:$AN,支线运输综合报表!$Q:$Q,$A9,支线运输综合报表!$AP:$AP,AH$2,支线运输综合报表!$E:$E,"Coleta")/COUNTIFS(支线运输综合报表!$Q:$Q,$A9,支线运输综合报表!$AP:$AP,AH$2,支线运输综合报表!$E:$E,"Coleta"),0) -> 0
A10: MG | B10: =G10-F10 -> 0.047619048 | C10: =IFERROR(SUMIFS(支线运输综合报表!$AN:$AN,支线运输综合报表!$Q:$Q,$A10,支线运输综合报表!$E:$E,"Coleta")/COUNTIFS(支线运输综合报表!$Q:$Q,$A10,支线运输综合报表!$E:$E,"Coleta"),0) -> 0.94805195 | D10: =IFERROR(SUMIFS(支线运输综合报表!$AN:$AN,支线运输综合报表!$Q:$Q,$A10,支线运输综合报表!$AP:$AP,D$2,支线运输综合报表!$E:$E,"Coleta")/COUNTIFS(支线运输综合报表!$Q:$Q,$A10,支线运输综合报表!$AP:$AP,D$2,支线运输综合报表!$E:$E,"Coleta"),0) -> 0.92592593 | E10: =IFERROR(SUMIFS(支线运输综合报表!$AN:$AN,支线运输综合报表!$Q:$Q,$A10,支线运输综合报表!$AP:$AP,E$2,支线运输综合报表!$E:$E,"Coleta")/COUNTIFS(支线运输综合报表!$Q:$Q,$A10,支线运输综合报表!$AP:$AP,E$2,支线运输综合报表!$E:$E,"Coleta"),0) -> 0.95833333 | F10: =IFERROR(SUMIFS(支线运输综合报表!$AN:$AN,支线运输综合报表!$Q:$Q,$A10,支线运输综合报表!$AP:$AP,F$2,支线运输综合报表!$E:$E,"Coleta")/COUNTIFS(支线运输综合报表!$Q:$Q,$A10,支线运输综合报表!$AP:$AP,F$2,支线运输综合报表!$E:$E,"Coleta"),0) -> 0.95238095 | G10: =IFERROR(SUMIFS(支线运输综合报表!$AN:$AN,支线运输综合报表!$Q:$Q,$A10,支线运输综合报表!$AP:$AP,G$2,支线运输综合报表!$E:$E,"Coleta")/COUNTIFS(支线运输综合报表!$Q:$Q,$A10,支线运输综合报表!$AP:$AP,G$2,支线运输综合报表!$E:$E,"Coleta"),0) -> 1 | H10: =IFERROR(SUMIFS(支线运输综合报表!$AN:$AN,支线运输综合报表!$Q:$Q,$A10,支线运输综合报表!$AP:$AP,H$2,支线运输综合报表!$E:$E,"Coleta")/COUNTIFS(支线运输综合报表!$Q:$Q,$A10,支线运输综合报表!$AP:$AP,H$2,支线运输综合报表!$E:$E,"Coleta"),0) -> 0 | I10: =IFERROR(SUMIFS(支线运输综合报表!$AN:$AN,支线运输综合报表!$Q:$Q,$A10,支线运输综合报表!$AP:$AP,I$2,支线运输综合报表!$E:$E,"Coleta")/COUNTIFS(支线运输综合报表!$Q:$Q,$A10,支线运输综合报表!$AP:$AP,I$2,支线运输综合报表!$E:$E,"Coleta"),0) -> 0 | J10: =IFERROR(SUMIFS(支线运输综合报表!$AN:$AN,支线运输综合报表!$Q:$Q,$A10,支线运输综合报表!$AP:$AP,J$2,支线运输综合报表!$E:$E,"Coleta")/COUNTIFS(支线运输综合报表!$Q:$Q,$A10,支线运输综合报表!$AP:$AP,J$2,支线运输综合报表!$E:$E,"Coleta"),0) -> 0 | K10: =IFERROR(SUMIFS(支线运输综合报表!$AN:$AN,支线运输综合报表!$Q:$Q,$A10,支线运输综合报表!$AP:$AP,K$2,支线运输综合报表!$E:$E,"Coleta")/COUNTIFS(支线运输综合报表!$Q:$Q,$A10,支线运输综合报表!$AP:$AP,K$2,支线运输综合报表!$E:$E,"Coleta"),0) -> 0 | ... AH10: =IFERROR(SUMIFS(支线运输综合报表!$AN:$AN,支线运输综合报表!$Q:$Q,$A10,支线运输综合报表!$AP:$AP,AH$2,支线运输综合报表!$E:$E,"Coleta")/COUNTIFS(支线运输综合报表!$Q:$Q,$A10,支线运输综合报表!$AP:$AP,AH$2,支线运输综合报表!$E:$E,"Coleta"),0) -> 0
A11: CE | B11: =G11-F11 -> -1 | C11: =IFERROR(SUMIFS(支线运输综合报表!$AN:$AN,支线运输综合报表!$Q:$Q,$A11,支线运输综合报表!$E:$E,"Coleta")/COUNTIFS(支线运输综合报表!$Q:$Q,$A11,支线运输综合报表!$E:$E,"Coleta"),0) -> 1 | D11: =IFERROR(SUMIFS(支线运输综合报表!$AN:$AN,支线运输综合报表!$Q:$Q,$A11,支线运输综合报表!$AP:$AP,D$2,支线运输综合报表!$E:$E,"Coleta")/COUNTIFS(支线运输综合报表!$Q:$Q,$A11,支线运输综合报表!$AP:$AP,D$2,支线运输综合报表!$E:$E,"Coleta"),0) -> 1 | E11: =IFERROR(SUMIFS(支线运输综合报表!$AN:$AN,支线运输综合报表!$Q:$Q,$A11,支线运输综合报表!$AP:$AP,E$2,支线运输综合报表!$E:$E,"Coleta")/COUNTIFS(支线运输综合报表!$Q:$Q,$A11,支线运输综合报表!$AP:$AP,E$2,支线运输综合报表!$E:$E,"Coleta"),0) -> 1 | F11: =IFERROR(SUMIFS(支线运输综合报表!$AN:$AN,支线运输综合报表!$Q:$Q,$A11,支线运输综合报表!$AP:$AP,F$2,支线运输综合报表!$E:$E,"Coleta")/COUNTIFS(支线运输综合报表!$Q:$Q,$A11,支线运输综合报表!$AP:$AP,F$2,支线运输综合报表!$E:$E,"Coleta"),0) -> 1 | G11: =IFERROR(SUMIFS(支线运输综合报表!$AN:$AN,支线运输综合报表!$Q:$Q,$A11,支线运输综合报表!$AP:$AP,G$2,支线运输综合报表!$E:$E,"Coleta")/COUNTIFS(支线运输综合报表!$Q:$Q,$A11,支线运输综合报表!$AP:$AP,G$2,支线运输综合报表!$E:$E,"Coleta"),0) -> 0 | H11: =IFERROR(SUMIFS(支线运输综合报表!$AN:$AN,支线运输综合报表!$Q:$Q,$A11,支线运输综合报表!$AP:$AP,H$2,支线运输综合报表!$E:$E,"Coleta")/COUNTIFS(支线运输综合报表!$Q:$Q,$A11,支线运输综合报表!$AP:$AP,H$2,支线运输综合报表!$E:$E,"Coleta"),0) -> 0 | I11: =IFERROR(SUMIFS(支线运输综合报表!$AN:$AN,支线运输综合报表!$Q:$Q,$A11,支线运输综合报表!$AP:$AP,I$2,支线运输综合报表!$E:$E,"Coleta")/COUNTIFS(支线运输综合报表!$Q:$Q,$A11,支线运输综合报表!$AP:$AP,I$2,支线运输综合报表!$E:$E,"Coleta"),0) -> 0 | J11: =IFERROR(SUMIFS(支线运输综合报表!$AN:$AN,支线运输综合报表!$Q:$Q,$A11,支线运输综合报表!$AP:$AP,J$2,支线运输综合报表!$E:$E,"Coleta")/COUNTIFS(支线运输综合报表!$Q:$Q,$A11,支线运输综合报表!$AP:$AP,J$2,支线运输综合报表!$E:$E,"Coleta"),0) -> 0 | K11: =IFERROR(SUMIFS(支线运输综合报表!$AN:$AN,支线运输综合报表!$Q:$Q,$A11,支线运输综合报表!$AP:$AP,K$2,支线运输综合报表!$E:$E,"Coleta")/COUNTIFS(支线运输综合报表!$Q:$Q,$A11,支线运输综合报表!$AP:$AP,K$2,支线运输综合报表!$E:$E,"Coleta"),0) -> 0 | ... AH11: =IFERROR(SUMIFS(支线运输综合报表!$AN:$AN,支线运输综合报表!$Q:$Q,$A11,支线运输综合报表!$AP:$AP,AH$2,支线运输综合报表!$E:$E,"Coleta")/COUNTIFS(支线运输综合报表!$Q:$Q,$A11,支线运输综合报表!$AP:$AP,AH$2,支线运输综合报表!$E:$E,"Coleta"),0) -> 0
A12: 散货封车率趋势Tendência da LACRE-Entrega
A13: 发车区域Região de Saida | B13: 环比±Variação | C13: 10月累计Acumulado de Outubro | D13: 46296 | E13: =D13+1 -> 46297 | F13: =E13+1 -> 46298 | G13: =F13+1 -> 46299 | H13: =G13+1 -> 46300 | I13: =H13+1 -> 46301 | J13: =I13+1 -> 46302 | K13: =J13+1 -> 46303 | L13: =K13+1 -> 46304 | ... AH13: =AG13+1 -> 46326 | AI13: 近七天趋势
A14: 合计 | B14: =G14-F14 -> -0.0098599373 | C14: =IFERROR(SUMIFS(支线运输综合报表!$AN:$AN,支线运输综合报表!$E:$E,"Entrega")/COUNTIFS(支线运输综合报表!$E:$E,"Entrega"),0) -> 0.97977664 | D14: =IFERROR(SUMIFS(支线运输综合报表!$AN:$AN,支线运输综合报表!$AP:$AP,D13,支线运输综合报表!$E:$E,"Entrega")/COUNTIFS(支线运输综合报表!$AP:$AP,D13,支线运输综合报表!$E:$E,"Entrega"),0) -> 0.98569857 | E14: =IFERROR(SUMIFS(支线运输综合报表!$AN:$AN,支线运输综合报表!$AP:$AP,E13,支线运输综合报表!$E:$E,"Entrega")/COUNTIFS(支线运输综合报表!$AP:$AP,E13,支线运输综合报表!$E:$E,"Entrega"),0) -> 0.98175966 | F14: =IFERROR(SUMIFS(支线运输综合报表!$AN:$AN,支线运输综合报表!$AP:$AP,F13,支线运输综合报表!$E:$E,"Entrega")/COUNTIFS(支线运输综合报表!$AP:$AP,F13,支线运输综合报表!$E:$E,"Entrega"),0) -> 0.97849462 | G14: =IFERROR(SUMIFS(支线运输综合报表!$AN:$AN,支线运输综合报表!$AP:$AP,G13,支线运输综合报表!$E:$E,"Entrega")/COUNTIFS(支线运输综合报表!$AP:$AP,G13,支线运输综合报表!$E:$E,"Entrega"),0) -> 0.96863469 | H14: =IFERROR(SUMIFS(支线运输综合报表!$AN:$AN,支线运输综合报表!$AP:$AP,H13,支线运输综合报表!$E:$E,"Entrega")/COUNTIFS(支线运输综合报表!$AP:$AP,H13,支线运输综合报表!$E:$E,"Entrega"),0) -> 0 | I14: =IFERROR(SUMIFS(支线运输综合报表!$AN:$AN,支线运输综合报表!$AP:$AP,I13,支线运输综合报表!$E:$E,"Entrega")/COUNTIFS(支线运输综合报表!$AP:$AP,I13,支线运输综合报表!$E:$E,"Entrega"),0) -> 0 | J14: =IFERROR(SUMIFS(支线运输综合报表!$AN:$AN,支线运输综合报表!$AP:$AP,J13,支线运输综合报表!$E:$E,"Entrega")/COUNTIFS(支线运输综合报表!$AP:$AP,J13,支线运输综合报表!$E:$E,"Entrega"),0) -> 0 | K14: =IFERROR(SUMIFS(支线运输综合报表!$AN:$AN,支线运输综合报表!$AP:$AP,K13,支线运输综合报表!$E:$E,"Entrega")/COUNTIFS(支线运输综合报表!$AP:$AP,K13,支线运输综合报表!$E:$E,"Entrega"),0) -> 0 | ... AH14: =IFERROR(SUMIFS(支线运输综合报表!$AN:$AN,支线运输综合报表!$AP:$AP,AH13,支线运输综合报表!$E:$E,"Entrega")/COUNTIFS(支线运输综合报表!$AP:$AP,AH13,支线运输综合报表!$E:$E,"Entrega"),0) -> 0
A15: CE | B15: =G15-F15 -> 0.0064935065 | C15: =IFERROR(SUMIFS(支线运输综合报表!$AN:$AN,支线运输综合报表!$Q:$Q,$A15,支线运输综合报表!$E:$E,"Entrega")/COUNTIFS(支线运输综合报表!$Q:$Q,$A15,支线运输综合报表!$E:$E,"Entrega"),0) -> 0.99088838 | D15: =IFERROR(SUMIFS(支线运输综合报表!$AN:$AN,支线运输综合报表!$Q:$Q,$A15,支线运输综合报表!$AP:$AP,D$2,支线运输综合报表!$E:$E,"Entrega")/COUNTIFS(支线运输综合报表!$Q:$Q,$A15,支线运输综合报表!$AP:$AP,D$2,支线运输综合报表!$E:$E,"Entrega"),0) -> 0.98484848 | E15: =IFERROR(SUMIFS(支线运输综合报表!$AN:$AN,支线运输综合报表!$Q:$Q,$A15,支线运输综合报表!$AP:$AP,E$2,支线运输综合报表!$E:$E,"Entrega")/COUNTIFS(支线运输综合报表!$Q:$Q,$A15,支线运输综合报表!$AP:$AP,E$2,支线运输综合报表!$E:$E,"Entrega"),0) -> 0.99315068 | F15: =IFERROR(SUMIFS(支线运输综合报表!$AN:$AN,支线运输综合报表!$Q:$Q,$A15,支线运输综合报表!$AP:$AP,F$2,支线运输综合报表!$E:$E,"Entrega")/COUNTIFS(支线运输综合报表!$Q:$Q,$A15,支线运输综合报表!$AP:$AP,F$2,支线运输综合报表!$E:$E,"Entrega"),0) -> 0.99350649 | G15: =IFERROR(SUMIFS(支线运输综合报表!$AN:$AN,支线运输综合报表!$Q:$Q,$A15,支线运输综合报表!$AP:$AP,G$2,支线运输综合报表!$E:$E,"Entrega")/COUNTIFS(支线运输综合报表!$Q:$Q,$A15,支线运输综合报表!$AP:$AP,G$2,支线运输综合报表!$E:$E,"Entrega"),0) -> 1 | H15: =IFERROR(SUMIFS(支线运输综合报表!$AN:$AN,支线运输综合报表!$Q:$Q,$A15,支线运输综合报表!$AP:$AP,H$2,支线运输综合报表!$E:$E,"Entrega")/COUNTIFS(支线运输综合报表!$Q:$Q,$A15,支线运输综合报表!$AP:$AP,H$2,支线运输综合报表!$E:$E,"Entrega"),0) -> 0 | I15: =IFERROR(SUMIFS(支线运输综合报表!$AN:$AN,支线运输综合报表!$Q:$Q,$A15,支线运输综合报表!$AP:$AP,I$2,支线运输综合报表!$E:$E,"Entrega")/COUNTIFS(支线运输综合报表!$Q:$Q,$A15,支线运输综合报表!$AP:$AP,I$2,支线运输综合报表!$E:$E,"Entrega"),0) -> 0 | J15: =IFERROR(SUMIFS(支线运输综合报表!$AN:$AN,支线运输综合报表!$Q:$Q,$A15,支线运输综合报表!$AP:$AP,J$2,支线运输综合报表!$E:$E,"Entrega")/COUNTIFS(支线运输综合报表!$Q:$Q,$A15,支线运输综合报表!$AP:$AP,J$2,支线运输综合报表!$E:$E,"Entrega"),0) -> 0 | K15: =IFERROR(SUMIFS(支线运输综合报表!$AN:$AN,支线运输综合报表!$Q:$Q,$A15,支线运输综合报表!$AP:$AP,K$2,支线运输综合报表!$E:$E,"Entrega")/COUNTIFS(支线运输综合报表!$Q:$Q,$A15,支线运输综合报表!$AP:$AP,K$2,支线运输综合报表!$E:$E,"Entrega"),0) -> 0 | ... AH15: =IFERROR(SUMIFS(支线运输综合报表!$AN:$AN,支线运输综合报表!$Q:$Q,$A15,支线运输综合报表!$AP:$AP,AH$2,支线运输综合报表!$E:$E,"Entrega")/COUNTIFS(支线运输综合报表!$Q:$Q,$A15,支线运输综合报表!$AP:$AP,AH$2,支线运输综合报表!$E:$E,"Entrega"),0) -> 0
A16: SPN | B16: =G16-F16 -> 0 | C16: =IFERROR(SUMIFS(支线运输综合报表!$AN:$AN,支线运输综合报表!$Q:$Q,$A16,支线运输综合报表!$E:$E,"Entrega")/COUNTIFS(支线运输综合报表!$Q:$Q,$A16,支线运输综合报表!$E:$E,"Entrega"),0) -> 1 | D16: =IFERROR(SUMIFS(支线运输综合报表!$AN:$AN,支线运输综合报表!$Q:$Q,$A16,支线运输综合报表!$AP:$AP,D$2,支线运输综合报表!$E:$E,"Entrega")/COUNTIFS(支线运输综合报表!$Q:$Q,$A16,支线运输综合报表!$AP:$AP,D$2,支线运输综合报表!$E:$E,"Entrega"),0) -> 1 | E16: =IFERROR(SUMIFS(支线运输综合报表!$AN:$AN,支线运输综合报表!$Q:$Q,$A16,支线运输综合报表!$AP:$AP,E$2,支线运输综合报表!$E:$E,"Entrega")/COUNTIFS(支线运输综合报表!$Q:$Q,$A16,支线运输综合报表!$AP:$AP,E$2,支线运输综合报表!$E:$E,"Entrega"),0) -> 1 | F16: =IFERROR(SUMIFS(支线运输综合报表!$AN:$AN,支线运输综合报表!$Q:$Q,$A16,支线运输综合报表!$AP:$AP,F$2,支线运输综合报表!$E:$E,"Entrega")/COUNTIFS(支线运输综合报表!$Q:$Q,$A16,支线运输综合报表!$AP:$AP,F$2,支线运输综合报表!$E:$E,"Entrega"),0) -> 1 | G16: =IFERROR(SUMIFS(支线运输综合报表!$AN:$AN,支线运输综合报表!$Q:$Q,$A16,支线运输综合报表!$AP:$AP,G$2,支线运输综合报表!$E:$E,"Entrega")/COUNTIFS(支线运输综合报表!$Q:$Q,$A16,支线运输综合报表!$AP:$AP,G$2,支线运输综合报表!$E:$E,"Entrega"),0) -> 1 | H16: =IFERROR(SUMIFS(支线运输综合报表!$AN:$AN,支线运输综合报表!$Q:$Q,$A16,支线运输综合报表!$AP:$AP,H$2,支线运输综合报表!$E:$E,"Entrega")/COUNTIFS(支线运输综合报表!$Q:$Q,$A16,支线运输综合报表!$AP:$AP,H$2,支线运输综合报表!$E:$E,"Entrega"),0) -> 0 | I16: =IFERROR(SUMIFS(支线运输综合报表!$AN:$AN,支线运输综合报表!$Q:$Q,$A16,支线运输综合报表!$AP:$AP,I$2,支线运输综合报表!$E:$E,"Entrega")/COUNTIFS(支线运输综合报表!$Q:$Q,$A16,支线运输综合报表!$AP:$AP,I$2,支线运输综合报表!$E:$E,"Entrega"),0) -> 0 | J16: =IFERROR(SUMIFS(支线运输综合报表!$AN:$AN,支线运输综合报表!$Q:$Q,$A16,支线运输综合报表!$AP:$AP,J$2,支线运输综合报表!$E:$E,"Entrega")/COUNTIFS(支线运输综合报表!$Q:$Q,$A16,支线运输综合报表!$AP:$AP,J$2,支线运输综合报表!$E:$E,"Entrega"),0) -> 0 | K16: =IFERROR(SUMIFS(支线运输综合报表!$AN:$AN,支线运输综合报表!$Q:$Q,$A16,支线运输综合报表!$AP:$AP,K$2,支线运输综合报表!$E:$E,"Entrega")/COUNTIFS(支线运输综合报表!$Q:$Q,$A16,支线运输综合报表!$AP:$AP,K$2,支线运输综合报表!$E:$E,"Entrega"),0) -> 0 | ... AH16: =IFERROR(SUMIFS(支线运输综合报表!$AN:$AN,支线运输综合报表!$Q:$Q,$A16,支线运输综合报表!$AP:$AP,AH$2,支线运输综合报表!$E:$E,"Entrega")/COUNTIFS(支线运输综合报表!$Q:$Q,$A16,支线运输综合报表!$AP:$AP,AH$2,支线运输综合报表!$E:$E,"Entrega"),0) -> 0
A17: SPS | B17: =G17-F17 -> 0.00054674686 | C17: =IFERROR(SUMIFS(支线运输综合报表!$AN:$AN,支线运输综合报表!$Q:$Q,$A17,支线运输综合报表!$E:$E,"Entrega")/COUNTIFS(支线运输综合报表!$Q:$Q,$A17,支线运输综合报表!$E:$E,"Entrega"),0) -> 0.98907956 | D17: =IFERROR(SUMIFS(支线运输综合报表!$AN:$AN,支线运输综合报表!$Q:$Q,$A17,支线运输综合报表!$AP:$AP,D$2,支线运输综合报表!$E:$E,"Entrega")/COUNTIFS(支线运输综合报表!$Q:$Q,$A17,支线运输综合报表!$AP:$AP,D$2,支线运输综合报表!$E:$E,"Entrega"),0) -> 1 | E17: =IFERROR(SUMIFS(支线运输综合报表!$AN:$AN,支线运输综合报表!$Q:$Q,$A17,支线运输综合报表!$AP:$AP,E$2,支线运输综合报表!$E:$E,"Entrega")/COUNTIFS(支线运输综合报表!$Q:$Q,$A17,支线运输综合报表!$AP:$AP,E$2,支线运输综合报表!$E:$E,"Entrega"),0) -> 0.97802198 | F17: =IFERROR(SUMIFS(支线运输综合报表!$AN:$AN,支线运输综合报表!$Q:$Q,$A17,支线运输综合报表!$AP:$AP,F$2,支线运输综合报表!$E:$E,"Entrega")/COUNTIFS(支线运输综合报表!$Q:$Q,$A17,支线运输综合报表!$AP:$AP,F$2,支线运输综合报表!$E:$E,"Entrega"),0) -> 0.98870056 | G17: =IFERROR(SUMIFS(支线运输综合报表!$AN:$AN,支线运输综合报表!$Q:$Q,$A17,支线运输综合报表!$AP:$AP,G$2,支线运输综合报表!$E:$E,"Entrega")/COUNTIFS(支线运输综合报表!$Q:$Q,$A17,支线运输综合报表!$AP:$AP,G$2,支线运输综合报表!$E:$E,"Entrega"),0) -> 0.98924731 | H17: =IFERROR(SUMIFS(支线运输综合报表!$AN:$AN,支线运输综合报表!$Q:$Q,$A17,支线运输综合报表!$AP:$AP,H$2,支线运输综合报表!$E:$E,"Entrega")/COUNTIFS(支线运输综合报表!$Q:$Q,$A17,支线运输综合报表!$AP:$AP,H$2,支线运输综合报表!$E:$E,"Entrega"),0) -> 0 | I17: =IFERROR(SUMIFS(支线运输综合报表!$AN:$AN,支线运输综合报表!$Q:$Q,$A17,支线运输综合报表!$AP:$AP,I$2,支线运输综合报表!$E:$E,"Entrega")/COUNTIFS(支线运输综合报表!$Q:$Q,$A17,支线运输综合报表!$AP:$AP,I$2,支线运输综合报表!$E:$E,"Entrega"),0) -> 0 | J17: =IFERROR(SUMIFS(支线运输综合报表!$AN:$AN,支线运输综合报表!$Q:$Q,$A17,支线运输综合报表!$AP:$AP,J$2,支线运输综合报表!$E:$E,"Entrega")/COUNTIFS(支线运输综合报表!$Q:$Q,$A17,支线运输综合报表!$AP:$AP,J$2,支线运输综合报表!$E:$E,"Entrega"),0) -> 0 | K17: =IFERROR(SUMIFS(支线运输综合报表!$AN:$AN,支线运输综合报表!$Q:$Q,$A17,支线运输综合报表!$AP:$AP,K$2,支线运输综合报表!$E:$E,"Entrega")/COUNTIFS(支线运输综合报表!$Q:$Q,$A17,支线运输综合报表!$AP:$AP,K$2,支线运输综合报表!$E:$E,"Entrega"),0) -> 0 | ... AH17: =IFERROR(SUMIFS(支线运输综合报表!$AN:$AN,支线运输综合报表!$Q:$Q,$A17,支线运输综合报表!$AP:$AP,AH$2,支线运输综合报表!$E:$E,"Entrega")/COUNTIFS(支线运输综合报表!$Q:$Q,$A17,支线运输综合报表!$AP:$AP,AH$2,支线运输综合报表!$E:$E,"Entrega"),0) -> 0
A18: GP | B18: =G18-F18 -> 0.007952936 | C18: =IFERROR(SUMIFS(支线运输综合报表!$AN:$AN,支线运输综合报表!$Q:$Q,$A18,支线运输综合报表!$E:$E,"Entrega")/COUNTIFS(支线运输综合报表!$Q:$Q,$A18,支线运输综合报表!$E:$E,"Entrega"),0) -> 0.97981651 | D18: =IFERROR(SUMIFS(支线运输综合报表!$AN:$AN,支线运输综合报表!$Q:$Q,$A18,支线运输综合报表!$AP:$AP,D$2,支线运输综合报表!$E:$E,"Entrega")/COUNTIFS(支线运输综合报表!$Q:$Q,$A18,支线运输综合报表!$AP:$AP,D$2,支线运输综合报表!$E:$E,"Entrega"),0) -> 0.99264706 | E18: =IFERROR(SUMIFS(支线运输综合报表!$AN:$AN,支线运输综合报表!$Q:$Q,$A18,支线运输综合报表!$AP:$AP,E$2,支线运输综合报表!$E:$E,"Entrega")/COUNTIFS(支线运输综合报表!$Q:$Q,$A18,支线运输综合报表!$AP:$AP,E$2,支线运输综合报表!$E:$E,"Entrega"),0) -> 0.97826087 | F18: =IFERROR(SUMIFS(支线运输综合报表!$AN:$AN,支线运输综合报表!$Q:$Q,$A18,支线运输综合报表!$AP:$AP,F$2,支线运输综合报表!$E:$E,"Entrega")/COUNTIFS(支线运输综合报表!$Q:$Q,$A18,支线运输综合报表!$AP:$AP,F$2,支线运输综合报表!$E:$E,"Entrega"),0) -> 0.97014925 | G18: =IFERROR(SUMIFS(支线运输综合报表!$AN:$AN,支线运输综合报表!$Q:$Q,$A18,支线运输综合报表!$AP:$AP,G$2,支线运输综合报表!$E:$E,"Entrega")/COUNTIFS(支线运输综合报表!$Q:$Q,$A18,支线运输综合报表!$AP:$AP,G$2,支线运输综合报表!$E:$E,"Entrega"),0) -> 0.97810219 | H18: =IFERROR(SUMIFS(支线运输综合报表!$AN:$AN,支线运输综合报表!$Q:$Q,$A18,支线运输综合报表!$AP:$AP,H$2,支线运输综合报表!$E:$E,"Entrega")/COUNTIFS(支线运输综合报表!$Q:$Q,$A18,支线运输综合报表!$AP:$AP,H$2,支线运输综合报表!$E:$E,"Entrega"),0) -> 0 | I18: =IFERROR(SUMIFS(支线运输综合报表!$AN:$AN,支线运输综合报表!$Q:$Q,$A18,支线运输综合报表!$AP:$AP,I$2,支线运输综合报表!$E:$E,"Entrega")/COUNTIFS(支线运输综合报表!$Q:$Q,$A18,支线运输综合报表!$AP:$AP,I$2,支线运输综合报表!$E:$E,"Entrega"),0) -> 0 | J18: =IFERROR(SUMIFS(支线运输综合报表!$AN:$AN,支线运输综合报表!$Q:$Q,$A18,支线运输综合报表!$AP:$AP,J$2,支线运输综合报表!$E:$E,"Entrega")/COUNTIFS(支线运输综合报表!$Q:$Q,$A18,支线运输综合报表!$AP:$AP,J$2,支线运输综合报表!$E:$E,"Entrega"),0) -> 0 | K18: =IFERROR(SUMIFS(支线运输综合报表!$AN:$AN,支线运输综合报表!$Q:$Q,$A18,支线运输综合报表!$AP:$AP,K$2,支线运输综合报表!$E:$E,"Entrega")/COUNTIFS(支线运输综合报表!$Q:$Q,$A18,支线运输综合报表!$AP:$AP,K$2,支线运输综合报表!$E:$E,"Entrega"),0) -> 0 | ... AH18: =IFERROR(SUMIFS(支线运输综合报表!$AN:$AN,支线运输综合报表!$Q:$Q,$A18,支线运输综合报表!$AP:$AP,AH$2,支线运输综合报表!$E:$E,"Entrega")/COUNTIFS(支线运输综合报表!$Q:$Q,$A18,支线运输综合报表!$AP:$AP,AH$2,支线运输综合报表!$E:$E,"Entrega"),0) -> 0
A19: SPE | B19: =G19-F19 -> -0.061315496 | C19: =IFERROR(SUMIFS(支线运输综合报表!$AN:$AN,支线运输综合报表!$Q:$Q,$A19,支线运输综合报表!$E:$E,"Entrega")/COUNTIFS(支线运输综合报表!$Q:$Q,$A19,支线运输综合报表!$E:$E,"Entrega"),0) -> 0.97744361 | D19: =IFERROR(SUMIFS(支线运输综合报表!$AN:$AN,支线运输综合报表!$Q:$Q,$A19,支线运输综合报表!$AP:$AP,D$2,支线运输综合报表!$E:$E,"Entrega")/COUNTIFS(支线运输综合报表!$Q:$Q,$A19,支线运输综合报表!$AP:$AP,D$2,支线运输综合报表!$E:$E,"Entrega"),0) -> 1 | E19: =IFERROR(SUMIFS(支线运输综合报表!$AN:$AN,支线运输综合报表!$Q:$Q,$A19,支线运输综合报表!$AP:$AP,E$2,支线运输综合报表!$E:$E,"Entrega")/COUNTIFS(支线运输综合报表!$Q:$Q,$A19,支线运输综合报表!$AP:$AP,E$2,支线运输综合报表!$E:$E,"Entrega"),0) -> 1 | F19: =IFERROR(SUMIFS(支线运输综合报表!$AN:$AN,支线运输综合报表!$Q:$Q,$A19,支线运输综合报表!$AP:$AP,F$2,支线运输综合报表!$E:$E,"Entrega")/COUNTIFS(支线运输综合报表!$Q:$Q,$A19,支线运输综合报表!$AP:$AP,F$2,支线运输综合报表!$E:$E,"Entrega"),0) -> 0.97435897 | G19: =IFERROR(SUMIFS(支线运输综合报表!$AN:$AN,支线运输综合报表!$Q:$Q,$A19,支线运输综合报表!$AP:$AP,G$2,支线运输综合报表!$E:$E,"Entrega")/COUNTIFS(支线运输综合报表!$Q:$Q,$A19,支线运输综合报表!$AP:$AP,G$2,支线运输综合报表!$E:$E,"Entrega"),0) -> 0.91304348 | H19: =IFERROR(SUMIFS(支线运输综合报表!$AN:$AN,支线运输综合报表!$Q:$Q,$A19,支线运输综合报表!$AP:$AP,H$2,支线运输综合报表!$E:$E,"Entrega")/COUNTIFS(支线运输综合报表!$Q:$Q,$A19,支线运输综合报表!$AP:$AP,H$2,支线运输综合报表!$E:$E,"Entrega"),0) -> 0 | I19: =IFERROR(SUMIFS(支线运输综合报表!$AN:$AN,支线运输综合报表!$Q:$Q,$A19,支线运输综合报表!$AP:$AP,I$2,支线运输综合报表!$E:$E,"Entrega")/COUNTIFS(支线运输综合报表!$Q:$Q,$A19,支线运输综合报表!$AP:$AP,I$2,支线运输综合报表!$E:$E,"Entrega"),0) -> 0 | J19: =IFERROR(SUMIFS(支线运输综合报表!$AN:$AN,支线运输综合报表!$Q:$Q,$A19,支线运输综合报表!$AP:$AP,J$2,支线运输综合报表!$E:$E,"Entrega")/COUNTIFS(支线运输综合报表!$Q:$Q,$A19,支线运输综合报表!$AP:$AP,J$2,支线运输综合报表!$E:$E,"Entrega"),0) -> 0 | K19: =IFERROR(SUMIFS(支线运输综合报表!$AN:$AN,支线运输综合报表!$Q:$Q,$A19,支线运输综合报表!$AP:$AP,K$2,支线运输综合报表!$E:$E,"Entrega")/COUNTIFS(支线运输综合报表!$Q:$Q,$A19,支线运输综合报表!$AP:$AP,K$2,支线运输综合报表!$E:$E,"Entrega"),0) -> 0 | ... AH19: =IFERROR(SUMIFS(支线运输综合报表!$AN:$AN,支线运输综合报表!$Q:$Q,$A19,支线运输综合报表!$AP:$AP,AH$2,支线运输综合报表!$E:$E,"Entrega")/COUNTIFS(支线运输综合报表!$Q:$Q,$A19,支线运输综合报表!$AP:$AP,AH$2,支线运输综合报表!$E:$E,"Entrega"),0) -> 0
A20: RJ | B20: =G20-F20 -> -0.017701863 | C20: =IFERROR(SUMIFS(支线运输综合报表!$AN:$AN,支线运输综合报表!$Q:$Q,$A20,支线运输综合报表!$E:$E,"Entrega")/COUNTIFS(支线运输综合报表!$Q:$Q,$A20,支线运输综合报表!$E:$E,"Entrega"),0) -> 0.98107256 | D20: =IFERROR(SUMIFS(支线运输综合报表!$AN:$AN,支线运输综合报表!$Q:$Q,$A20,支线运输综合报表!$AP:$AP,D$2,支线运输综合报表!$E:$E,"Entrega")/COUNTIFS(支线运输综合报表!$Q:$Q,$A20,支线运输综合报表!$AP:$AP,D$2,支线运输综合报表!$E:$E,"Entrega"),0) -> 0.97916667 | E20: =IFERROR(SUMIFS(支线运输综合报表!$AN:$AN,支线运输综合报表!$Q:$Q,$A20,支线运输综合报表!$AP:$AP,E$2,支线运输综合报表!$E:$E,"Entrega")/COUNTIFS(支线运输综合报表!$Q:$Q,$A20,支线运输综合报表!$AP:$AP,E$2,支线运输综合报表!$E:$E,"Entrega"),0) -> 0.9787234 | F20: =IFERROR(SUMIFS(支线运输综合报表!$AN:$AN,支线运输综合报表!$Q:$Q,$A20,支线运输综合报表!$AP:$AP,F$2,支线运输综合报表!$E:$E,"Entrega")/COUNTIFS(支线运输综合报表!$Q:$Q,$A20,支线运输综合报表!$AP:$AP,F$2,支线运输综合报表!$E:$E,"Entrega"),0) -> 0.98913043 | G20: =IFERROR(SUMIFS(支线运输综合报表!$AN:$AN,支线运输综合报表!$Q:$Q,$A20,支线运输综合报表!$AP:$AP,G$2,支线运输综合报表!$E:$E,"Entrega")/COUNTIFS(支线运输综合报表!$Q:$Q,$A20,支线运输综合报表!$AP:$AP,G$2,支线运输综合报表!$E:$E,"Entrega"),0) -> 0.97142857 | H20: =IFERROR(SUMIFS(支线运输综合报表!$AN:$AN,支线运输综合报表!$Q:$Q,$A20,支线运输综合报表!$AP:$AP,H$2,支线运输综合报表!$E:$E,"Entrega")/COUNTIFS(支线运输综合报表!$Q:$Q,$A20,支线运输综合报表!$AP:$AP,H$2,支线运输综合报表!$E:$E,"Entrega"),0) -> 0 | I20: =IFERROR(SUMIFS(支线运输综合报表!$AN:$AN,支线运输综合报表!$Q:$Q,$A20,支线运输综合报表!$AP:$AP,I$2,支线运输综合报表!$E:$E,"Entrega")/COUNTIFS(支线运输综合报表!$Q:$Q,$A20,支线运输综合报表!$AP:$AP,I$2,支线运输综合报表!$E:$E,"Entrega"),0) -> 0 | J20: =IFERROR(SUMIFS(支线运输综合报表!$AN:$AN,支线运输综合报表!$Q:$Q,$A20,支线运输综合报表!$AP:$AP,J$2,支线运输综合报表!$E:$E,"Entrega")/COUNTIFS(支线运输综合报表!$Q:$Q,$A20,支线运输综合报表!$AP:$AP,J$2,支线运输综合报表!$E:$E,"Entrega"),0) -> 0 | K20: =IFERROR(SUMIFS(支线运输综合报表!$AN:$AN,支线运输综合报表!$Q:$Q,$A20,支线运输综合报表!$AP:$AP,K$2,支线运输综合报表!$E:$E,"Entrega")/COUNTIFS(支线运输综合报表!$Q:$Q,$A20,支线运输综合报表!$AP:$AP,K$2,支线运输综合报表!$E:$E,"Entrega"),0) -> 0 | ... AH20: =IFERROR(SUMIFS(支线运输综合报表!$AN:$AN,支线运输综合报表!$Q:$Q,$A20,支线运输综合报表!$AP:$AP,AH$2,支线运输综合报表!$E:$E,"Entrega")/COUNTIFS(支线运输综合报表!$Q:$Q,$A20,支线运输综合报表!$AP:$AP,AH$2,支线运输综合报表!$E:$E,"Entrega"),0) -> 0
A21: PR | B21: =G21-F21 -> -0.043664996 | C21: =IFERROR(SUMIFS(支线运输综合报表!$AN:$AN,支线运输综合报表!$Q:$Q,$A21,支线运输综合报表!$E:$E,"Entrega")/COUNTIFS(支线运输综合报表!$Q:$Q,$A21,支线运输综合报表!$E:$E,"Entrega"),0) -> 0.94396552 | D21: =IFERROR(SUMIFS(支线运输综合报表!$AN:$AN,支线运输综合报表!$Q:$Q,$A21,支线运输综合报表!$AP:$AP,D$2,支线运输综合报表!$E:$E,"Entrega")/COUNTIFS(支线运输综合报表!$Q:$Q,$A21,支线运输综合报表!$AP:$AP,D$2,支线运输综合报表!$E:$E,"Entrega"),0) -> 0.95384615 | E21: =IFERROR(SUMIFS(支线运输综合报表!$AN:$AN,支线运输综合报表!$Q:$Q,$A21,支线运输综合报表!$AP:$AP,E$2,支线运输综合报表!$E:$E,"Entrega")/COUNTIFS(支线运输综合报表!$Q:$Q,$A21,支线运输综合报表!$AP:$AP,E$2,支线运输综合报表!$E:$E,"Entrega"),0) -> 0.94615385 | F21: =IFERROR(SUMIFS(支线运输综合报表!$AN:$AN,支线运输综合报表!$Q:$Q,$A21,支线运输综合报表!$AP:$AP,F$2,支线运输综合报表!$E:$E,"Entrega")/COUNTIFS(支线运输综合报表!$Q:$Q,$A21,支线运输综合报表!$AP:$AP,F$2,支线运输综合报表!$E:$E,"Entrega"),0) -> 0.95275591 | G21: =IFERROR(SUMIFS(支线运输综合报表!$AN:$AN,支线运输综合报表!$Q:$Q,$A21,支线运输综合报表!$AP:$AP,G$2,支线运输综合报表!$E:$E,"Entrega")/COUNTIFS(支线运输综合报表!$Q:$Q,$A21,支线运输综合报表!$AP:$AP,G$2,支线运输综合报表!$E:$E,"Entrega"),0) -> 0.90909091 | H21: =IFERROR(SUMIFS(支线运输综合报表!$AN:$AN,支线运输综合报表!$Q:$Q,$A21,支线运输综合报表!$AP:$AP,H$2,支线运输综合报表!$E:$E,"Entrega")/COUNTIFS(支线运输综合报表!$Q:$Q,$A21,支线运输综合报表!$AP:$AP,H$2,支线运输综合报表!$E:$E,"Entrega"),0) -> 0 | I21: =IFERROR(SUMIFS(支线运输综合报表!$AN:$AN,支线运输综合报表!$Q:$Q,$A21,支线运输综合报表!$AP:$AP,I$2,支线运输综合报表!$E:$E,"Entrega")/COUNTIFS(支线运输综合报表!$Q:$Q,$A21,支线运输综合报表!$AP:$AP,I$2,支线运输综合报表!$E:$E,"Entrega"),0) -> 0 | J21: =IFERROR(SUMIFS(支线运输综合报表!$AN:$AN,支线运输综合报表!$Q:$Q,$A21,支线运输综合报表!$AP:$AP,J$2,支线运输综合报表!$E:$E,"Entrega")/COUNTIFS(支线运输综合报表!$Q:$Q,$A21,支线运输综合报表!$AP:$AP,J$2,支线运输综合报表!$E:$E,"Entrega"),0) -> 0 | K21: =IFERROR(SUMIFS(支线运输综合报表!$AN:$AN,支线运输综合报表!$Q:$Q,$A21,支线运输综合报表!$AP:$AP,K$2,支线运输综合报表!$E:$E,"Entrega")/COUNTIFS(支线运输综合报表!$Q:$Q,$A21,支线运输综合报表!$AP:$AP,K$2,支线运输综合报表!$E:$E,"Entrega"),0) -> 0 | ... AH21: =IFERROR(SUMIFS(支线运输综合报表!$AN:$AN,支线运输综合报表!$Q:$Q,$A21,支线运输综合报表!$AP:$AP,AH$2,支线运输综合报表!$E:$E,"Entrega")/COUNTIFS(支线运输综合报表!$Q:$Q,$A21,支线运输综合报表!$AP:$AP,AH$2,支线运输综合报表!$E:$E,"Entrega"),0) -> 0
A22: MG | B22: =G22-F22 -> 0.009382716 | C22: =IFERROR(SUMIFS(支线运输综合报表!$AN:$AN,支线运输综合报表!$Q:$Q,$A22,支线运输综合报表!$E:$E,"Entrega")/COUNTIFS(支线运输综合报表!$Q:$Q,$A22,支线运输综合报表!$E:$E,"Entrega"),0) -> 0.97222222 | D22: =IFERROR(SUMIFS(支线运输综合报表!$AN:$AN,支线运输综合报表!$Q:$Q,$A22,支线运输综合报表!$AP:$AP,D$2,支线运输综合报表!$E:$E,"Entrega")/COUNTIFS(支线运输综合报表!$Q:$Q,$A22,支线运输综合报表!$AP:$AP,D$2,支线运输综合报表!$E:$E,"Entrega"),0) -> 0.97647059 | E22: =IFERROR(SUMIFS(支线运输综合报表!$AN:$AN,支线运输综合报表!$Q:$Q,$A22,支线运输综合报表!$AP:$AP,E$2,支线运输综合报表!$E:$E,"Entrega")/COUNTIFS(支线运输综合报表!$Q:$Q,$A22,支线运输综合报表!$AP:$AP,E$2,支线运输综合报表!$E:$E,"Entrega"),0) -> 1 | F22: =IFERROR(SUMIFS(支线运输综合报表!$AN:$AN,支线运输综合报表!$Q:$Q,$A22,支线运输综合报表!$AP:$AP,F$2,支线运输综合报表!$E:$E,"Entrega")/COUNTIFS(支线运输综合报表!$Q:$Q,$A22,支线运输综合报表!$AP:$AP,F$2,支线运输综合报表!$E:$E,"Entrega"),0) -> 0.95061728 | G22: =IFERROR(SUMIFS(支线运输综合报表!$AN:$AN,支线运输综合报表!$Q:$Q,$A22,支线运输综合报表!$AP:$AP,G$2,支线运输综合报表!$E:$E,"Entrega")/COUNTIFS(支线运输综合报表!$Q:$Q,$A22,支线运输综合报表!$AP:$AP,G$2,支线运输综合报表!$E:$E,"Entrega"),0) -> 0.96 | H22: =IFERROR(SUMIFS(支线运输综合报表!$AN:$AN,支线运输综合报表!$Q:$Q,$A22,支线运输综合报表!$AP:$AP,H$2,支线运输综合报表!$E:$E,"Entrega")/COUNTIFS(支线运输综合报表!$Q:$Q,$A22,支线运输综合报表!$AP:$AP,H$2,支线运输综合报表!$E:$E,"Entrega"),0) -> 0 | I22: =IFERROR(SUMIFS(支线运输综合报表!$AN:$AN,支线运输综合报表!$Q:$Q,$A22,支线运输综合报表!$AP:$AP,I$2,支线运输综合报表!$E:$E,"Entrega")/COUNTIFS(支线运输综合报表!$Q:$Q,$A22,支线运输综合报表!$AP:$AP,I$2,支线运输综合报表!$E:$E,"Entrega"),0) -> 0 | J22: =IFERROR(SUMIFS(支线运输综合报表!$AN:$AN,支线运输综合报表!$Q:$Q,$A22,支线运输综合报表!$AP:$AP,J$2,支线运输综合报表!$E:$E,"Entrega")/COUNTIFS(支线运输综合报表!$Q:$Q,$A22,支线运输综合报表!$AP:$AP,J$2,支线运输综合报表!$E:$E,"Entrega"),0) -> 0 | K22: =IFERROR(SUMIFS(支线运输综合报表!$AN:$AN,支线运输综合报表!$Q:$Q,$A22,支线运输综合报表!$AP:$AP,K$2,支线运输综合报表!$E:$E,"Entrega")/COUNTIFS(支线运输综合报表!$Q:$Q,$A22,支线运输综合报表!$AP:$AP,K$2,支线运输综合报表!$E:$E,"Entrega"),0) -> 0 | ... AH22: =IFERROR(SUMIFS(支线运输综合报表!$AN:$AN,支线运输综合报表!$Q:$Q,$A22,支线运输综合报表!$AP:$AP,AH$2,支线运输综合报表!$E:$E,"Entrega")/COUNTIFS(支线运输综合报表!$Q:$Q,$A22,支线运输综合报表!$AP:$AP,AH$2,支线运输综合报表!$E:$E,"Entrega"),0) -> 0
A23: BA | B23: =G23-F23 -> 0.021276596 | C23: =IFERROR(SUMIFS(支线运输综合报表!$AN:$AN,支线运输综合报表!$Q:$Q,$A23,支线运输综合报表!$E:$E,"Entrega")/COUNTIFS(支线运输综合报表!$Q:$Q,$A23,支线运输综合报表!$E:$E,"Entrega"),0) -> 0.99285714 | D23: =IFERROR(SUMIFS(支线运输综合报表!$AN:$AN,支线运输综合报表!$Q:$Q,$A23,支线运输综合报表!$AP:$AP,D$2,支线运输综合报表!$E:$E,"Entrega")/COUNTIFS(支线运输综合报表!$Q:$Q,$A23,支线运输综合报表!$AP:$AP,D$2,支线运输综合报表!$E:$E,"Entrega"),0) -> 1 | E23: =IFERROR(SUMIFS(支线运输综合报表!$AN:$AN,支线运输综合报表!$Q:$Q,$A23,支线运输综合报表!$AP:$AP,E$2,支线运输综合报表!$E:$E,"Entrega")/COUNTIFS(支线运输综合报表!$Q:$Q,$A23,支线运输综合报表!$AP:$AP,E$2,支线运输综合报表!$E:$E,"Entrega"),0) -> 1 | F23: =IFERROR(SUMIFS(支线运输综合报表!$AN:$AN,支线运输综合报表!$Q:$Q,$A23,支线运输综合报表!$AP:$AP,F$2,支线运输综合报表!$E:$E,"Entrega")/COUNTIFS(支线运输综合报表!$Q:$Q,$A23,支线运输综合报表!$AP:$AP,F$2,支线运输综合报表!$E:$E,"Entrega"),0) -> 0.9787234 | G23: =IFERROR(SUMIFS(支线运输综合报表!$AN:$AN,支线运输综合报表!$Q:$Q,$A23,支线运输综合报表!$AP:$AP,G$2,支线运输综合报表!$E:$E,"Entrega")/COUNTIFS(支线运输综合报表!$Q:$Q,$A23,支线运输综合报表!$AP:$AP,G$2,支线运输综合报表!$E:$E,"Entrega"),0) -> 1 | H23: =IFERROR(SUMIFS(支线运输综合报表!$AN:$AN,支线运输综合报表!$Q:$Q,$A23,支线运输综合报表!$AP:$AP,H$2,支线运输综合报表!$E:$E,"Entrega")/COUNTIFS(支线运输综合报表!$Q:$Q,$A23,支线运输综合报表!$AP:$AP,H$2,支线运输综合报表!$E:$E,"Entrega"),0) -> 0 | I23: =IFERROR(SUMIFS(支线运输综合报表!$AN:$AN,支线运输综合报表!$Q:$Q,$A23,支线运输综合报表!$AP:$AP,I$2,支线运输综合报表!$E:$E,"Entrega")/COUNTIFS(支线运输综合报表!$Q:$Q,$A23,支线运输综合报表!$AP:$AP,I$2,支线运输综合报表!$E:$E,"Entrega"),0) -> 0 | J23: =IFERROR(SUMIFS(支线运输综合报表!$AN:$AN,支线运输综合报表!$Q:$Q,$A23,支线运输综合报表!$AP:$AP,J$2,支线运输综合报表!$E:$E,"Entrega")/COUNTIFS(支线运输综合报表!$Q:$Q,$A23,支线运输综合报表!$AP:$AP,J$2,支线运输综合报表!$E:$E,"Entrega"),0) -> 0 | K23: =IFERROR(SUMIFS(支线运输综合报表!$AN:$AN,支线运输综合报表!$Q:$Q,$A23,支线运输综合报表!$AP:$AP,K$2,支线运输综合报表!$E:$E,"Entrega")/COUNTIFS(支线运输综合报表!$Q:$Q,$A23,支线运输综合报表!$AP:$AP,K$2,支线运输综合报表!$E:$E,"Entrega"),0) -> 0 | ... AH23: =IFERROR(SUMIFS(支线运输综合报表!$AN:$AN,支线运输综合报表!$Q:$Q,$A23,支线运输综合报表!$AP:$AP,AH$2,支线运输综合报表!$E:$E,"Entrega")/COUNTIFS(支线运输综合报表!$Q:$Q,$A23,支线运输综合报表!$AP:$AP,AH$2,支线运输综合报表!$E:$E,"Entrega"),0) -> 0

Sheet 解车趋势Tendencia deslacre
A1: 集货解车率趋势Tendência da DESLACRE-COLETA
A2: 到车区域Região de Chegada | B2: 环比Variação± | C2: 10月累计Acumulado de Outubro | D2: 46296 | E2: =D2+1 -> 46297 | F2: =E2+1 -> 46298 | G2: =F2+1 -> 46299 | H2: =G2+1 -> 46300 | I2: =H2+1 -> 46301 | J2: =I2+1 -> 46302 | K2: =J2+1 -> 46303 | L2: =K2+1 -> 46304 | ... AH2: =AG2+1 -> 46326 | AI2: 近七天趋势
A3: 合计 | B3: =G3-F3 -> -0.021141649 | C3: =IFERROR(SUMIFS(支线运输综合报表!$AO:$AO,支线运输综合报表!$E:$E,"Coleta")/COUNTIFS(支线运输综合报表!$E:$E,"Coleta"),0) -> 0.92964072 | D3: =IFERROR(SUMIFS(支线运输综合报表!$AO:$AO,支线运输综合报表!$AP:$AP,D2,支线运输综合报表!$E:$E,"Coleta")/COUNTIFS(支线运输综合报表!$AP:$AP,D2,支线运输综合报表!$E:$E,"Coleta"),0) -> 0.92173913 | E3: =IFERROR(SUMIFS(支线运输综合报表!$AO:$AO,支线运输综合报表!$AP:$AP,E2,支线运输综合报表!$E:$E,"Coleta")/COUNTIFS(支线运输综合报表!$AP:$AP,E2,支线运输综合报表!$E:$E,"Coleta"),0) -> 0.93991416 | F3: =IFERROR(SUMIFS(支线运输综合报表!$AO:$AO,支线运输综合报表!$AP:$AP,F2,支线运输综合报表!$E:$E,"Coleta")/COUNTIFS(支线运输综合报表!$AP:$AP,F2,支线运输综合报表!$E:$E,"Coleta"),0) -> 0.93023256 | G3: =IFERROR(SUMIFS(支线运输综合报表!$AO:$AO,支线运输综合报表!$AP:$AP,G2,支线运输综合报表!$E:$E,"Coleta")/COUNTIFS(支线运输综合报表!$AP:$AP,G2,支线运输综合报表!$E:$E,"Coleta"),0) -> 0.90909091 | H3: =IFERROR(SUMIFS(支线运输综合报表!$AO:$AO,支线运输综合报表!$AP:$AP,H2,支线运输综合报表!$E:$E,"Coleta")/COUNTIFS(支线运输综合报表!$AP:$AP,H2,支线运输综合报表!$E:$E,"Coleta"),0) -> 0 | I3: =IFERROR(SUMIFS(支线运输综合报表!$AO:$AO,支线运输综合报表!$AP:$AP,I2,支线运输综合报表!$E:$E,"Coleta")/COUNTIFS(支线运输综合报表!$AP:$AP,I2,支线运输综合报表!$E:$E,"Coleta"),0) -> 0 | J3: =IFERROR(SUMIFS(支线运输综合报表!$AO:$AO,支线运输综合报表!$AP:$AP,J2,支线运输综合报表!$E:$E,"Coleta")/COUNTIFS(支线运输综合报表!$AP:$AP,J2,支线运输综合报表!$E:$E,"Coleta"),0) -> 0 | K3: =IFERROR(SUMIFS(支线运输综合报表!$AO:$AO,支线运输综合报表!$AP:$AP,K2,支线运输综合报表!$E:$E,"Coleta")/COUNTIFS(支线运输综合报表!$AP:$AP,K2,支线运输综合报表!$E:$E,"Coleta"),0) -> 0 | ... AH3: =IFERROR(SUMIFS(支线运输综合报表!$AO:$AO,支线运输综合报表!$AP:$AP,AH2,支线运输综合报表!$E:$E,"Coleta")/COUNTIFS(支线运输综合报表!$AP:$AP,AH2,支线运输综合报表!$E:$E,"Coleta"),0) -> 0
A4: SPN | B4: =G4-F4 -> -0.11111111 | C4: =IFERROR(SUMIFS(支线运输综合报表!$AO:$AO,支线运输综合报表!$AD:$AD,$A4,支线运输综合报表!$E:$E,"Coleta")/COUNTIFS(支线运输综合报表!$AD:$AD,$A4,支线运输综合报表!$E:$E,"Coleta"),0) -> 0.98130841 | D4: =IFERROR(SUMIFS(支线运输综合报表!$AO:$AO,支线运输综合报表!$AD:$AD,$A4,支线运输综合报表!$AP:$AP,D$2,支线运输综合报表!$E:$E,"Coleta")/COUNTIFS(支线运输综合报表!$AD:$AD,$A4,支线运输综合报表!$AP:$AP,D$2,支线运输综合报表!$E:$E,"Coleta"),0) -> 0.96875 | E4: =IFERROR(SUMIFS(支线运输综合报表!$AO:$AO,支线运输综合报表!$AD:$AD,$A4,支线运输综合报表!$AP:$AP,E$2,支线运输综合报表!$E:$E,"Coleta")/COUNTIFS(支线运输综合报表!$AD:$AD,$A4,支线运输综合报表!$AP:$AP,E$2,支线运输综合报表!$E:$E,"Coleta"),0) -> 1 | F4: =IFERROR(SUMIFS(支线运输综合报表!$AO:$AO,支线运输综合报表!$AD:$AD,$A4,支线运输综合报表!$AP:$AP,F$2,支线运输综合报表!$E:$E,"Coleta")/COUNTIFS(支线运输综合报表!$AD:$AD,$A4,支线运输综合报表!$AP:$AP,F$2,支线运输综合报表!$E:$E,"Coleta"),0) -> 1 | G4: =IFERROR(SUMIFS(支线运输综合报表!$AO:$AO,支线运输综合报表!$AD:$AD,$A4,支线运输综合报表!$AP:$AP,G$2,支线运输综合报表!$E:$E,"Coleta")/COUNTIFS(支线运输综合报表!$AD:$AD,$A4,支线运输综合报表!$AP:$AP,G$2,支线运输综合报表!$E:$E,"Coleta"),0) -> 0.88888889 | H4: =IFERROR(SUMIFS(支线运输综合报表!$AO:$AO,支线运输综合报表!$AD:$AD,$A4,支线运输综合报表!$AP:$AP,H$2,支线运输综合报表!$E:$E,"Coleta")/COUNTIFS(支线运输综合报表!$AD:$AD,$A4,支线运输综合报表!$AP:$AP,H$2,支线运输综合报表!$E:$E,"Coleta"),0) -> 0 | I4: =IFERROR(SUMIFS(支线运输综合报表!$AO:$AO,支线运输综合报表!$AD:$AD,$A4,支线运输综合报表!$AP:$AP,I$2,支线运输综合报表!$E:$E,"Coleta")/COUNTIFS(支线运输综合报表!$AD:$AD,$A4,支线运输综合报表!$AP:$AP,I$2,支线运输综合报表!$E:$E,"Coleta"),0) -> 0 | J4: =IFERROR(SUMIFS(支线运输综合报表!$AO:$AO,支线运输综合报表!$AD:$AD,$A4,支线运输综合报表!$AP:$AP,J$2,支线运输综合报表!$E:$E,"Coleta")/COUNTIFS(支线运输综合报表!$AD:$AD,$A4,支线运输综合报表!$AP:$AP,J$2,支线运输综合报表!$E:$E,"Coleta"),0) -> 0 | K4: =IFERROR(SUMIFS(支线运输综合报表!$AO:$AO,支线运输综合报表!$AD:$AD,$A4,支线运输综合报表!$AP:$AP,K$2,支线运输综合报表!$E:$E,"Coleta")/COUNTIFS(支线运输综合报表!$AD:$AD,$A4,支线运输综合报表!$AP:$AP,K$2,支线运输综合报表!$E:$E,"Coleta"),0) -> 0 | ... AH4: =IFERROR(SUMIFS(支线运输综合报表!$AO:$AO,支线运输综合报表!$AD:$AD,$A4,支线运输综合报表!$AP:$AP,AH$2,支线运输综合报表!$E:$E,"Coleta")/COUNTIFS(支线运输综合报表!$AD:$AD,$A4,支线运输综合报表!$AP:$AP,AH$2,支线运输综合报表!$E:$E,"Coleta"),0) -> 0
A5: SPS | B5: =G5-F5 -> 0.011494253 | C5: =IFERROR(SUMIFS(支线运输综合报表!$AO:$AO,支线运输综合报表!$AD:$AD,$A5,支线运输综合报表!$E:$E,"Coleta")/COUNTIFS(支线运输综合报表!$AD:$AD,$A5,支线运输综合报表!$E:$E,"Coleta"),0) -> 0.96100279 | D5: =IFERROR(SUMIFS(支线运输综合报表!$AO:$AO,支线运输综合报表!$AD:$AD,$A5,支线运输综合报表!$AP:$AP,D$2,支线运输综合报表!$E:$E,"Coleta")/COUNTIFS(支线运输综合报表!$AD:$AD,$A5,支线运输综合报表!$AP:$AP,D$2,支线运输综合报表!$E:$E,"Coleta"),0) -> 0.95384615 | E5: =IFERROR(SUMIFS(支线运输综合报表!$AO:$AO,支线运输综合报表!$AD:$AD,$A5,支线运输综合报表!$AP:$AP,E$2,支线运输综合报表!$E:$E,"Coleta")/COUNTIFS(支线运输综合报表!$AD:$AD,$A5,支线运输综合报表!$AP:$AP,E$2,支线运输综合报表!$E:$E,"Coleta"),0) -> 0.94573643 | F5: =IFERROR(SUMIFS(支线运输综合报表!$AO:$AO,支线运输综合报表!$AD:$AD,$A5,支线运输综合报表!$AP:$AP,F$2,支线运输综合报表!$E:$E,"Coleta")/COUNTIFS(支线运输综合报表!$AD:$AD,$A5,支线运输综合报表!$AP:$AP,F$2,支线运输综合报表!$E:$E,"Coleta"),0) -> 0.98850575 | G5: =IFERROR(SUMIFS(支线运输综合报表!$AO:$AO,支线运输综合报表!$AD:$AD,$A5,支线运输综合报表!$AP:$AP,G$2,支线运输综合报表!$E:$E,"Coleta")/COUNTIFS(支线运输综合报表!$AD:$AD,$A5,支线运输综合报表!$AP:$AP,G$2,支线运输综合报表!$E:$E,"Coleta"),0) -> 1 | H5: =IFERROR(SUMIFS(支线运输综合报表!$AO:$AO,支线运输综合报表!$AD:$AD,$A5,支线运输综合报表!$AP:$AP,H$2,支线运输综合报表!$E:$E,"Coleta")/COUNTIFS(支线运输综合报表!$AD:$AD,$A5,支线运输综合报表!$AP:$AP,H$2,支线运输综合报表!$E:$E,"Coleta"),0) -> 0 | I5: =IFERROR(SUMIFS(支线运输综合报表!$AO:$AO,支线运输综合报表!$AD:$AD,$A5,支线运输综合报表!$AP:$AP,I$2,支线运输综合报表!$E:$E,"Coleta")/COUNTIFS(支线运输综合报表!$AD:$AD,$A5,支线运输综合报表!$AP:$AP,I$2,支线运输综合报表!$E:$E,"Coleta"),0) -> 0 | J5: =IFERROR(SUMIFS(支线运输综合报表!$AO:$AO,支线运输综合报表!$AD:$AD,$A5,支线运输综合报表!$AP:$AP,J$2,支线运输综合报表!$E:$E,"Coleta")/COUNTIFS(支线运输综合报表!$AD:$AD,$A5,支线运输综合报表!$AP:$AP,J$2,支线运输综合报表!$E:$E,"Coleta"),0) -> 0 | K5: =IFERROR(SUMIFS(支线运输综合报表!$AO:$AO,支线运输综合报表!$AD:$AD,$A5,支线运输综合报表!$AP:$AP,K$2,支线运输综合报表!$E:$E,"Coleta")/COUNTIFS(支线运输综合报表!$AD:$AD,$A5,支线运输综合报表!$AP:$AP,K$2,支线运输综合报表!$E:$E,"Coleta"),0) -> 0 | ... AH5: =IFERROR(SUMIFS(支线运输综合报表!$AO:$AO,支线运输综合报表!$AD:$AD,$A5,支线运输综合报表!$AP:$AP,AH$2,支线运输综合报表!$E:$E,"Coleta")/COUNTIFS(支线运输综合报表!$AD:$AD,$A5,支线运输综合报表!$AP:$AP,AH$2,支线运输综合报表!$E:$E,"Coleta"),0) -> 0
A6: GP | B6: =G6-F6 -> 0.66666667 | C6: =IFERROR(SUMIFS(支线运输综合报表!$AO:$AO,支线运输综合报表!$AD:$AD,$A6,支线运输综合报表!$E:$E,"Coleta")/COUNTIFS(支线运输综合报表!$AD:$AD,$A6,支线运输综合报表!$E:$E,"Coleta"),0) -> 0.71428571 | D6: =IFERROR(SUMIFS(支线运输综合报表!$AO:$AO,支线运输综合报表!$AD:$AD,$A6,支线运输综合报表!$AP:$AP,D$2,支线运输综合报表!$E:$E,"Coleta")/COUNTIFS(支线运输综合报表!$AD:$AD,$A6,支线运输综合报表!$AP:$AP,D$2,支线运输综合报表!$E:$E,"Coleta"),0) -> 0.85714286 | E6: =IFERROR(SUMIFS(支线运输综合报表!$AO:$AO,支线运输综合报表!$AD:$AD,$A6,支线运输综合报表!$AP:$AP,E$2,支线运输综合报表!$E:$E,"Coleta")/COUNTIFS(支线运输综合报表!$AD:$AD,$A6,支线运输综合报表!$AP:$AP,E$2,支线运输综合报表!$E:$E,"Coleta"),0) -> 0.85714286 | F6: =IFERROR(SUMIFS(支线运输综合报表!$AO:$AO,支线运输综合报表!$AD:$AD,$A6,支线运输综合报表!$AP:$AP,F$2,支线运输综合报表!$E:$E,"Coleta")/COUNTIFS(支线运输综合报表!$AD:$AD,$A6,支线运输综合报表!$AP:$AP,F$2,支线运输综合报表!$E:$E,"Coleta"),0) -> 0.33333333 | G6: =IFERROR(SUMIFS(支线运输综合报表!$AO:$AO,支线运输综合报表!$AD:$AD,$A6,支线运输综合报表!$AP:$AP,G$2,支线运输综合报表!$E:$E,"Coleta")/COUNTIFS(支线运输综合报表!$AD:$AD,$A6,支线运输综合报表!$AP:$AP,G$2,支线运输综合报表!$E:$E,"Coleta"),0) -> 1 | H6: =IFERROR(SUMIFS(支线运输综合报表!$AO:$AO,支线运输综合报表!$AD:$AD,$A6,支线运输综合报表!$AP:$AP,H$2,支线运输综合报表!$E:$E,"Coleta")/COUNTIFS(支线运输综合报表!$AD:$AD,$A6,支线运输综合报表!$AP:$AP,H$2,支线运输综合报表!$E:$E,"Coleta"),0) -> 0 | I6: =IFERROR(SUMIFS(支线运输综合报表!$AO:$AO,支线运输综合报表!$AD:$AD,$A6,支线运输综合报表!$AP:$AP,I$2,支线运输综合报表!$E:$E,"Coleta")/COUNTIFS(支线运输综合报表!$AD:$AD,$A6,支线运输综合报表!$AP:$AP,I$2,支线运输综合报表!$E:$E,"Coleta"),0) -> 0 | J6: =IFERROR(SUMIFS(支线运输综合报表!$AO:$AO,支线运输综合报表!$AD:$AD,$A6,支线运输综合报表!$AP:$AP,J$2,支线运输综合报表!$E:$E,"Coleta")/COUNTIFS(支线运输综合报表!$AD:$AD,$A6,支线运输综合报表!$AP:$AP,J$2,支线运输综合报表!$E:$E,"Coleta"),0) -> 0 | K6: =IFERROR(SUMIFS(支线运输综合报表!$AO:$AO,支线运输综合报表!$AD:$AD,$A6,支线运输综合报表!$AP:$AP,K$2,支线运输综合报表!$E:$E,"Coleta")/COUNTIFS(支线运输综合报表!$AD:$AD,$A6,支线运输综合报表!$AP:$AP,K$2,支线运输综合报表!$E:$E,"Coleta"),0) -> 0 | ... AH6: =IFERROR(SUMIFS(支线运输综合报表!$AO:$AO,支线运输综合报表!$AD:$AD,$A6,支线运输综合报表!$AP:$AP,AH$2,支线运输综合报表!$E:$E,"Coleta")/COUNTIFS(支线运输综合报表!$AD:$AD,$A6,支线运输综合报表!$AP:$AP,AH$2,支线运输综合报表!$E:$E,"Coleta"),0) -> 0
A7: SPE | B7: =G7-F7 -> -0.33333333 | C7: =IFERROR(SUMIFS(支线运输综合报表!$AO:$AO,支线运输综合报表!$AD:$AD,$A7,支线运输综合报表!$E:$E,"Coleta")/COUNTIFS(支线运输综合报表!$AD:$AD,$A7,支线运输综合报表!$E:$E,"Coleta"),0) -> 0.9625 | D7: =IFERROR(SUMIFS(支线运输综合报表!$AO:$AO,支线运输综合报表!$AD:$AD,$A7,支线运输综合报表!$AP:$AP,D$2,支线运输综合报表!$E:$E,"Coleta")/COUNTIFS(支线运输综合报表!$AD:$AD,$A7,支线运输综合报表!$AP:$AP,D$2,支线运输综合报表!$E:$E,"Coleta"),0) -> 0.96428571 | E7: =IFERROR(SUMIFS(支线运输综合报表!$AO:$AO,支线运输综合报表!$AD:$AD,$A7,支线运输综合报表!$AP:$AP,E$2,支线运输综合报表!$E:$E,"Coleta")/COUNTIFS(支线运输综合报表!$AD:$AD,$A7,支线运输综合报表!$AP:$AP,E$2,支线运输综合报表!$E:$E,"Coleta"),0) -> 0.96875 | F7: =IFERROR(SUMIFS(支线运输综合报表!$AO:$AO,支线运输综合报表!$AD:$AD,$A7,支线运输综合报表!$AP:$AP,F$2,支线运输综合报表!$E:$E,"Coleta")/COUNTIFS(支线运输综合报表!$AD:$AD,$A7,支线运输综合报表!$AP:$AP,F$2,支线运输综合报表!$E:$E,"Coleta"),0) -> 1 | G7: =IFERROR(SUMIFS(支线运输综合报表!$AO:$AO,支线运输综合报表!$AD:$AD,$A7,支线运输综合报表!$AP:$AP,G$2,支线运输综合报表!$E:$E,"Coleta")/COUNTIFS(支线运输综合报表!$AD:$AD,$A7,支线运输综合报表!$AP:$AP,G$2,支线运输综合报表!$E:$E,"Coleta"),0) -> 0.66666667 | H7: =IFERROR(SUMIFS(支线运输综合报表!$AO:$AO,支线运输综合报表!$AD:$AD,$A7,支线运输综合报表!$AP:$AP,H$2,支线运输综合报表!$E:$E,"Coleta")/COUNTIFS(支线运输综合报表!$AD:$AD,$A7,支线运输综合报表!$AP:$AP,H$2,支线运输综合报表!$E:$E,"Coleta"),0) -> 0 | I7: =IFERROR(SUMIFS(支线运输综合报表!$AO:$AO,支线运输综合报表!$AD:$AD,$A7,支线运输综合报表!$AP:$AP,I$2,支线运输综合报表!$E:$E,"Coleta")/COUNTIFS(支线运输综合报表!$AD:$AD,$A7,支线运输综合报表!$AP:$AP,I$2,支线运输综合报表!$E:$E,"Coleta"),0) -> 0 | J7: =IFERROR(SUMIFS(支线运输综合报表!$AO:$AO,支线运输综合报表!$AD:$AD,$A7,支线运输综合报表!$AP:$AP,J$2,支线运输综合报表!$E:$E,"Coleta")/COUNTIFS(支线运输综合报表!$AD:$AD,$A7,支线运输综合报表!$AP:$AP,J$2,支线运输综合报表!$E:$E,"Coleta"),0) -> 0 | K7: =IFERROR(SUMIFS(支线运输综合报表!$AO:$AO,支线运输综合报表!$AD:$AD,$A7,支线运输综合报表!$AP:$AP,K$2,支线运输综合报表!$E:$E,"Coleta")/COUNTIFS(支线运输综合报表!$AD:$AD,$A7,支线运输综合报表!$AP:$AP,K$2,支线运输综合报表!$E:$E,"Coleta"),0) -> 0 | ... AH7: =IFERROR(SUMIFS(支线运输综合报表!$AO:$AO,支线运输综合报表!$AD:$AD,$A7,支线运输综合报表!$AP:$AP,AH$2,支线运输综合报表!$E:$E,"Coleta")/COUNTIFS(支线运输综合报表!$AD:$AD,$A7,支线运输综合报表!$AP:$AP,AH$2,支线运输综合报表!$E:$E,"Coleta"),0) -> 0
A8: RJ | B8: =G8-F8 -> 0 | C8: =IFERROR(SUMIFS(支线运输综合报表!$AO:$AO,支线运输综合报表!$AD:$AD,$A8,支线运输综合报表!$E:$E,"Coleta")/COUNTIFS(支线运输综合报表!$AD:$AD,$A8,支线运输综合报表!$E:$E,"Coleta"),0) -> 1 | D8: =IFERROR(SUMIFS(支线运输综合报表!$AO:$AO,支线运输综合报表!$AD:$AD,$A8,支线运输综合报表!$AP:$AP,D$2,支线运输综合报表!$E:$E,"Coleta")/COUNTIFS(支线运输综合报表!$AD:$AD,$A8,支线运输综合报表!$AP:$AP,D$2,支线运输综合报表!$E:$E,"Coleta"),0) -> 1 | E8: =IFERROR(SUMIFS(支线运输综合报表!$AO:$AO,支线运输综合报表!$AD:$AD,$A8,支线运输综合报表!$AP:$AP,E$2,支线运输综合报表!$E:$E,"Coleta")/COUNTIFS(支线运输综合报表!$AD:$AD,$A8,支线运输综合报表!$AP:$AP,E$2,支线运输综合报表!$E:$E,"Coleta"),0) -> 1 | F8: =IFERROR(SUMIFS(支线运输综合报表!$AO:$AO,支线运输综合报表!$AD:$AD,$A8,支线运输综合报表!$AP:$AP,F$2,支线运输综合报表!$E:$E,"Coleta")/COUNTIFS(支线运输综合报表!$AD:$AD,$A8,支线运输综合报表!$AP:$AP,F$2,支线运输综合报表!$E:$E,"Coleta"),0) -> 1 | G8: =IFERROR(SUMIFS(支线运输综合报表!$AO:$AO,支线运输综合报表!$AD:$AD,$A8,支线运输综合报表!$AP:$AP,G$2,支线运输综合报表!$E:$E,"Coleta")/COUNTIFS(支线运输综合报表!$AD:$AD,$A8,支线运输综合报表!$AP:$AP,G$2,支线运输综合报表!$E:$E,"Coleta"),0) -> 1 | H8: =IFERROR(SUMIFS(支线运输综合报表!$AO:$AO,支线运输综合报表!$AD:$AD,$A8,支线运输综合报表!$AP:$AP,H$2,支线运输综合报表!$E:$E,"Coleta")/COUNTIFS(支线运输综合报表!$AD:$AD,$A8,支线运输综合报表!$AP:$AP,H$2,支线运输综合报表!$E:$E,"Coleta"),0) -> 0 | I8: =IFERROR(SUMIFS(支线运输综合报表!$AO:$AO,支线运输综合报表!$AD:$AD,$A8,支线运输综合报表!$AP:$AP,I$2,支线运输综合报表!$E:$E,"Coleta")/COUNTIFS(支线运输综合报表!$AD:$AD,$A8,支线运输综合报表!$AP:$AP,I$2,支线运输综合报表!$E:$E,"Coleta"),0) -> 0 | J8: =IFERROR(SUMIFS(支线运输综合报表!$AO:$AO,支线运输综合报表!$AD:$AD,$A8,支线运输综合报表!$AP:$AP,J$2,支线运输综合报表!$E:$E,"Coleta")/COUNTIFS(支线运输综合报表!$AD:$AD,$A8,支线运输综合报表!$AP:$AP,J$2,支线运输综合报表!$E:$E,"Coleta"),0) -> 0 | K8: =IFERROR(SUMIFS(支线运输综合报表!$AO:$AO,支线运输综合报表!$AD:$AD,$A8,支线运输综合报表!$AP:$AP,K$2,支线运输综合报表!$E:$E,"Coleta")/COUNTIFS(支线运输综合报表!$AD:$AD,$A8,支线运输综合报表!$AP:$AP,K$2,支线运输综合报表!$E:$E,"Coleta"),0) -> 0 | ... AH8: =IFERROR(SUMIFS(支线运输综合报表!$AO:$AO,支线运输综合报表!$AD:$AD,$A8,支线运输综合报表!$AP:$AP,AH$2,支线运输综合报表!$E:$E,"Coleta")/COUNTIFS(支线运输综合报表!$AD:$AD,$A8,支线运输综合报表!$AP:$AP,AH$2,支线运输综合报表!$E:$E,"Coleta"),0) -> 0
A9: PR | B9: =G9-F9 -> 0 | C9: =IFERROR(SUMIFS(支线运输综合报表!$AO:$AO,支线运输综合报表!$AD:$AD,$A9,支线运输综合报表!$E:$E,"Coleta")/COUNTIFS(支线运输综合报表!$AD:$AD,$A9,支线运输综合报表!$E:$E,"Coleta"),0) -> 0.57142857 | D9: =IFERROR(SUMIFS(支线运输综合报表!$AO:$AO,支线运输综合报表!$AD:$AD,$A9,支线运输综合报表!$AP:$AP,D$2,支线运输综合报表!$E:$E,"Coleta")/COUNTIFS(支线运输综合报表!$AD:$AD,$A9,支线运输综合报表!$AP:$AP,D$2,支线运输综合报表!$E:$E,"Coleta"),0) -> 0.55555556 | E9: =IFERROR(SUMIFS(支线运输综合报表!$AO:$AO,支线运输综合报表!$AD:$AD,$A9,支线运输综合报表!$AP:$AP,E$2,支线运输综合报表!$E:$E,"Coleta")/COUNTIFS(支线运输综合报表!$AD:$AD,$A9,支线运输综合报表!$AP:$AP,E$2,支线运输综合报表!$E:$E,"Coleta"),0) -> 0.66666667 | F9: =IFERROR(SUMIFS(支线运输综合报表!$AO:$AO,支线运输综合报表!$AD:$AD,$A9,支线运输综合报表!$AP:$AP,F$2,支线运输综合报表!$E:$E,"Coleta")/COUNTIFS(支线运输综合报表!$AD:$AD,$A9,支线运输综合报表!$AP:$AP,F$2,支线运输综合报表!$E:$E,"Coleta"),0) -> 0.5 | G9: =IFERROR(SUMIFS(支线运输综合报表!$AO:$AO,支线运输综合报表!$AD:$AD,$A9,支线运输综合报表!$AP:$AP,G$2,支线运输综合报表!$E:$E,"Coleta")/COUNTIFS(支线运输综合报表!$AD:$AD,$A9,支线运输综合报表!$AP:$AP,G$2,支线运输综合报表!$E:$E,"Coleta"),0) -> 0.5 | H9: =IFERROR(SUMIFS(支线运输综合报表!$AO:$AO,支线运输综合报表!$AD:$AD,$A9,支线运输综合报表!$AP:$AP,H$2,支线运输综合报表!$E:$E,"Coleta")/COUNTIFS(支线运输综合报表!$AD:$AD,$A9,支线运输综合报表!$AP:$AP,H$2,支线运输综合报表!$E:$E,"Coleta"),0) -> 0 | I9: =IFERROR(SUMIFS(支线运输综合报表!$AO:$AO,支线运输综合报表!$AD:$AD,$A9,支线运输综合报表!$AP:$AP,I$2,支线运输综合报表!$E:$E,"Coleta")/COUNTIFS(支线运输综合报表!$AD:$AD,$A9,支线运输综合报表!$AP:$AP,I$2,支线运输综合报表!$E:$E,"Coleta"),0) -> 0 | J9: =IFERROR(SUMIFS(支线运输综合报表!$AO:$AO,支线运输综合报表!$AD:$AD,$A9,支线运输综合报表!$AP:$AP,J$2,支线运输综合报表!$E:$E,"Coleta")/COUNTIFS(支线运输综合报表!$AD:$AD,$A9,支线运输综合报表!$AP:$AP,J$2,支线运输综合报表!$E:$E,"Coleta"),0) -> 0 | K9: =IFERROR(SUMIFS(支线运输综合报表!$AO:$AO,支线运输综合报表!$AD:$AD,$A9,支线运输综合报表!$AP:$AP,K$2,支线运输综合报表!$E:$E,"Coleta")/COUNTIFS(支线运输综合报表!$AD:$AD,$A9,支线运输综合报表!$AP:$AP,K$2,支线运输综合报表!$E:$E,"Coleta"),0) -> 0 | ... AH9: =IFERROR(SUMIFS(支线运输综合报表!$AO:$AO,支线运输综合报表!$AD:$AD,$A9,支线运输综合报表!$AP:$AP,AH$2,支线运输综合报表!$E:$E,"Coleta")/COUNTIFS(支线运输综合报表!$AD:$AD,$A9,支线运输综合报表!$AP:$AP,AH$2,支线运输综合报表!$E:$E,"Coleta"),0) -> 0
A10: MG | B10: =G10-F10 -> 0.1 | C10: =IFERROR(SUMIFS(支线运输综合报表!$AO:$AO,支线运输综合报表!$AD:$AD,$A10,支线运输综合报表!$E:$E,"Coleta")/COUNTIFS(支线运输综合报表!$AD:$AD,$A10,支线运输综合报表!$E:$E,"Coleta"),0) -> 0.85714286 | D10: =IFERROR(SUMIFS(支线运输综合报表!$AO:$AO,支线运输综合报表!$AD:$AD,$A10,支线运输综合报表!$AP:$AP,D$2,支线运输综合报表!$E:$E,"Coleta")/COUNTIFS(支线运输综合报表!$AD:$AD,$A10,支线运输综合报表!$AP:$AP,D$2,支线运输综合报表!$E:$E,"Coleta"),0) -> 0.73333333 | E10: =IFERROR(SUMIFS(支线运输综合报表!$AO:$AO,支线运输综合报表!$AD:$AD,$A10,支线运输综合报表!$AP:$AP,E$2,支线运输综合报表!$E:$E,"Coleta")/COUNTIFS(支线运输综合报表!$AD:$AD,$A10,支线运输综合报表!$AP:$AP,E$2,支线运输综合报表!$E:$E,"Coleta"),0) -> 0.93333333 | F10: =IFERROR(SUMIFS(支线运输综合报表!$AO:$AO,支线运输综合报表!$AD:$AD,$A10,支线运输综合报表!$AP:$AP,F$2,支线运输综合报表!$E:$E,"Coleta")/COUNTIFS(支线运输综合报表!$AD:$AD,$A10,支线运输综合报表!$AP:$AP,F$2,支线运输综合报表!$E:$E,"Coleta"),0) -> 0.9 | G10: =IFERROR(SUMIFS(支线运输综合报表!$AO:$AO,支线运输综合报表!$AD:$AD,$A10,支线运输综合报表!$AP:$AP,G$2,支线运输综合报表!$E:$E,"Coleta")/COUNTIFS(支线运输综合报表!$AD:$AD,$A10,支线运输综合报表!$AP:$AP,G$2,支线运输综合报表!$E:$E,"Coleta"),0) -> 1 | H10: =IFERROR(SUMIFS(支线运输综合报表!$AO:$AO,支线运输综合报表!$AD:$AD,$A10,支线运输综合报表!$AP:$AP,H$2,支线运输综合报表!$E:$E,"Coleta")/COUNTIFS(支线运输综合报表!$AD:$AD,$A10,支线运输综合报表!$AP:$AP,H$2,支线运输综合报表!$E:$E,"Coleta"),0) -> 0 | I10: =IFERROR(SUMIFS(支线运输综合报表!$AO:$AO,支线运输综合报表!$AD:$AD,$A10,支线运输综合报表!$AP:$AP,I$2,支线运输综合报表!$E:$E,"Coleta")/COUNTIFS(支线运输综合报表!$AD:$AD,$A10,支线运输综合报表!$AP:$AP,I$2,支线运输综合报表!$E:$E,"Coleta"),0) -> 0 | J10: =IFERROR(SUMIFS(支线运输综合报表!$AO:$AO,支线运输综合报表!$AD:$AD,$A10,支线运输综合报表!$AP:$AP,J$2,支线运输综合报表!$E:$E,"Coleta")/COUNTIFS(支线运输综合报表!$AD:$AD,$A10,支线运输综合报表!$AP:$AP,J$2,支线运输综合报表!$E:$E,"Coleta"),0) -> 0 | K10: =IFERROR(SUMIFS(支线运输综合报表!$AO:$AO,支线运输综合报表!$AD:$AD,$A10,支线运输综合报表!$AP:$AP,K$2,支线运输综合报表!$E:$E,"Coleta")/COUNTIFS(支线运输综合报表!$AD:$AD,$A10,支线运输综合报表!$AP:$AP,K$2,支线运输综合报表!$E:$E,"Coleta"),0) -> 0 | ... AH10: =IFERROR(SUMIFS(支线运输综合报表!$AO:$AO,支线运输综合报表!$AD:$AD,$A10,支线运输综合报表!$AP:$AP,AH$2,支线运输综合报表!$E:$E,"Coleta")/COUNTIFS(支线运输综合报表!$AD:$AD,$A10,支线运输综合报表!$AP:$AP,AH$2,支线运输综合报表!$E:$E,"Coleta"),0) -> 0
A11: CE | B11: =G11-F11 -> -1 | C11: =IFERROR(SUMIFS(支线运输综合报表!$AO:$AO,支线运输综合报表!$AD:$AD,$A11,支线运输综合报表!$E:$E,"Coleta")/COUNTIFS(支线运输综合报表!$AD:$AD,$A11,支线运输综合报表!$E:$E,"Coleta"),0) -> 0.75 | D11: =IFERROR(SUMIFS(支线运输综合报表!$AO:$AO,支线运输综合报表!$AD:$AD,$A11,支线运输综合报表!$AP:$AP,D$2,支线运输综合报表!$E:$E,"Coleta")/COUNTIFS(支线运输综合报表!$AD:$AD,$A11,支线运输综合报表!$AP:$AP,D$2,支线运输综合报表!$E:$E,"Coleta"),0) -> 0.5 | E11: =IFERROR(SUMIFS(支线运输综合报表!$AO:$AO,支线运输综合报表!$AD:$AD,$A11,支线运输综合报表!$AP:$AP,E$2,支线运输综合报表!$E:$E,"Coleta")/COUNTIFS(支线运输综合报表!$AD:$AD,$A11,支线运输综合报表!$AP:$AP,E$2,支线运输综合报表!$E:$E,"Coleta"),0) -> 1 | F11: =IFERROR(SUMIFS(支线运输综合报表!$AO:$AO,支线运输综合报表!$AD:$AD,$A11,支线运输综合报表!$AP:$AP,F$2,支线运输综合报表!$E:$E,"Coleta")/COUNTIFS(支线运输综合报表!$AD:$AD,$A11,支线运输综合报表!$AP:$AP,F$2,支线运输综合报表!$E:$E,"Coleta"),0) -> 1 | G11: =IFERROR(SUMIFS(支线运输综合报表!$AO:$AO,支线运输综合报表!$AD:$AD,$A11,支线运输综合报表!$AP:$AP,G$2,支线运输综合报表!$E:$E,"Coleta")/COUNTIFS(支线运输综合报表!$AD:$AD,$A11,支线运输综合报表!$AP:$AP,G$2,支线运输综合报表!$E:$E,"Coleta"),0) -> 0 | H11: =IFERROR(SUMIFS(支线运输综合报表!$AO:$AO,支线运输综合报表!$AD:$AD,$A11,支线运输综合报表!$AP:$AP,H$2,支线运输综合报表!$E:$E,"Coleta")/COUNTIFS(支线运输综合报表!$AD:$AD,$A11,支线运输综合报表!$AP:$AP,H$2,支线运输综合报表!$E:$E,"Coleta"),0) -> 0 | I11: =IFERROR(SUMIFS(支线运输综合报表!$AO:$AO,支线运输综合报表!$AD:$AD,$A11,支线运输综合报表!$AP:$AP,I$2,支线运输综合报表!$E:$E,"Coleta")/COUNTIFS(支线运输综合报表!$AD:$AD,$A11,支线运输综合报表!$AP:$AP,I$2,支线运输综合报表!$E:$E,"Coleta"),0) -> 0 | J11: =IFERROR(SUMIFS(支线运输综合报表!$AO:$AO,支线运输综合报表!$AD:$AD,$A11,支线运输综合报表!$AP:$AP,J$2,支线运输综合报表!$E:$E,"Coleta")/COUNTIFS(支线运输综合报表!$AD:$AD,$A11,支线运输综合报表!$AP:$AP,J$2,支线运输综合报表!$E:$E,"Coleta"),0) -> 0 | K11: =IFERROR(SUMIFS(支线运输综合报表!$AO:$AO,支线运输综合报表!$AD:$AD,$A11,支线运输综合报表!$AP:$AP,K$2,支线运输综合报表!$E:$E,"Coleta")/COUNTIFS(支线运输综合报表!$AD:$AD,$A11,支线运输综合报表!$AP:$AP,K$2,支线运输综合报表!$E:$E,"Coleta"),0) -> 0 | ... AH11: =IFERROR(SUMIFS(支线运输综合报表!$AO:$AO,支线运输综合报表!$AD:$AD,$A11,支线运输综合报表!$AP:$AP,AH$2,支线运输综合报表!$E:$E,"Coleta")/COUNTIFS(支线运输综合报表!$AD:$AD,$A11,支线运输综合报表!$AP:$AP,AH$2,支线运输综合报表!$E:$E,"Coleta"),0) -> 0
A12: 散货解车率趋势Tendência da DESLACRE-Entrega
A13: 到车区域Região de Chegada | B13: 环比±Variação | C13: 10月累计Acumulado de Outubro | D13: 46296 | E13: =D13+1 -> 46297 | F13: =E13+1 -> 46298 | G13: =F13+1 -> 46299 | H13: =G13+1 -> 46300 | I13: =H13+1 -> 46301 | J13: =I13+1 -> 46302 | K13: =J13+1 -> 46303 | L13: =K13+1 -> 46304 | ... AH13: =AG13+1 -> 46326 | AI13: 近七天趋势
A14: 合计 | B14: =G14-F14 -> -0.018521605 | C14: =IFERROR(SUMIFS(支线运输综合报表!$AO:$AO,支线运输综合报表!$E:$E,"Entrega")/COUNTIFS(支线运输综合报表!$E:$E,"Entrega"),0) -> 0.92544522 | D14: =IFERROR(SUMIFS(支线运输综合报表!$AO:$AO,支线运输综合报表!$AP:$AP,D13,支线运输综合报表!$E:$E,"Entrega")/COUNTIFS(支线运输综合报表!$AP:$AP,D13,支线运输综合报表!$E:$E,"Entrega"),0) -> 0.92519252 | E14: =IFERROR(SUMIFS(支线运输综合报表!$AO:$AO,支线运输综合报表!$AP:$AP,E13,支线运输综合报表!$E:$E,"Entrega")/COUNTIFS(支线运输综合报表!$AP:$AP,E13,支线运输综合报表!$E:$E,"Entrega"),0) -> 0.94098712 | F14: =IFERROR(SUMIFS(支线运输综合报表!$AO:$AO,支线运输综合报表!$AP:$AP,F13,支线运输综合报表!$E:$E,"Entrega")/COUNTIFS(支线运输综合报表!$AP:$AP,F13,支线运输综合报表!$E:$E,"Entrega"),0) -> 0.92258065 | G14: =IFERROR(SUMIFS(支线运输综合报表!$AO:$AO,支线运输综合报表!$AP:$AP,G13,支线运输综合报表!$E:$E,"Entrega")/COUNTIFS(支线运输综合报表!$AP:$AP,G13,支线运输综合报表!$E:$E,"Entrega"),0) -> 0.90405904 | H14: =IFERROR(SUMIFS(支线运输综合报表!$AO:$AO,支线运输综合报表!$AP:$AP,H13,支线运输综合报表!$E:$E,"Entrega")/COUNTIFS(支线运输综合报表!$AP:$AP,H13,支线运输综合报表!$E:$E,"Entrega"),0) -> 0 | I14: =IFERROR(SUMIFS(支线运输综合报表!$AO:$AO,支线运输综合报表!$AP:$AP,I13,支线运输综合报表!$E:$E,"Entrega")/COUNTIFS(支线运输综合报表!$AP:$AP,I13,支线运输综合报表!$E:$E,"Entrega"),0) -> 0 | J14: =IFERROR(SUMIFS(支线运输综合报表!$AO:$AO,支线运输综合报表!$AP:$AP,J13,支线运输综合报表!$E:$E,"Entrega")/COUNTIFS(支线运输综合报表!$AP:$AP,J13,支线运输综合报表!$E:$E,"Entrega"),0) -> 0 | K14: =IFERROR(SUMIFS(支线运输综合报表!$AO:$AO,支线运输综合报表!$AP:$AP,K13,支线运输综合报表!$E:$E,"Entrega")/COUNTIFS(支线运输综合报表!$AP:$AP,K13,支线运输综合报表!$E:$E,"Entrega"),0) -> 0 | ... AH14: =IFERROR(SUMIFS(支线运输综合报表!$AO:$AO,支线运输综合报表!$AP:$AP,AH13,支线运输综合报表!$E:$E,"Entrega")/COUNTIFS(支线运输综合报表!$AP:$AP,AH13,支线运输综合报表!$E:$E,"Entrega"),0) -> 0
A15: CE | B15: =G15-F15 -> -0.23376623 | C15: =IFERROR(SUMIFS(支线运输综合报表!$AO:$AO,支线运输综合报表!$AD:$AD,$A15,支线运输综合报表!$E:$E,"Entrega")/COUNTIFS(支线运输综合报表!$AD:$AD,$A15,支线运输综合报表!$E:$E,"Entrega"),0) -> 0.94077449 | D15: =IFERROR(SUMIFS(支线运输综合报表!$AO:$AO,支线运输综合报表!$AD:$AD,$A15,支线运输综合报表!$AP:$AP,D$2,支线运输综合报表!$E:$E,"Entrega")/COUNTIFS(支线运输综合报表!$AD:$AD,$A15,支线运输综合报表!$AP:$AP,D$2,支线运输综合报表!$E:$E,"Entrega"),0) -> 0.93181818 | E15: =IFERROR(SUMIFS(支线运输综合报表!$AO:$AO,支线运输综合报表!$AD:$AD,$A15,支线运输综合报表!$AP:$AP,E$2,支线运输综合报表!$E:$E,"Entrega")/COUNTIFS(支线运输综合报表!$AD:$AD,$A15,支线运输综合报表!$AP:$AP,E$2,支线运输综合报表!$E:$E,"Entrega"),0) -> 0.95205479 | F15: =IFERROR(SUMIFS(支线运输综合报表!$AO:$AO,支线运输综合报表!$AD:$AD,$A15,支线运输综合报表!$AP:$AP,F$2,支线运输综合报表!$E:$E,"Entrega")/COUNTIFS(支线运输综合报表!$AD:$AD,$A15,支线运输综合报表!$AP:$AP,F$2,支线运输综合报表!$E:$E,"Entrega"),0) -> 0.94805195 | G15: =IFERROR(SUMIFS(支线运输综合报表!$AO:$AO,支线运输综合报表!$AD:$AD,$A15,支线运输综合报表!$AP:$AP,G$2,支线运输综合报表!$E:$E,"Entrega")/COUNTIFS(支线运输综合报表!$AD:$AD,$A15,支线运输综合报表!$AP:$AP,G$2,支线运输综合报表!$E:$E,"Entrega"),0) -> 0.71428571 | H15: =IFERROR(SUMIFS(支线运输综合报表!$AO:$AO,支线运输综合报表!$AD:$AD,$A15,支线运输综合报表!$AP:$AP,H$2,支线运输综合报表!$E:$E,"Entrega")/COUNTIFS(支线运输综合报表!$AD:$AD,$A15,支线运输综合报表!$AP:$AP,H$2,支线运输综合报表!$E:$E,"Entrega"),0) -> 0 | I15: =IFERROR(SUMIFS(支线运输综合报表!$AO:$AO,支线运输综合报表!$AD:$AD,$A15,支线运输综合报表!$AP:$AP,I$2,支线运输综合报表!$E:$E,"Entrega")/COUNTIFS(支线运输综合报表!$AD:$AD,$A15,支线运输综合报表!$AP:$AP,I$2,支线运输综合报表!$E:$E,"Entrega"),0) -> 0 | J15: =IFERROR(SUMIFS(支线运输综合报表!$AO:$AO,支线运输综合报表!$AD:$AD,$A15,支线运输综合报表!$AP:$AP,J$2,支线运输综合报表!$E:$E,"Entrega")/COUNTIFS(支线运输综合报表!$AD:$AD,$A15,支线运输综合报表!$AP:$AP,J$2,支线运输综合报表!$E:$E,"Entrega"),0) -> 0 | K15: =IFERROR(SUMIFS(支线运输综合报表!$AO:$AO,支线运输综合报表!$AD:$AD,$A15,支线运输综合报表!$AP:$AP,K$2,支线运输综合报表!$E:$E,"Entrega")/COUNTIFS(支线运输综合报表!$AD:$AD,$A15,支线运输综合报表!$AP:$AP,K$2,支线运输综合报表!$E:$E,"Entrega"),0) -> 0 | ... AH15: =IFERROR(SUMIFS(支线运输综合报表!$AO:$AO,支线运输综合报表!$AD:$AD,$A15,支线运输综合报表!$AP:$AP,AH$2,支线运输综合报表!$E:$E,"Entrega")/COUNTIFS(支线运输综合报表!$AD:$AD,$A15,支线运输综合报表!$AP:$AP,AH$2,支线运输综合报表!$E:$E,"Entrega"),0) -> 0
A16: SPN | B16: =G16-F16 -> -0.016483516 | C16: =IFERROR(SUMIFS(支线运输综合报表!$AO:$AO,支线运输综合报表!$AD:$AD,$A16,支线运输综合报表!$E:$E,"Entrega")/COUNTIFS(支线运输综合报表!$AD:$AD,$A16,支线运输综合报表!$E:$E,"Entrega"),0) -> 0.97761194 | D16: =IFERROR(SUMIFS(支线运输综合报表!$AO:$AO,支线运输综合报表!$AD:$AD,$A16,支线运输综合报表!$AP:$AP,D$2,支线运输综合报表!$E:$E,"Entrega")/COUNTIFS(支线运输综合报表!$AD:$AD,$A16,支线运输综合报表!$AP:$AP,D$2,支线运输综合报表!$E:$E,"Entrega"),0) -> 0.96774194 | E16: =IFERROR(SUMIFS(支线运输综合报表!$AO:$AO,支线运输综合报表!$AD:$AD,$A16,支线运输综合报表!$AP:$AP,E$2,支线运输综合报表!$E:$E,"Entrega")/COUNTIFS(支线运输综合报表!$AD:$AD,$A16,支线运输综合报表!$AP:$AP,E$2,支线运输综合报表!$E:$E,"Entrega"),0) -> 0.98591549 | F16: =IFERROR(SUMIFS(支线运输综合报表!$AO:$AO,支线运输综合报表!$AD:$AD,$A16,支线运输综合报表!$AP:$AP,F$2,支线运输综合报表!$E:$E,"Entrega")/COUNTIFS(支线运输综合报表!$AD:$AD,$A16,支线运输综合报表!$AP:$AP,F$2,支线运输综合报表!$E:$E,"Entrega"),0) -> 0.98571429 | G16: =IFERROR(SUMIFS(支线运输综合报表!$AO:$AO,支线运输综合报表!$AD:$AD,$A16,支线运输综合报表!$AP:$AP,G$2,支线运输综合报表!$E:$E,"Entrega")/COUNTIFS(支线运输综合报表!$AD:$AD,$A16,支线运输综合报表!$AP:$AP,G$2,支线运输综合报表!$E:$E,"Entrega"),0) -> 0.96923077 | H16: =IFERROR(SUMIFS(支线运输综合报表!$AO:$AO,支线运输综合报表!$AD:$AD,$A16,支线运输综合报表!$AP:$AP,H$2,支线运输综合报表!$E:$E,"Entrega")/COUNTIFS(支线运输综合报表!$AD:$AD,$A16,支线运输综合报表!$AP:$AP,H$2,支线运输综合报表!$E:$E,"Entrega"),0) -> 0 | I16: =IFERROR(SUMIFS(支线运输综合报表!$AO:$AO,支线运输综合报表!$AD:$AD,$A16,支线运输综合报表!$AP:$AP,I$2,支线运输综合报表!$E:$E,"Entrega")/COUNTIFS(支线运输综合报表!$AD:$AD,$A16,支线运输综合报表!$AP:$AP,I$2,支线运输综合报表!$E:$E,"Entrega"),0) -> 0 | J16: =IFERROR(SUMIFS(支线运输综合报表!$AO:$AO,支线运输综合报表!$AD:$AD,$A16,支线运输综合报表!$AP:$AP,J$2,支线运输综合报表!$E:$E,"Entrega")/COUNTIFS(支线运输综合报表!$AD:$AD,$A16,支线运输综合报表!$AP:$AP,J$2,支线运输综合报表!$E:$E,"Entrega"),0) -> 0 | K16: =IFERROR(SUMIFS(支线运输综合报表!$AO:$AO,支线运输综合报表!$AD:$AD,$A16,支线运输综合报表!$AP:$AP,K$2,支线运输综合报表!$E:$E,"Entrega")/COUNTIFS(支线运输综合报表!$AD:$AD,$A16,支线运输综合报表!$AP:$AP,K$2,支线运输综合报表!$E:$E,"Entrega"),0) -> 0 | ... AH16: =IFERROR(SUMIFS(支线运输综合报表!$AO:$AO,支线运输综合报表!$AD:$AD,$A16,支线运输综合报表!$AP:$AP,AH$2,支线运输综合报表!$E:$E,"Entrega")/COUNTIFS(支线运输综合报表!$AD:$AD,$A16,支线运输综合报表!$AP:$AP,AH$2,支线运输综合报表!$E:$E,"Entrega"),0) -> 0
A17: SPS | B17: =G17-F17 -> 0.042827901 | C17: =IFERROR(SUMIFS(支线运输综合报表!$AO:$AO,支线运输综合报表!$AD:$AD,$A17,支线运输综合报表!$E:$E,"Entrega")/COUNTIFS(支线运输综合报表!$AD:$AD,$A17,支线运输综合报表!$E:$E,"Entrega"),0) -> 0.90352505 | D17: =IFERROR(SUMIFS(支线运输综合报表!$AO:$AO,支线运输综合报表!$AD:$AD,$A17,支线运输综合报表!$AP:$AP,D$2,支线运输综合报表!$E:$E,"Entrega")/COUNTIFS(支线运输综合报表!$AD:$AD,$A17,支线运输综合报表!$AP:$AP,D$2,支线运输综合报表!$E:$E,"Entrega"),0) -> 0.90384615 | E17: =IFERROR(SUMIFS(支线运输综合报表!$AO:$AO,支线运输综合报表!$AD:$AD,$A17,支线运输综合报表!$AP:$AP,E$2,支线运输综合报表!$E:$E,"Entrega")/COUNTIFS(支线运输综合报表!$AD:$AD,$A17,支线运输综合报表!$AP:$AP,E$2,支线运输综合报表!$E:$E,"Entrega"),0) -> 0.92 | F17: =IFERROR(SUMIFS(支线运输综合报表!$AO:$AO,支线运输综合报表!$AD:$AD,$A17,支线运输综合报表!$AP:$AP,F$2,支线运输综合报表!$E:$E,"Entrega")/COUNTIFS(支线运输综合报表!$AD:$AD,$A17,支线运输综合报表!$AP:$AP,F$2,支线运输综合报表!$E:$E,"Entrega"),0) -> 0.87671233 | G17: =IFERROR(SUMIFS(支线运输综合报表!$AO:$AO,支线运输综合报表!$AD:$AD,$A17,支线运输综合报表!$AP:$AP,G$2,支线运输综合报表!$E:$E,"Entrega")/COUNTIFS(支线运输综合报表!$AD:$AD,$A17,支线运输综合报表!$AP:$AP,G$2,支线运输综合报表!$E:$E,"Entrega"),0) -> 0.91954023 | H17: =IFERROR(SUMIFS(支线运输综合报表!$AO:$AO,支线运输综合报表!$AD:$AD,$A17,支线运输综合报表!$AP:$AP,H$2,支线运输综合报表!$E:$E,"Entrega")/COUNTIFS(支线运输综合报表!$AD:$AD,$A17,支线运输综合报表!$AP:$AP,H$2,支线运输综合报表!$E:$E,"Entrega"),0) -> 0 | I17: =IFERROR(SUMIFS(支线运输综合报表!$AO:$AO,支线运输综合报表!$AD:$AD,$A17,支线运输综合报表!$AP:$AP,I$2,支线运输综合报表!$E:$E,"Entrega")/COUNTIFS(支线运输综合报表!$AD:$AD,$A17,支线运输综合报表!$AP:$AP,I$2,支线运输综合报表!$E:$E,"Entrega"),0) -> 0 | J17: =IFERROR(SUMIFS(支线运输综合报表!$AO:$AO,支线运输综合报表!$AD:$AD,$A17,支线运输综合报表!$AP:$AP,J$2,支线运输综合报表!$E:$E,"Entrega")/COUNTIFS(支线运输综合报表!$AD:$AD,$A17,支线运输综合报表!$AP:$AP,J$2,支线运输综合报表!$E:$E,"Entrega"),0) -> 0 | K17: =IFERROR(SUMIFS(支线运输综合报表!$AO:$AO,支线运输综合报表!$AD:$AD,$A17,支线运输综合报表!$AP:$AP,K$2,支线运输综合报表!$E:$E,"Entrega")/COUNTIFS(支线运输综合报表!$AD:$AD,$A17,支线运输综合报表!$AP:$AP,K$2,支线运输综合报表!$E:$E,"Entrega"),0) -> 0 | ... AH17: =IFERROR(SUMIFS(支线运输综合报表!$AO:$AO,支线运输综合报表!$AD:$AD,$A17,支线运输综合报表!$AP:$AP,AH$2,支线运输综合报表!$E:$E,"Entrega")/COUNTIFS(支线运输综合报表!$AD:$AD,$A17,支线运输综合报表!$AP:$AP,AH$2,支线运输综合报表!$E:$E,"Entrega"),0) -> 0
A18: GP | B18: =G18-F18 -> -0.028282828 | C18: =IFERROR(SUMIFS(支线运输综合报表!$AO:$AO,支线运输综合报表!$AD:$AD,$A18,支线运输综合报表!$E:$E,"Entrega")/COUNTIFS(支线运输综合报表!$AD:$AD,$A18,支线运输综合报表!$E:$E,"Entrega"),0) -> 0.93854749 | D18: =IFERROR(SUMIFS(支线运输综合报表!$AO:$AO,支线运输综合报表!$AD:$AD,$A18,支线运输综合报表!$AP:$AP,D$2,支线运输综合报表!$E:$E,"Entrega")/COUNTIFS(支线运输综合报表!$AD:$AD,$A18,支线运输综合报表!$AP:$AP,D$2,支线运输综合报表!$E:$E,"Entrega"),0) -> 0.95522388 | E18: =IFERROR(SUMIFS(支线运输综合报表!$AO:$AO,支线运输综合报表!$AD:$AD,$A18,支线运输综合报表!$AP:$AP,E$2,支线运输综合报表!$E:$E,"Entrega")/COUNTIFS(支线运输综合报表!$AD:$AD,$A18,支线运输综合报表!$AP:$AP,E$2,支线运输综合报表!$E:$E,"Entrega"),0) -> 0.94852941 | F18: =IFERROR(SUMIFS(支线运输综合报表!$AO:$AO,支线运输综合报表!$AD:$AD,$A18,支线运输综合报表!$AP:$AP,F$2,支线运输综合报表!$E:$E,"Entrega")/COUNTIFS(支线运输综合报表!$AD:$AD,$A18,支线运输综合报表!$AP:$AP,F$2,支线运输综合报表!$E:$E,"Entrega"),0) -> 0.93939394 | G18: =IFERROR(SUMIFS(支线运输综合报表!$AO:$AO,支线运输综合报表!$AD:$AD,$A18,支线运输综合报表!$AP:$AP,G$2,支线运输综合报表!$E:$E,"Entrega")/COUNTIFS(支线运输综合报表!$AD:$AD,$A18,支线运输综合报表!$AP:$AP,G$2,支线运输综合报表!$E:$E,"Entrega"),0) -> 0.91111111 | H18: =IFERROR(SUMIFS(支线运输综合报表!$AO:$AO,支线运输综合报表!$AD:$AD,$A18,支线运输综合报表!$AP:$AP,H$2,支线运输综合报表!$E:$E,"Entrega")/COUNTIFS(支线运输综合报表!$AD:$AD,$A18,支线运输综合报表!$AP:$AP,H$2,支线运输综合报表!$E:$E,"Entrega"),0) -> 0 | I18: =IFERROR(SUMIFS(支线运输综合报表!$AO:$AO,支线运输综合报表!$AD:$AD,$A18,支线运输综合报表!$AP:$AP,I$2,支线运输综合报表!$E:$E,"Entrega")/COUNTIFS(支线运输综合报表!$AD:$AD,$A18,支线运输综合报表!$AP:$AP,I$2,支线运输综合报表!$E:$E,"Entrega"),0) -> 0 | J18: =IFERROR(SUMIFS(支线运输综合报表!$AO:$AO,支线运输综合报表!$AD:$AD,$A18,支线运输综合报表!$AP:$AP,J$2,支线运输综合报表!$E:$E,"Entrega")/COUNTIFS(支线运输综合报表!$AD:$AD,$A18,支线运输综合报表!$AP:$AP,J$2,支线运输综合报表!$E:$E,"Entrega"),0) -> 0 | K18: =IFERROR(SUMIFS(支线运输综合报表!$AO:$AO,支线运输综合报表!$AD:$AD,$A18,支线运输综合报表!$AP:$AP,K$2,支线运输综合报表!$E:$E,"Entrega")/COUNTIFS(支线运输综合报表!$AD:$AD,$A18,支线运输综合报表!$AP:$AP,K$2,支线运输综合报表!$E:$E,"Entrega"),0) -> 0 | ... AH18: =IFERROR(SUMIFS(支线运输综合报表!$AO:$AO,支线运输综合报表!$AD:$AD,$A18,支线运输综合报表!$AP:$AP,AH$2,支线运输综合报表!$E:$E,"Entrega")/COUNTIFS(支线运输综合报表!$AD:$AD,$A18,支线运输综合报表!$AP:$AP,AH$2,支线运输综合报表!$E:$E,"Entrega"),0) -> 0
A19: SPE | B19: =G19-F19 -> -0.11294261 | C19: =IFERROR(SUMIFS(支线运输综合报表!$AO:$AO,支线运输综合报表!$AD:$AD,$A19,支线运输综合报表!$E:$E,"Entrega")/COUNTIFS(支线运输综合报表!$AD:$AD,$A19,支线运输综合报表!$E:$E,"Entrega"),0) -> 0.92488263 | D19: =IFERROR(SUMIFS(支线运输综合报表!$AO:$AO,支线运输综合报表!$AD:$AD,$A19,支线运输综合报表!$AP:$AP,D$2,支线运输综合报表!$E:$E,"Entrega")/COUNTIFS(支线运输综合报表!$AD:$AD,$A19,支线运输综合报表!$AP:$AP,D$2,支线运输综合报表!$E:$E,"Entrega"),0) -> 0.95238095 | E19: =IFERROR(SUMIFS(支线运输综合报表!$AO:$AO,支线运输综合报表!$AD:$AD,$A19,支线运输综合报表!$AP:$AP,E$2,支线运输综合报表!$E:$E,"Entrega")/COUNTIFS(支线运输综合报表!$AD:$AD,$A19,支线运输综合报表!$AP:$AP,E$2,支线运输综合报表!$E:$E,"Entrega"),0) -> 0.95081967 | F19: =IFERROR(SUMIFS(支线运输综合报表!$AO:$AO,支线运输综合报表!$AD:$AD,$A19,支线运输综合报表!$AP:$AP,F$2,支线运输综合报表!$E:$E,"Entrega")/COUNTIFS(支线运输综合报表!$AD:$AD,$A19,支线运输综合报表!$AP:$AP,F$2,支线运输综合报表!$E:$E,"Entrega"),0) -> 0.92063492 | G19: =IFERROR(SUMIFS(支线运输综合报表!$AO:$AO,支线运输综合报表!$AD:$AD,$A19,支线运输综合报表!$AP:$AP,G$2,支线运输综合报表!$E:$E,"Entrega")/COUNTIFS(支线运输综合报表!$AD:$AD,$A19,支线运输综合报表!$AP:$AP,G$2,支线运输综合报表!$E:$E,"Entrega"),0) -> 0.80769231 | H19: =IFERROR(SUMIFS(支线运输综合报表!$AO:$AO,支线运输综合报表!$AD:$AD,$A19,支线运输综合报表!$AP:$AP,H$2,支线运输综合报表!$E:$E,"Entrega")/COUNTIFS(支线运输综合报表!$AD:$AD,$A19,支线运输综合报表!$AP:$AP,H$2,支线运输综合报表!$E:$E,"Entrega"),0) -> 0 | I19: =IFERROR(SUMIFS(支线运输综合报表!$AO:$AO,支线运输综合报表!$AD:$AD,$A19,支线运输综合报表!$AP:$AP,I$2,支线运输综合报表!$E:$E,"Entrega")/COUNTIFS(支线运输综合报表!$AD:$AD,$A19,支线运输综合报表!$AP:$AP,I$2,支线运输综合报表!$E:$E,"Entrega"),0) -> 0 | J19: =IFERROR(SUMIFS(支线运输综合报表!$AO:$AO,支线运输综合报表!$AD:$AD,$A19,支线运输综合报表!$AP:$AP,J$2,支线运输综合报表!$E:$E,"Entrega")/COUNTIFS(支线运输综合报表!$AD:$AD,$A19,支线运输综合报表!$AP:$AP,J$2,支线运输综合报表!$E:$E,"Entrega"),0) -> 0 | K19: =IFERROR(SUMIFS(支线运输综合报表!$AO:$AO,支线运输综合报表!$AD:$AD,$A19,支线运输综合报表!$AP:$AP,K$2,支线运输综合报表!$E:$E,"Entrega")/COUNTIFS(支线运输综合报表!$AD:$AD,$A19,支线运输综合报表!$AP:$AP,K$2,支线运输综合报表!$E:$E,"Entrega"),0) -> 0 | ... AH19: =IFERROR(SUMIFS(支线运输综合报表!$AO:$AO,支线运输综合报表!$AD:$AD,$A19,支线运输综合报表!$AP:$AP,AH$2,支线运输综合报表!$E:$E,"Entrega")/COUNTIFS(支线运输综合报表!$AD:$AD,$A19,支线运输综合报表!$AP:$AP,AH$2,支线运输综合报表!$E:$E,"Entrega"),0) -> 0
A20: RJ | B20: =G20-F20 -> -0.066770186 | C20: =IFERROR(SUMIFS(支线运输综合报表!$AO:$AO,支线运输综合报表!$AD:$AD,$A20,支线运输综合报表!$E:$E,"Entrega")/COUNTIFS(支线运输综合报表!$AD:$AD,$A20,支线运输综合报表!$E:$E,"Entrega"),0) -> 0.93059937 | D20: =IFERROR(SUMIFS(支线运输综合报表!$AO:$AO,支线运输综合报表!$AD:$AD,$A20,支线运输综合报表!$AP:$AP,D$2,支线运输综合报表!$E:$E,"Entrega")/COUNTIFS(支线运输综合报表!$AD:$AD,$A20,支线运输综合报表!$AP:$AP,D$2,支线运输综合报表!$E:$E,"Entrega"),0) -> 0.94791667 | E20: =IFERROR(SUMIFS(支线运输综合报表!$AO:$AO,支线运输综合报表!$AD:$AD,$A20,支线运输综合报表!$AP:$AP,E$2,支线运输综合报表!$E:$E,"Entrega")/COUNTIFS(支线运输综合报表!$AD:$AD,$A20,支线运输综合报表!$AP:$AP,E$2,支线运输综合报表!$E:$E,"Entrega"),0) -> 0.94680851 | F20: =IFERROR(SUMIFS(支线运输综合报表!$AO:$AO,支线运输综合报表!$AD:$AD,$A20,支线运输综合报表!$AP:$AP,F$2,支线运输综合报表!$E:$E,"Entrega")/COUNTIFS(支线运输综合报表!$AD:$AD,$A20,支线运输综合报表!$AP:$AP,F$2,支线运输综合报表!$E:$E,"Entrega"),0) -> 0.92391304 | G20: =IFERROR(SUMIFS(支线运输综合报表!$AO:$AO,支线运输综合报表!$AD:$AD,$A20,支线运输综合报表!$AP:$AP,G$2,支线运输综合报表!$E:$E,"Entrega")/COUNTIFS(支线运输综合报表!$AD:$AD,$A20,支线运输综合报表!$AP:$AP,G$2,支线运输综合报表!$E:$E,"Entrega"),0) -> 0.85714286 | H20: =IFERROR(SUMIFS(支线运输综合报表!$AO:$AO,支线运输综合报表!$AD:$AD,$A20,支线运输综合报表!$AP:$AP,H$2,支线运输综合报表!$E:$E,"Entrega")/COUNTIFS(支线运输综合报表!$AD:$AD,$A20,支线运输综合报表!$AP:$AP,H$2,支线运输综合报表!$E:$E,"Entrega"),0) -> 0 | I20: =IFERROR(SUMIFS(支线运输综合报表!$AO:$AO,支线运输综合报表!$AD:$AD,$A20,支线运输综合报表!$AP:$AP,I$2,支线运输综合报表!$E:$E,"Entrega")/COUNTIFS(支线运输综合报表!$AD:$AD,$A20,支线运输综合报表!$AP:$AP,I$2,支线运输综合报表!$E:$E,"Entrega"),0) -> 0 | J20: =IFERROR(SUMIFS(支线运输综合报表!$AO:$AO,支线运输综合报表!$AD:$AD,$A20,支线运输综合报表!$AP:$AP,J$2,支线运输综合报表!$E:$E,"Entrega")/COUNTIFS(支线运输综合报表!$AD:$AD,$A20,支线运输综合报表!$AP:$AP,J$2,支线运输综合报表!$E:$E,"Entrega"),0) -> 0 | K20: =IFERROR(SUMIFS(支线运输综合报表!$AO:$AO,支线运输综合报表!$AD:$AD,$A20,支线运输综合报表!$AP:$AP,K$2,支线运输综合报表!$E:$E,"Entrega")/COUNTIFS(支线运输综合报表!$AD:$AD,$A20,支线运输综合报表!$AP:$AP,K$2,支线运输综合报表!$E:$E,"Entrega"),0) -> 0 | ... AH20: =IFERROR(SUMIFS(支线运输综合报表!$AO:$AO,支线运输综合报表!$AD:$AD,$A20,支线运输综合报表!$AP:$AP,AH$2,支线运输综合报表!$E:$E,"Entrega")/COUNTIFS(支线运输综合报表!$AD:$AD,$A20,支线运输综合报表!$AP:$AP,AH$2,支线运输综合报表!$E:$E,"Entrega"),0) -> 0
A21: PR | B21: =G21-F21 -> -0.01922487 | C21: =IFERROR(SUMIFS(支线运输综合报表!$AO:$AO,支线运输综合报表!$AD:$AD,$A21,支线运输综合报表!$E:$E,"Entrega")/COUNTIFS(支线运输综合报表!$AD:$AD,$A21,支线运输综合报表!$E:$E,"Entrega"),0) -> 0.84698276 | D21: =IFERROR(SUMIFS(支线运输综合报表!$AO:$AO,支线运输综合报表!$AD:$AD,$A21,支线运输综合报表!$AP:$AP,D$2,支线运输综合报表!$E:$E,"Entrega")/COUNTIFS(支线运输综合报表!$AD:$AD,$A21,支线运输综合报表!$AP:$AP,D$2,支线运输综合报表!$E:$E,"Entrega"),0) -> 0.83076923 | E21: =IFERROR(SUMIFS(支线运输综合报表!$AO:$AO,支线运输综合报表!$AD:$AD,$A21,支线运输综合报表!$AP:$AP,E$2,支线运输综合报表!$E:$E,"Entrega")/COUNTIFS(支线运输综合报表!$AD:$AD,$A21,支线运输综合报表!$AP:$AP,E$2,支线运输综合报表!$E:$E,"Entrega"),0) -> 0.86923077 | F21: =IFERROR(SUMIFS(支线运输综合报表!$AO:$AO,支线运输综合报表!$AD:$AD,$A21,支线运输综合报表!$AP:$AP,F$2,支线运输综合报表!$E:$E,"Entrega")/COUNTIFS(支线运输综合报表!$AD:$AD,$A21,支线运输综合报表!$AP:$AP,F$2,支线运输综合报表!$E:$E,"Entrega"),0) -> 0.8503937 | G21: =IFERROR(SUMIFS(支线运输综合报表!$AO:$AO,支线运输综合报表!$AD:$AD,$A21,支线运输综合报表!$AP:$AP,G$2,支线运输综合报表!$E:$E,"Entrega")/COUNTIFS(支线运输综合报表!$AD:$AD,$A21,支线运输综合报表!$AP:$AP,G$2,支线运输综合报表!$E:$E,"Entrega"),0) -> 0.83116883 | H21: =IFERROR(SUMIFS(支线运输综合报表!$AO:$AO,支线运输综合报表!$AD:$AD,$A21,支线运输综合报表!$AP:$AP,H$2,支线运输综合报表!$E:$E,"Entrega")/COUNTIFS(支线运输综合报表!$AD:$AD,$A21,支线运输综合报表!$AP:$AP,H$2,支线运输综合报表!$E:$E,"Entrega"),0) -> 0 | I21: =IFERROR(SUMIFS(支线运输综合报表!$AO:$AO,支线运输综合报表!$AD:$AD,$A21,支线运输综合报表!$AP:$AP,I$2,支线运输综合报表!$E:$E,"Entrega")/COUNTIFS(支线运输综合报表!$AD:$AD,$A21,支线运输综合报表!$AP:$AP,I$2,支线运输综合报表!$E:$E,"Entrega"),0) -> 0 | J21: =IFERROR(SUMIFS(支线运输综合报表!$AO:$AO,支线运输综合报表!$AD:$AD,$A21,支线运输综合报表!$AP:$AP,J$2,支线运输综合报表!$E:$E,"Entrega")/COUNTIFS(支线运输综合报表!$AD:$AD,$A21,支线运输综合报表!$AP:$AP,J$2,支线运输综合报表!$E:$E,"Entrega"),0) -> 0 | K21: =IFERROR(SUMIFS(支线运输综合报表!$AO:$AO,支线运输综合报表!$AD:$AD,$A21,支线运输综合报表!$AP:$AP,K$2,支线运输综合报表!$E:$E,"Entrega")/COUNTIFS(支线运输综合报表!$AD:$AD,$A21,支线运输综合报表!$AP:$AP,K$2,支线运输综合报表!$E:$E,"Entrega"),0) -> 0 | ... AH21: =IFERROR(SUMIFS(支线运输综合报表!$AO:$AO,支线运输综合报表!$AD:$AD,$A21,支线运输综合报表!$AP:$AP,AH$2,支线运输综合报表!$E:$E,"Entrega")/COUNTIFS(支线运输综合报表!$AD:$AD,$A21,支线运输综合报表!$AP:$AP,AH$2,支线运输综合报表!$E:$E,"Entrega"),0) -> 0
A22: MG | B22: =G22-F22 -> -0.015011179 | C22: =IFERROR(SUMIFS(支线运输综合报表!$AO:$AO,支线运输综合报表!$AD:$AD,$A22,支线运输综合报表!$E:$E,"Entrega")/COUNTIFS(支线运输综合报表!$AD:$AD,$A22,支线运输综合报表!$E:$E,"Entrega"),0) -> 0.95533499 | D22: =IFERROR(SUMIFS(支线运输综合报表!$AO:$AO,支线运输综合报表!$AD:$AD,$A22,支线运输综合报表!$AP:$AP,D$2,支线运输综合报表!$E:$E,"Entrega")/COUNTIFS(支线运输综合报表!$AD:$AD,$A22,支线运输综合报表!$AP:$AP,D$2,支线运输综合报表!$E:$E,"Entrega"),0) -> 0.95283019 | E22: =IFERROR(SUMIFS(支线运输综合报表!$AO:$AO,支线运输综合报表!$AD:$AD,$A22,支线运输综合报表!$AP:$AP,E$2,支线运输综合报表!$E:$E,"Entrega")/COUNTIFS(支线运输综合报表!$AD:$AD,$A22,支线运输综合报表!$AP:$AP,E$2,支线运输综合报表!$E:$E,"Entrega"),0) -> 0.98058252 | F22: =IFERROR(SUMIFS(支线运输综合报表!$AO:$AO,支线运输综合报表!$AD:$AD,$A22,支线运输综合报表!$AP:$AP,F$2,支线运输综合报表!$E:$E,"Entrega")/COUNTIFS(支线运输综合报表!$AD:$AD,$A22,支线运输综合报表!$AP:$AP,F$2,支线运输综合报表!$E:$E,"Entrega"),0) -> 0.95049505 | G22: =IFERROR(SUMIFS(支线运输综合报表!$AO:$AO,支线运输综合报表!$AD:$AD,$A22,支线运输综合报表!$AP:$AP,G$2,支线运输综合报表!$E:$E,"Entrega")/COUNTIFS(支线运输综合报表!$AD:$AD,$A22,支线运输综合报表!$AP:$AP,G$2,支线运输综合报表!$E:$E,"Entrega"),0) -> 0.93548387 | H22: =IFERROR(SUMIFS(支线运输综合报表!$AO:$AO,支线运输综合报表!$AD:$AD,$A22,支线运输综合报表!$AP:$AP,H$2,支线运输综合报表!$E:$E,"Entrega")/COUNTIFS(支线运输综合报表!$AD:$AD,$A22,支线运输综合报表!$AP:$AP,H$2,支线运输综合报表!$E:$E,"Entrega"),0) -> 0 | I22: =IFERROR(SUMIFS(支线运输综合报表!$AO:$AO,支线运输综合报表!$AD:$AD,$A22,支线运输综合报表!$AP:$AP,I$2,支线运输综合报表!$E:$E,"Entrega")/COUNTIFS(支线运输综合报表!$AD:$AD,$A22,支线运输综合报表!$AP:$AP,I$2,支线运输综合报表!$E:$E,"Entrega"),0) -> 0 | J22: =IFERROR(SUMIFS(支线运输综合报表!$AO:$AO,支线运输综合报表!$AD:$AD,$A22,支线运输综合报表!$AP:$AP,J$2,支线运输综合报表!$E:$E,"Entrega")/COUNTIFS(支线运输综合报表!$AD:$AD,$A22,支线运输综合报表!$AP:$AP,J$2,支线运输综合报表!$E:$E,"Entrega"),0) -> 0 | K22: =IFERROR(SUMIFS(支线运输综合报表!$AO:$AO,支线运输综合报表!$AD:$AD,$A22,支线运输综合报表!$AP:$AP,K$2,支线运输综合报表!$E:$E,"Entrega")/COUNTIFS(支线运输综合报表!$AD:$AD,$A22,支线运输综合报表!$AP:$AP,K$2,支线运输综合报表!$E:$E,"Entrega"),0) -> 0 | ... AH22: =IFERROR(SUMIFS(支线运输综合报表!$AO:$AO,支线运输综合报表!$AD:$AD,$A22,支线运输综合报表!$AP:$AP,AH$2,支线运输综合报表!$E:$E,"Entrega")/COUNTIFS(支线运输综合报表!$AD:$AD,$A22,支线运输综合报表!$AP:$AP,AH$2,支线运输综合报表!$E:$E,"Entrega"),0) -> 0
A23: BA | B23: =G23-F23 -> 0.022222222 | C23: =IFERROR(SUMIFS(支线运输综合报表!$AO:$AO,支线运输综合报表!$AD:$AD,$A23,支线运输综合报表!$E:$E,"Entrega")/COUNTIFS(支线运输综合报表!$AD:$AD,$A23,支线运输综合报表!$E:$E,"Entrega"),0) -> 0.97744361 | D23: =IFERROR(SUMIFS(支线运输综合报表!$AO:$AO,支线运输综合报表!$AD:$AD,$A23,支线运输综合报表!$AP:$AP,D$2,支线运输综合报表!$E:$E,"Entrega")/COUNTIFS(支线运输综合报表!$AD:$AD,$A23,支线运输综合报表!$AP:$AP,D$2,支线运输综合报表!$E:$E,"Entrega"),0) -> 0.96666667 | E23: =IFERROR(SUMIFS(支线运输综合报表!$AO:$AO,支线运输综合报表!$AD:$AD,$A23,支线运输综合报表!$AP:$AP,E$2,支线运输综合报表!$E:$E,"Entrega")/COUNTIFS(支线运输综合报表!$AD:$AD,$A23,支线运输综合报表!$AP:$AP,E$2,支线运输综合报表!$E:$E,"Entrega"),0) -> 0.97560976 | F23: =IFERROR(SUMIFS(支线运输综合报表!$AO:$AO,支线运输综合报表!$AD:$AD,$A23,支线运输综合报表!$AP:$AP,F$2,支线运输综合报表!$E:$E,"Entrega")/COUNTIFS(支线运输综合报表!$AD:$AD,$A23,支线运输综合报表!$AP:$AP,F$2,支线运输综合报表!$E:$E,"Entrega"),0) -> 0.97777778 | G23: =IFERROR(SUMIFS(支线运输综合报表!$AO:$AO,支线运输综合报表!$AD:$AD,$A23,支线运输综合报表!$AP:$AP,G$2,支线运输综合报表!$E:$E,"Entrega")/COUNTIFS(支线运输综合报表!$AD:$AD,$A23,支线运输综合报表!$AP:$AP,G$2,支线运输综合报表!$E:$E,"Entrega"),0) -> 1 | H23: =IFERROR(SUMIFS(支线运输综合报表!$AO:$AO,支线运输综合报表!$AD:$AD,$A23,支线运输综合报表!$AP:$AP,H$2,支线运输综合报表!$E:$E,"Entrega")/COUNTIFS(支线运输综合报表!$AD:$AD,$A23,支线运输综合报表!$AP:$AP,H$2,支线运输综合报表!$E:$E,"Entrega"),0) -> 0 | I23: =IFERROR(SUMIFS(支线运输综合报表!$AO:$AO,支线运输综合报表!$AD:$AD,$A23,支线运输综合报表!$AP:$AP,I$2,支线运输综合报表!$E:$E,"Entrega")/COUNTIFS(支线运输综合报表!$AD:$AD,$A23,支线运输综合报表!$AP:$AP,I$2,支线运输综合报表!$E:$E,"Entrega"),0) -> 0 | J23: =IFERROR(SUMIFS(支线运输综合报表!$AO:$AO,支线运输综合报表!$AD:$AD,$A23,支线运输综合报表!$AP:$AP,J$2,支线运输综合报表!$E:$E,"Entrega")/COUNTIFS(支线运输综合报表!$AD:$AD,$A23,支线运输综合报表!$AP:$AP,J$2,支线运输综合报表!$E:$E,"Entrega"),0) -> 0 | K23: =IFERROR(SUMIFS(支线运输综合报表!$AO:$AO,支线运输综合报表!$AD:$AD,$A23,支线运输综合报表!$AP:$AP,K$2,支线运输综合报表!$E:$E,"Entrega")/COUNTIFS(支线运输综合报表!$AD:$AD,$A23,支线运输综合报表!$AP:$AP,K$2,支线运输综合报表!$E:$E,"Entrega"),0) -> 0 | ... AH23: =IFERROR(SUMIFS(支线运输综合报表!$AO:$AO,支线运输综合报表!$AD:$AD,$A23,支线运输综合报表!$AP:$AP,AH$2,支线运输综合报表!$E:$E,"Entrega")/COUNTIFS(支线运输综合报表!$AD:$AD,$A23,支线运输综合报表!$AP:$AP,AH$2,支线运输综合报表!$E:$E,"Entrega"),0) -> 0

Sheet 数据源A base de dados
